Workbook
Name averageFX_period: INPUTS!$B$13
Name BS_descr: INPUTS!$B$12
Name CFS_Descr: INPUTS!$B$15
Name comp_period_1: INPUTS!$B$8
Name comp_period_2: INPUTS!$B$9
Name company_name: INPUTS!$B$6
Name currentperiod_end_date: INPUTS!$B$7
Name currentperiod_year: INPUTS!$B$12
Name IFRS_adopt: INPUTS!$B$10
Name IFRS_adoptdate: INPUTS!$B$10
Name IS_Descr: INPUTS!$B$13
Name period: INPUTS!$B$11
Name periodend_spotFX: INPUTS!$B$14
Name priorperiod_end_date: INPUTS!$B$8
Name proforma_date: INPUTS!$B$10
Name SOCE_descr: INPUTS!$B$14

Sheet Dashboard
C1: Current Period | E1: Comparative Period
A3: Balance sheet balancing check | C3: =#REF! -> #REF! | E3: =#REF! -> #REF!
A4: SOCE - Share capital | C4: =#REF! -> #REF! | E4: =#REF! -> #REF!
A5: SOCE - Contributed surplus | C5: =#REF! -> #REF! | E5: =#REF! -> #REF!
A6: SOCE - AOCI | C6: =#REF! -> #REF! | E6: =#REF! -> #REF!
A7: SOCE - Accumulated deficit | C7: =#REF! -> #REF! | E7: =#REF! -> #REF!
A8: SOCE - NCI | C8: =#REF! -> #REF! | E8: =#REF! -> #REF!
A9: SOCE - Total equity | C9: =#REF! -> #REF! | E9: =#REF! -> #REF!

Sheet FS.PRO
A1: =company_name -> Consolidated Hallor Group Inc.
A2: Proforma Financial Statements
A5: Consolidated Working Capital >> | C5: =C20-C37 -> 2036560 | E5: =E20-E37 -> 1645025 | G5: =G20-G37 -> 238317 | I5: =I20-I37 -> 6425422 | K5: =K20-K37 -> 18191186
C7: Consolidated | E7: Consolidated | G7: Consolidated | I7: Consolidated | K7: Hallor Group
C8: 46203 | E8: =EOMONTH(C8,12) -> 46568 | G8: =EOMONTH(E8,12) -> 46934 | I8: =EOMONTH(G8,12) -> 47299 | K8: =EOMONTH(I8,12) -> 47664
A9: =BS_descr -> Statement of Financial Position
C10: =C8 -> 46203 | E10: =E8 -> 46568 | G10: =G8 -> 46934 | I10: =I8 -> 47299 | K10: =K8 -> 47664
A11: ASSETS
A12: Current assets
A13: Cash | B13: $ | C13: =SUMIF(BS.PRO!$AK:$AK,$A13,BS.PRO!L:L) -> 1942431 | D13: $ | E13: =SUMIF(BS.PRO!$AK:$AK,$A13,BS.PRO!R:R) -> 1813362 | F13: $ | G13: =SUMIF(BS.PRO!$AK:$AK,$A13,BS.PRO!X:X) -> 1408703 | H13: $ | I13: =SUMIF(BS.PRO!$AK:$AK,$A13,BS.PRO!AD:AD) -> 9856641 | J13: $ | K13: =SUMIF(BS.PRO!$AK:$AK,$A13,BS.PRO!AJ:AJ) -> 25432405
A14: Receivables | C14: =SUMIF(BS.PRO!$AK:$AK,$A14,BS.PRO!L:L) -> 18 | E14: =SUMIF(BS.PRO!$AK:$AK,$A14,BS.PRO!R:R) -> 18 | G14: =SUMIF(BS.PRO!$AK:$AK,$A14,BS.PRO!X:X) -> 18 | I14: =SUMIF(BS.PRO!$AK:$AK,$A14,BS.PRO!AD:AD) -> 18 | K14: =SUMIF(BS.PRO!$AK:$AK,$A14,BS.PRO!AJ:AJ) -> 18
A15: Prepaid expenses | C15: =SUMIF(BS.PRO!$AK:$AK,$A15,BS.PRO!L:L) -> 0 | E15: =SUMIF(BS.PRO!$AK:$AK,$A15,BS.PRO!R:R) -> 0 | G15: =SUMIF(BS.PRO!$AK:$AK,$A15,BS.PRO!X:X) -> 0 | I15: =SUMIF(BS.PRO!$AK:$AK,$A15,BS.PRO!AD:AD) -> 0 | K15: =SUMIF(BS.PRO!$AK:$AK,$A15,BS.PRO!AJ:AJ) -> 0
A16: Sales tax receivable | C16: =SUMIF(BS.PRO!$AK:$AK,$A16,BS.PRO!L:L) -> 0 | E16: =SUMIF(BS.PRO!$AK:$AK,$A16,BS.PRO!R:R) -> 0 | G16: =SUMIF(BS.PRO!$AK:$AK,$A16,BS.PRO!X:X) -> 0 | I16: =SUMIF(BS.PRO!$AK:$AK,$A16,BS.PRO!AD:AD) -> 0 | K16: =SUMIF(BS.PRO!$AK:$AK,$A16,BS.PRO!AJ:AJ) -> 0
A17: Inventory | C17: =SUMIF(BS.PRO!$AK:$AK,$A17,BS.PRO!L:L) -> 159517 | E17: =SUMIF(BS.PRO!$AK:$AK,$A17,BS.PRO!R:R) -> 602850 | G17: =SUMIF(BS.PRO!$AK:$AK,$A17,BS.PRO!X:X) -> 2142850 | I17: =SUMIF(BS.PRO!$AK:$AK,$A17,BS.PRO!AD:AD) -> 5269517 | K17: =SUMIF(BS.PRO!$AK:$AK,$A17,BS.PRO!AJ:AJ) -> 10309517
A18: Due from related parties | C18: =SUMIF(BS.PRO!$AK:$AK,$A18,BS.PRO!L:L) -> 0 | E18: =SUMIF(BS.PRO!$AK:$AK,$A18,BS.PRO!R:R) -> 0 | G18: =SUMIF(BS.PRO!$AK:$AK,$A18,BS.PRO!X:X) -> 0 | I18: =SUMIF(BS.PRO!$AK:$AK,$A18,BS.PRO!AD:AD) -> 0 | K18: =SUMIF(BS.PRO!$AK:$AK,$A18,BS.PRO!AJ:AJ) -> 0
A19: Current portion of loan receivable | C19: =SUMIF(BS.PRO!$AK:$AK,$A19,BS.PRO!L:L) -> 0 | E19: =SUMIF(BS.PRO!$AK:$AK,$A19,BS.PRO!R:R) -> 0 | G19: =SUMIF(BS.PRO!$AK:$AK,$A19,BS.PRO!X:X) -> 0 | I19: =SUMIF(BS.PRO!$AK:$AK,$A19,BS.PRO!AD:AD) -> 0 | K19: =SUMIF(BS.PRO!$AK:$AK,$A19,BS.PRO!AJ:AJ) -> 0
A20: Total current assets | B20: $ | C20: =SUM(C13:C19) -> 2101966 | D20: $ | E20: =SUM(E13:E19) -> 2416230 | F20: $ | G20: =SUM(G13:G19) -> 3551571 | H20: $ | I20: =SUM(I13:I19) -> 15126176 | J20: $ | K20: =SUM(K13:K19) -> 35741940
A21: Non-current assets
A23: Equipment | C23: =SUMIF(BS.PRO!$AK:$AK,$A23,BS.PRO!L:L) -> 3442 | E23: =SUMIF(BS.PRO!$AK:$AK,$A23,BS.PRO!R:R) -> 3442 | G23: =SUMIF(BS.PRO!$AK:$AK,$A23,BS.PRO!X:X) -> 3442 | I23: =SUMIF(BS.PRO!$AK:$AK,$A23,BS.PRO!AD:AD) -> 3442 | K23: =SUMIF(BS.PRO!$AK:$AK,$A23,BS.PRO!AJ:AJ) -> 3442
A24: Intangible assets | C24: =SUMIF(BS.PRO!$AK:$AK,$A24,BS.PRO!L:L) -> 3015078 | E24: =SUMIF(BS.PRO!$AK:$AK,$A24,BS.PRO!R:R) -> 1758714 | G24: =SUMIF(BS.PRO!$AK:$AK,$A24,BS.PRO!X:X) -> 502350 | I24: =SUMIF(BS.PRO!$AK:$AK,$A24,BS.PRO!AD:AD) -> 314091 | K24: =SUMIF(BS.PRO!$AK:$AK,$A24,BS.PRO!AJ:AJ) -> 314091
A25: Goodwill | C25: =SUMIF(BS.PRO!$AK:$AK,$A25,BS.PRO!L:L) -> 0 | E25: =SUMIF(BS.PRO!$AK:$AK,$A25,BS.PRO!R:R) -> 0 | G25: =SUMIF(BS.PRO!$AK:$AK,$A25,BS.PRO!X:X) -> 0 | I25: =SUMIF(BS.PRO!$AK:$AK,$A25,BS.PRO!AD:AD) -> 0 | K25: =SUMIF(BS.PRO!$AK:$AK,$A25,BS.PRO!AJ:AJ) -> 0
A26: Total non-current assets | B26: $ | C26: =SUM(C23:C25) -> 3018520 | D26: $ | E26: =SUM(E23:E25) -> 1762156 | F26: $ | G26: =SUM(G23:G25) -> 505792 | H26: $ | I26: =SUM(I23:I25) -> 317533 | J26: $ | K26: =SUM(K23:K25) -> 317533
A27: Total Assets | B27: $ | C27: =SUM(C20,C26) -> 5120486 | D27: $ | E27: =SUM(E20,E26) -> 4178386 | F27: $ | G27: =SUM(G20,G26) -> 4057363 | H27: $ | I27: =SUM(I20,I26) -> 15443709 | J27: $ | K27: =SUM(K20,K26) -> 36059473
A28: LIABILITIES
A29: Current liabilities
A30: Accounts payables and accrued liabilities | C30: =-SUMIF(BS.PRO!$AK:$AK,$A30,BS.PRO!L:L) -> 0 | E30: =-SUMIF(BS.PRO!$AK:$AK,$A30,BS.PRO!R:R) -> 0 | G30: =-SUMIF(BS.PRO!$AK:$AK,$A30,BS.PRO!X:X) -> 0 | I30: =-SUMIF(BS.PRO!$AK:$AK,$A30,BS.PRO!AD:AD) -> 0 | K30: =-SUMIF(BS.PRO!$AK:$AK,$A30,BS.PRO!AJ:AJ) -> 0
A31: Accrued Warranty Liability | C31: =-SUMIF(BS.PRO!$AK:$AK,$A31,BS.PRO!L:L) -> 64506 | E31: =-SUMIF(BS.PRO!$AK:$AK,$A31,BS.PRO!R:R) -> 176555 | G31: =-SUMIF(BS.PRO!$AK:$AK,$A31,BS.PRO!X:X) -> 656104 | I31: =-SUMIF(BS.PRO!$AK:$AK,$A31,BS.PRO!AD:AD) -> 1856104 | K31: =-SUMIF(BS.PRO!$AK:$AK,$A31,BS.PRO!AJ:AJ) -> 3956104
A32: Convertible debt | C32: =-SUMIF(BS.PRO!$AK:$AK,$A32,BS.PRO!L:L) -> 0 | E32: =-SUMIF(BS.PRO!$AK:$AK,$A32,BS.PRO!R:R) -> 0 | G32: =-SUMIF(BS.PRO!$AK:$AK,$A32,BS.PRO!X:X) -> 0 | I32: =-SUMIF(BS.PRO!$AK:$AK,$A32,BS.PRO!AD:AD) -> 0 | K32: =-SUMIF(BS.PRO!$AK:$AK,$A32,BS.PRO!AJ:AJ) -> 0
A33: Deferred revenue | C33: =-SUMIF(BS.PRO!$AK:$AK,$A33,BS.PRO!L:L) -> 0 | E33: =-SUMIF(BS.PRO!$AK:$AK,$A33,BS.PRO!R:R) -> 593750 | G33: =-SUMIF(BS.PRO!$AK:$AK,$A33,BS.PRO!X:X) -> 2656250 | I33: =-SUMIF(BS.PRO!$AK:$AK,$A33,BS.PRO!AD:AD) -> 6843750 | K33: =-SUMIF(BS.PRO!$AK:$AK,$A33,BS.PRO!AJ:AJ) -> 13593750
A34: Due to related parties | C34: =-SUMIF(BS.PRO!$AK:$AK,$A34,BS.PRO!L:L) -> 900 | E34: =-SUMIF(BS.PRO!$AK:$AK,$A34,BS.PRO!R:R) -> 900 | G34: =-SUMIF(BS.PRO!$AK:$AK,$A34,BS.PRO!X:X) -> 900 | I34: =-SUMIF(BS.PRO!$AK:$AK,$A34,BS.PRO!AD:AD) -> 900 | K34: =-SUMIF(BS.PRO!$AK:$AK,$A34,BS.PRO!AJ:AJ) -> 900
A35: Income tax payable | C35: =-SUMIF(BS.PRO!$AK:$AK,$A35,BS.PRO!L:L) -> 0 | E35: =-SUMIF(BS.PRO!$AK:$AK,$A35,BS.PRO!R:R) -> 0 | G35: =-SUMIF(BS.PRO!$AK:$AK,$A35,BS.PRO!X:X) -> 0 | I35: =-SUMIF(BS.PRO!$AK:$AK,$A35,BS.PRO!AD:AD) -> 0 | K35: =-SUMIF(BS.PRO!$AK:$AK,$A35,BS.PRO!AJ:AJ) -> 0
A36: Sales tax payable | C36: =-SUMIF(BS.PRO!$AK:$AK,$A36,BS.PRO!L:L) -> 0 | E36: =-SUMIF(BS.PRO!$AK:$AK,$A36,BS.PRO!R:R) -> 0 | G36: =-SUMIF(BS.PRO!$AK:$AK,$A36,BS.PRO!X:X) -> 0 | I36: =-SUMIF(BS.PRO!$AK:$AK,$A36,BS.PRO!AD:AD) -> 0 | K36: =-SUMIF(BS.PRO!$AK:$AK,$A36,BS.PRO!AJ:AJ) -> 0
A37: Total current liabilities | B37: $ | C37: =SUM(C30:C36) -> 65406 | D37: $ | E37: =SUM(E30:E36) -> 771205 | F37: $ | G37: =SUM(G30:G36) -> 3313254 | H37: $ | I37: =SUM(I30:I36) -> 8700754 | J37: $ | K37: =SUM(K30:K36) -> 17550754
A38: Non-current liabilities
A39: Loans and borrowings | C39: =-SUMIF(BS.PRO!$AK:$AK,$A39,BS.PRO!L:L) -> 3000000 | E39: =-SUMIF(BS.PRO!$AK:$AK,$A39,BS.PRO!R:R) -> 3000000 | G39: =-SUMIF(BS.PRO!$AK:$AK,$A39,BS.PRO!X:X) -> 0 | I39: =-SUMIF(BS.PRO!$AK:$AK,$A39,BS.PRO!AD:AD) -> 0 | K39: =-SUMIF(BS.PRO!$AK:$AK,$A39,BS.PRO!AJ:AJ) -> 0
A40: Total Liabilities | B40: $ | C40: =SUM(C37:C39) -> 3065406 | D40: $ | E40: =SUM(E37:E39) -> 3771205 | F40: $ | G40: =SUM(G37:G39) -> 3313254 | H40: $ | I40: =SUM(I37:I39) -> 8700754 | J40: $ | K40: =SUM(K37:K39) -> 17550754
A41: EQUITY
A42: Share capital | B42: $ | C42: =-SUMIF(BS.PRO!$AK:$AK,$A42,BS.PRO!L:L) -> 8555220 | D42: $ | E42: =-SUMIF(BS.PRO!$AK:$AK,$A42,BS.PRO!R:R) -> 8555220 | F42: $ | G42: =-SUMIF(BS.PRO!$AK:$AK,$A42,BS.PRO!X:X) -> 8555220 | H42: $ | I42: =-SUMIF(BS.PRO!$AK:$AK,$A42,BS.PRO!AD:AD) -> 8555220 | J42: $ | K42: =-SUMIF(BS.PRO!$AK:$AK,$A42,BS.PRO!AJ:AJ) -> 8555220
A43: Contributed surplus | C43: =-SUMIF(BS.PRO!$AK:$AK,$A43,BS.PRO!L:L) -> 308750 | E43: =-SUMIF(BS.PRO!$AK:$AK,$A43,BS.PRO!R:R) -> 308750 | G43: =-SUMIF(BS.PRO!$AK:$AK,$A43,BS.PRO!X:X) -> 308750 | I43: =-SUMIF(BS.PRO!$AK:$AK,$A43,BS.PRO!AD:AD) -> 308750 | K43: =-SUMIF(BS.PRO!$AK:$AK,$A43,BS.PRO!AJ:AJ) -> 308750
A44: Accumulated deficit | C44: =-SUMIF(BS.PRO!$AM:$AM,$A44,BS.PRO!L:L) -> -6808890 | E44: =-SUMIF(BS.PRO!$AM:$AM,$A44,BS.PRO!R:R) -> -8456789 | G44: =-SUMIF(BS.PRO!$AM:$AM,$A44,BS.PRO!X:X) -> -8119861 | I44: =-SUMIF(BS.PRO!$AM:$AM,$A44,BS.PRO!AD:AD) -> -2121015 | K44: =-SUMIF(BS.PRO!$AM:$AM,$A44,BS.PRO!AJ:AJ) -> 9644749
A45: Total Shareholders’ (deficit) equity | B45: $ | C45: =SUM(C42:C44) -> 2055080 | D45: $ | E45: =SUM(E42:E44) -> 407181 | F45: $ | G45: =SUM(G42:G44) -> 744109 | H45: $ | I45: =SUM(I42:I44) -> 6742955 | J45: $ | K45: =SUM(K42:K44) -> 18508719
A46: Total Equity | B46: $ | C46: =SUM(C45:C45) -> 2055080 | D46: $ | E46: =SUM(E45:E45) -> 407181 | F46: $ | G46: =SUM(G45:G45) -> 744109 | H46: $ | I46: =SUM(I45:I45) -> 6742955 | J46: $ | K46: =SUM(K45:K45) -> 18508719
A47: Total Liabilities and equity | B47: $ | C47: =SUM(C40,C46) -> 5120486 | D47: $ | E47: =SUM(E40,E46) -> 4178386 | F47: $ | G47: =SUM(G40,G46) -> 4057363 | H47: $ | I47: =SUM(I40,I46) -> 15443709 | J47: $ | K47: =SUM(K40,K46) -> 36059473
A49: Balance CHECK | C49: =C27-C47 -> 0 | E49: =E27-E47 -> 0 | G49: =G27-G47 -> 0 | I49: =I27-I47 -> 0 | K49: =K27-K47 -> 0
A51: =company_name -> Consolidated Hallor Group Inc.
C52: =C57/C55 -> 0.25206774 | E52: =E57/E55 -> 0.25333328 | G52: =G57/G55 -> 0.25333333 | I52: =I57/I55 -> 0.25333334 | K52: =K57/K55 -> 0.25333333
A53: =IS_Descr -> Statement of Loss and Comprehensive Loss | C53: =_xlfn.XLOOKUP(INPUTS!$B$3,INPUTS!$A$16:$A$19,INPUTS!$B$16:$B$19,"n/a",0,1) -> year ended | E53: =C53 -> year ended | G53: =E53 -> year ended | I53: =G53 -> year ended | K53: =I53 -> year ended
C54: =C8 -> 46203 | E54: =E8 -> 46568 | G54: =G8 -> 46934 | I54: =I8 -> 47299 | K54: =K8 -> 47664
A55: Sale of electric vehicle | B55: $ | C55: =-SUMIF(BS.PRO!$AL:$AL,$A55,BS.PRO!L:L) -> 507800 | D55: $ | E55: =-SUMIF(BS.PRO!$AL:$AL,$A55,BS.PRO!R:R) -> 6531250 | F55: $ | G55: =-SUMIF(BS.PRO!$AL:$AL,$A55,BS.PRO!X:X) -> 29812500 | H55: $ | I55: =-SUMIF(BS.PRO!$AL:$AL,$A55,BS.PRO!AD:AD) -> 70812500 | J55: $ | K55: =-SUMIF(BS.PRO!$AL:$AL,$A55,BS.PRO!AJ:AJ) -> 124500000
A56: Cost of goods sold | C56: =-SUMIF(BS.PRO!AL:AL,A56,BS.PRO!L:L) -> -379800 | E56: =-SUMIF(BS.PRO!$AL:$AL,$A56,BS.PRO!R:R) -> -4876667 | G56: =-SUMIF(BS.PRO!$AL:$AL,$A56,BS.PRO!X:X) -> -22260000 | I56: =-SUMIF(BS.PRO!$AL:$AL,$A56,BS.PRO!AD:AD) -> -52873333 | K56: =-SUMIF(BS.PRO!$AL:$AL,$A56,BS.PRO!AJ:AJ) -> -92960000
A57: Net profit | B57: $ | C57: =SUM(C55:C56) -> 128000 | D57: $ | E57: =SUM(E55:E56) -> 1654583 | F57: $ | G57: =SUM(G55:G56) -> 7552500 | H57: $ | I57: =SUM(I55:I56) -> 17939167 | J57: $ | K57: =SUM(K55:K56) -> 31540000
A59: Operating expenses
A60: Bank fees | B60: $ | C60: =SUMIF(BS.PRO!$AL:$AL,$A60,BS.PRO!L:L) -> 2074 | D60: $ | E60: =SUMIF(BS.PRO!$AL:$AL,$A60,BS.PRO!R:R) -> 2514 | F60: $ | G60: =SUMIF(BS.PRO!$AL:$AL,$A60,BS.PRO!X:X) -> 2639 | H60: $ | I60: =SUMIF(BS.PRO!$AL:$AL,$A60,BS.PRO!AD:AD) -> 2772 | J60: $ | K60: =SUMIF(BS.PRO!$AL:$AL,$A60,BS.PRO!AJ:AJ) -> 2910
A61: Professional fees | C61: =SUMIF(BS.PRO!$AL:$AL,$A61,BS.PRO!L:L) -> 111500 | E61: =SUMIF(BS.PRO!$AL:$AL,$A61,BS.PRO!R:R) -> 90000 | G61: =SUMIF(BS.PRO!$AL:$AL,$A61,BS.PRO!X:X) -> 90000 | I61: =SUMIF(BS.PRO!$AL:$AL,$A61,BS.PRO!AD:AD) -> 108000 | K61: =SUMIF(BS.PRO!$AL:$AL,$A61,BS.PRO!AJ:AJ) -> 129600
A62: Consulting expense | C62: =SUMIF(BS.PRO!$AL:$AL,$A62,BS.PRO!L:L) -> 273417 | E62: =SUMIF(BS.PRO!$AL:$AL,$A62,BS.PRO!R:R) -> 276000 | G62: =SUMIF(BS.PRO!$AL:$AL,$A62,BS.PRO!X:X) -> 276000 | I62: =SUMIF(BS.PRO!$AL:$AL,$A62,BS.PRO!AD:AD) -> 276000 | K62: =SUMIF(BS.PRO!$AL:$AL,$A62,BS.PRO!AJ:AJ) -> 276000
A63: Dues, licenses, and permits | C63: =SUMIF(BS.PRO!$AL:$AL,$A63,BS.PRO!L:L) -> 2194 | E63: =SUMIF(BS.PRO!$AL:$AL,$A63,BS.PRO!R:R) -> 1812 | G63: =SUMIF(BS.PRO!$AL:$AL,$A63,BS.PRO!X:X) -> 1849 | I63: =SUMIF(BS.PRO!$AL:$AL,$A63,BS.PRO!AD:AD) -> 1886 | K63: =SUMIF(BS.PRO!$AL:$AL,$A63,BS.PRO!AJ:AJ) -> 1923
A64: Advertising and marketing | C64: =SUMIF(BS.PRO!$AL:$AL,$A64,BS.PRO!L:L) -> 78640 | E64: =SUMIF(BS.PRO!$AL:$AL,$A64,BS.PRO!R:R) -> 434250 | G64: =SUMIF(BS.PRO!$AL:$AL,$A64,BS.PRO!X:X) -> 1671750 | I64: =SUMIF(BS.PRO!$AL:$AL,$A64,BS.PRO!AD:AD) -> 3828000 | K64: =SUMIF(BS.PRO!$AL:$AL,$A64,BS.PRO!AJ:AJ) -> 6640500
A65: Meals and entertainment | C65: =SUMIF(BS.PRO!$AL:$AL,$A65,BS.PRO!L:L) -> 3000 | E65: =SUMIF(BS.PRO!$AL:$AL,$A65,BS.PRO!R:R) -> 3300 | G65: =SUMIF(BS.PRO!$AL:$AL,$A65,BS.PRO!X:X) -> 3630 | I65: =SUMIF(BS.PRO!$AL:$AL,$A65,BS.PRO!AD:AD) -> 3993 | K65: =SUMIF(BS.PRO!$AL:$AL,$A65,BS.PRO!AJ:AJ) -> 4392
A66: Travel expenses | C66: =SUMIF(BS.PRO!$AL:$AL,$A66,BS.PRO!L:L) -> 6000 | E66: =SUMIF(BS.PRO!$AL:$AL,$A66,BS.PRO!R:R) -> 6600 | G66: =SUMIF(BS.PRO!$AL:$AL,$A66,BS.PRO!X:X) -> 7260 | I66: =SUMIF(BS.PRO!$AL:$AL,$A66,BS.PRO!AD:AD) -> 7986 | K66: =SUMIF(BS.PRO!$AL:$AL,$A66,BS.PRO!AJ:AJ) -> 8785
A67: Transfer agent and regulatory expenses | C67: =SUMIF(BS.PRO!$AL:$AL,$A67,BS.PRO!L:L) -> 9000 | E67: =SUMIF(BS.PRO!$AL:$AL,$A67,BS.PRO!R:R) -> 9450 | G67: =SUMIF(BS.PRO!$AL:$AL,$A67,BS.PRO!X:X) -> 9923 | I67: =SUMIF(BS.PRO!$AL:$AL,$A67,BS.PRO!AD:AD) -> 10419 | K67: =SUMIF(BS.PRO!$AL:$AL,$A67,BS.PRO!AJ:AJ) -> 10940
A68: Insurance | C68: =SUMIF(BS.PRO!$AL:$AL,$A68,BS.PRO!L:L) -> 30204 | E68: =SUMIF(BS.PRO!$AL:$AL,$A68,BS.PRO!R:R) -> 31500 | G68: =SUMIF(BS.PRO!$AL:$AL,$A68,BS.PRO!X:X) -> 33075 | I68: =SUMIF(BS.PRO!$AL:$AL,$A68,BS.PRO!AD:AD) -> 34729 | K68: =SUMIF(BS.PRO!$AL:$AL,$A68,BS.PRO!AJ:AJ) -> 36465
A69: Office expenses | C69: =SUMIF(BS.PRO!$AL:$AL,$A69,BS.PRO!L:L) -> 24589 | E69: =SUMIF(BS.PRO!$AL:$AL,$A69,BS.PRO!R:R) -> 26400 | G69: =SUMIF(BS.PRO!$AL:$AL,$A69,BS.PRO!X:X) -> 29040 | I69: =SUMIF(BS.PRO!$AL:$AL,$A69,BS.PRO!AD:AD) -> 31944 | K69: =SUMIF(BS.PRO!$AL:$AL,$A69,BS.PRO!AJ:AJ) -> 35138
A70: Selling expense | C70: =SUMIF(BS.PRO!$AL:$AL,$A70,BS.PRO!L:L) -> 0 | E70: =SUMIF(BS.PRO!$AL:$AL,$A70,BS.PRO!R:R) -> 60000 | G70: =SUMIF(BS.PRO!$AL:$AL,$A70,BS.PRO!X:X) -> 1275000 | I70: =SUMIF(BS.PRO!$AL:$AL,$A70,BS.PRO!AD:AD) -> 3000000 | K70: =SUMIF(BS.PRO!$AL:$AL,$A70,BS.PRO!AJ:AJ) -> 5250000
A71: Shipping expense | C71: =SUMIF(BS.PRO!$AL:$AL,$A71,BS.PRO!L:L) -> 6000 | E71: =SUMIF(BS.PRO!$AL:$AL,$A71,BS.PRO!R:R) -> 142500 | G71: =SUMIF(BS.PRO!$AL:$AL,$A71,BS.PRO!X:X) -> 637500 | I71: =SUMIF(BS.PRO!$AL:$AL,$A71,BS.PRO!AD:AD) -> 1500000 | K71: =SUMIF(BS.PRO!$AL:$AL,$A71,BS.PRO!AJ:AJ) -> 2625000
A72: Shop supplies | C72: =SUMIF(BS.PRO!$AL:$AL,$A72,BS.PRO!L:L) -> 3633 | E72: =SUMIF(BS.PRO!$AL:$AL,$A72,BS.PRO!R:R) -> 86292 | G72: =SUMIF(BS.PRO!$AL:$AL,$A72,BS.PRO!X:X) -> 386042 | I72: =SUMIF(BS.PRO!$AL:$AL,$A72,BS.PRO!AD:AD) -> 908333 | K72: =SUMIF(BS.PRO!$AL:$AL,$A72,BS.PRO!AJ:AJ) -> 1589583
... A77: Research and development | C77: =SUMIF(BS.PRO!$AL:$AL,$A77,BS.PRO!L:L) -> 0 | E77: =SUMIF(BS.PRO!$AL:$AL,$A77,BS.PRO!R:R) -> 310000 | G77: =SUMIF(BS.PRO!$AL:$AL,$A77,BS.PRO!X:X) -> 310000 | I77: =SUMIF(BS.PRO!$AL:$AL,$A77,BS.PRO!AD:AD) -> 310000 | K77: =SUMIF(BS.PRO!$AL:$AL,$A77,BS.PRO!AJ:AJ) -> 310000
A79: Total operating expenses | B79: $ | C79: =-SUM(C60:C78) -> -1828302 | D79: $ | E79: =-SUM(E60:E78) -> -2942482 | F79: $ | G79: =-SUM(G60:G78) -> -6855572 | H79: $ | I79: =-SUM(I60:I78) -> -11940321 | J79: $ | K79: =-SUM(K60:K78) -> -19774236
A80: Operating income / (loss) | B80: $ | C80: =SUM(C57,C79) -> -1700302 | D80: $ | E80: =SUM(E57,E79) -> -1287899 | F80: $ | G80: =SUM(G57,G79) -> 696928 | H80: $ | I80: =SUM(I57,I79) -> 5998846 | J80: $ | K80: =SUM(K57,K79) -> 11765764
A81: Other income (expenses)
A82: Other income | C82: =-SUMIF(BS.PRO!$AL:$AL,$A82,BS.PRO!L:L) -> 47085 | E82: =-SUMIF(BS.PRO!$AL:$AL,$A82,BS.PRO!R:R) -> 0 | G82: =-SUMIF(BS.PRO!$AL:$AL,$A82,BS.PRO!X:X) -> 0 | I82: =-SUMIF(BS.PRO!$AL:$AL,$A82,BS.PRO!AD:AD) -> 0 | K82: =-SUMIF(BS.PRO!$AL:$AL,$A82,BS.PRO!AJ:AJ) -> 0
A83: Interest income | C83: =-SUMIF(BS.PRO!$AL:$AL,$A83,BS.PRO!L:L) -> 0 | E83: =-SUMIF(BS.PRO!$AL:$AL,$A83,BS.PRO!R:R) -> 0 | G83: =-SUMIF(BS.PRO!$AL:$AL,$A83,BS.PRO!X:X) -> 0 | I83: =-SUMIF(BS.PRO!$AL:$AL,$A83,BS.PRO!AD:AD) -> 0 | K83: =-SUMIF(BS.PRO!$AL:$AL,$A83,BS.PRO!AJ:AJ) -> 0
A84: Net financial expenses | C84: =-SUMIF(BS.PRO!$AL:$AL,$A84,BS.PRO!L:L) -> -36210 | E84: =-SUMIF(BS.PRO!$AL:$AL,$A84,BS.PRO!R:R) -> 0 | G84: =-SUMIF(BS.PRO!$AL:$AL,$A84,BS.PRO!X:X) -> 0 | I84: =-SUMIF(BS.PRO!$AL:$AL,$A84,BS.PRO!AD:AD) -> 0 | K84: =-SUMIF(BS.PRO!$AL:$AL,$A84,BS.PRO!AJ:AJ) -> 0
A85: Accretion expense | C85: =-SUMIF(BS.PRO!$AL:$AL,$A85,BS.PRO!L:L) -> 0 | E85: =-SUMIF(BS.PRO!$AL:$AL,$A85,BS.PRO!R:R) -> 0 | G85: =-SUMIF(BS.PRO!$AL:$AL,$A85,BS.PRO!X:X) -> 0 | I85: =-SUMIF(BS.PRO!$AL:$AL,$A85,BS.PRO!AD:AD) -> 0 | K85: =-SUMIF(BS.PRO!$AL:$AL,$A85,BS.PRO!AJ:AJ) -> 0
A86: Interest expense | C86: =-SUMIF(BS.PRO!$AL:$AL,$A86,BS.PRO!L:L) -> -141773 | E86: =-SUMIF(BS.PRO!$AL:$AL,$A86,BS.PRO!R:R) -> -360000 | G86: =-SUMIF(BS.PRO!$AL:$AL,$A86,BS.PRO!X:X) -> -360000 | I86: =-SUMIF(BS.PRO!$AL:$AL,$A86,BS.PRO!AD:AD) -> 0 | K86: =-SUMIF(BS.PRO!$AL:$AL,$A86,BS.PRO!AJ:AJ) -> 0
A87: Loss before tax | B87: $ | C87: =SUM(C80:C86) -> -1831200 | D87: $ | E87: =SUM(E80:E86) -> -1647899 | F87: $ | G87: =SUM(G80:G86) -> 336928 | H87: $ | I87: =SUM(I80:I86) -> 5998846 | J87: $ | K87: =SUM(K80:K86) -> 11765764
A88: Current tax recovery (expense) | C88: =SUMIF('IS - F25'!N:N,FS.1!A70,'IS - F25'!M:M) -> 0
A89: Deferred tax recovery (expense) | C89: =SUMIF('IS - F25'!N:N,FS.1!A71,'IS - F25'!M:M) -> 0
A90: Net income / (loss) for the year | B90: $ | C90: =SUM(C87:C89) -> -1831200 | D90: $ | E90: =SUM(E87:E89) -> -1647899 | F90: $ | G90: =SUM(G87:G89) -> 336928 | H90: $ | I90: =SUM(I87:I89) -> 5998846 | J90: $ | K90: =SUM(K87:K89) -> 11765764
A91: Comprehensive income / (loss) for the year | B91: $ | C91: =SUM(C90:C90) -> -1831200 | D91: $ | E91: =SUM(E90:E90) -> -1647899 | F91: $ | G91: =SUM(G90:G90) -> 336928 | H91: $ | I91: =SUM(I90:I90) -> 5998846 | J91: $ | K91: =SUM(K90:K90) -> 11765764
A93: CHECK | C93: =BS.PRO!L4+C91 -> 0 | E93: =BS.PRO!R4+E91 -> 0 | G93: =BS.PRO!X4+G91 -> 0 | I93: =BS.PRO!AD4+I91 -> 0 | K93: =BS.PRO!AJ4+K91 -> 0
A97: =company_name -> Consolidated Hallor Group Inc.
A98: =SOCE_descr -> Statements of Changes in Shareholders's Equity
C99: Share capital | E99: Contributed Surplus | G99: Accumulated Deficit | I99: Total equity
A100: Balance - June 30, 2024 | B100: $ | C100: =FS.1!C92 -> 8224099 | D100: $ | E100: =FS.1!E92 -> 308750 | F100: $ | G100: -3067490 | H100: $ | I100: =ROUND(SUM(C100:G100),0) -> 5465359
A101: Net loss for year | C101: =FS.1!C95 -> 0 | E101: =FS.1!E95 -> 0 | G101: =-BS.PRO!F4-38490 -> -1910200 | I101: =ROUND(SUM(C101:G101),0) -> -1910200
A102: ="Balance - "&TEXT(currentperiod_end_date,"MMMM D, YYYY") -> Balance - June 30, 2025 | B102: $ | C102: =ROUND(SUM(C100:C101),0) -> 8224099 | D102: $ | E102: =ROUND(SUM(E100:E101),0) -> 308750 | F102: $ | G102: =ROUND(SUM(G100:G101),0) -> -4977690 | I102: =ROUND(SUM(I100:I101),0) -> 3555159
A103: Conversion of convertible debt to common shares | C103: =-BS.PRO!J88 -> 331121 | I103: =ROUND(SUM(C103:G103),0) -> 331121
A104: Net loss for year | C104: 0 | E104: 0 | G104: =C91 -> -1831200 | I104: =ROUND(SUM(C104:G104),0) -> -1831200
A105: Balance - June 30, 2026 | B105: $ | C105: =ROUND(SUM(C102:C104),0) -> 8555220 | D105: $ | E105: =ROUND(SUM(E102:E104),0) -> 308750 | F105: $ | G105: =ROUND(SUM(G102:G104),0) -> -6808890 | I105: =ROUND(SUM(I102:I104),0) -> 2055080
A106: Net loss for year | C106: 0 | E106: 0 | G106: =E91 -> -1647899 | I106: =ROUND(SUM(C106:G106),0) -> -1647899
A107: Balance - June 30, 2027 | B107: $ | C107: =ROUND(SUM(C105:C106),0) -> 8555220 | D107: $ | E107: =ROUND(SUM(E105:E106),0) -> 308750 | F107: $ | G107: =ROUND(SUM(G105:G106),0) -> -8456789 | I107: =ROUND(SUM(I105:I106),0) -> 407181
A108: Net income for year | C108: 0 | E108: 0 | G108: =G91 -> 336928 | I108: =ROUND(SUM(C108:G108),0) -> 336928
A109: Balance - June 30, 2028 | B109: $ | C109: =ROUND(SUM(C107:C108),0) -> 8555220 | D109: $ | E109: =ROUND(SUM(E107:E108),0) -> 308750 | F109: $ | G109: =ROUND(SUM(G107:G108),0) -> -8119861 | I109: =ROUND(SUM(I107:I108),0) -> 744109
A110: Net income for year | C110: 0 | E110: 0 | G110: =I91 -> 5998846 | I110: =ROUND(SUM(C110:G110),0) -> 5998846
A111: Balance - June 30, 2029 | B111: $ | C111: =ROUND(SUM(C109:C110),0) -> 8555220 | D111: $ | E111: =ROUND(SUM(E109:E110),0) -> 308750 | F111: $ | G111: =ROUND(SUM(G109:G110),0) -> -2121015 | I111: =ROUND(SUM(I109:I110),0) -> 6742955
A112: Net income for year | C112: 0 | E112: 0 | G112: =K91 -> 11765764 | I112: =ROUND(SUM(C112:G112),0) -> 11765764
A113: Balance - June 30, 2030 | B113: $ | C113: =ROUND(SUM(C111:C112),0) -> 8555220 | D113: $ | E113: =ROUND(SUM(E111:E112),0) -> 308750 | F113: $ | G113: =ROUND(SUM(G111:G112),0) -> 9644749 | I113: =ROUND(SUM(I111:I112),0) -> 18508719
A115: Check - F26 | C115: =C105-C42 -> 0 | E115: =E102-E43 -> 0 | G115: =G105-C44 -> 0 | I115: =I105-C45 -> 0
A116: Check - F27 | C116: =C107-E42 -> 0 | E116: =E107-E43 -> 0 | G116: =G107-E44 -> 0 | I116: =I107-E45 -> 0
A117: Check - F28 | C117: =C109-G42 -> 0 | E117: =E109-G43 -> 0 | G117: =G109-G44 -> 0 | I117: =I109-G45 -> 0
...

Sheet FS.1
A1: =company_name -> Consolidated Hallor Group Inc.
A2: Financial Statements
A5: Consolidated Working Capital >> | C5: =C20-C36 -> -683160 | E5: =E20-E36 -> -67788
C7: Consolidated | E7: Hallor Group | T7: META DATA BELOW - DO NOT EDIT
C8: =TEXT(currentperiod_end_date, "MMMM DD, YYYY") -> June 30, 2025 | E8: =TEXT(priorperiod_end_date,"MMMM DD, YYYY") -> June 30, 2024 | T8: =C10 -> June 30, 2025 | U8: =E10 -> June 30, 2024
A9: =BS_descr -> Statement of Financial Position
C10: =C8 -> June 30, 2025 | E10: =E8 -> June 30, 2024 | K10: Change $ | L10: Change % | O10: Movement explanation
A11: ASSETS
A12: Current assets
A13: Cash | B13: $ | C13: =SUMIF('BS.1 - F25'!G:G,FS.1!A13,'BS.1 - F25'!F:F) -> 392 | D13: $ | E13: =SUMIF('BS.2 - F24'!G:G,A13,'BS.2 - F24'!F:F) -> 5604 | K13: =C13-E13 -> -5212 | L13: =IFERROR(K13/E13,0) -> -0.93004996 | O13: Refer to cashflow proof and SCF for movement of cash | T13: 201 | U13: 101
A14: Receivables | C14: =SUMIF('BS.1 - F25'!G:G,FS.1!A14,'BS.1 - F25'!F:F) -> 0 | E14: =SUMIF('BS.2 - F24'!G:G,A14,'BS.2 - F24'!F:F) -> 0 | K14: =C14-E14 -> 0 | L14: =IFERROR(K14/E14,0) -> 0 | O14: Primiarly due to GST rec balance of $26k acquired on acquisition of Hallor Industries; remaining amount due to GST ITCs recognized in Q1 for consolidated group | T14: =IF(C14<>"",MAX(T$13:T13)+1,"") -> 202 | U14: =IF(E14<>"",MAX(U$13:U13)+1,"") -> 102
A15: Prepaid expenses | C15: =SUMIF('BS.1 - F25'!G:G,FS.1!A15,'BS.1 - F25'!F:F) -> 0 | E15: =SUMIF('BS.2 - F24'!G:G,A15,'BS.2 - F24'!F:F) -> 0 | K15: =C15-E15 -> 0 | L15: =IFERROR(K15/E15,0) -> 0 | T15: =IF(C15<>"",MAX(T$13:T14)+1,"") -> 203 | U15: =IF(E15<>"",MAX(U$13:U14)+1,"") -> 103
A16: Sales tax receivable | C16: =SUMIF('BS.1 - F25'!G:G,FS.1!A16,'BS.1 - F25'!F:F) -> 37905 | E16: =SUMIF('BS.2 - F24'!G:G,A16,'BS.2 - F24'!F:F) -> 30450 | K16: =C16-E16 -> 7455 | L16: =IFERROR(K16/E16,0) -> 0.24482759 | T16: =IF(C16<>"",MAX(T$13:T15)+1,"") -> 204 | U16: =IF(E16<>"",MAX(U$13:U15)+1,"") -> 104
A17: Inventory | C17: =SUMIF('BS.1 - F25'!G:G,FS.1!A17,'BS.1 - F25'!F:F) -> 161256 | E17: =SUMIF('BS.2 - F24'!G:G,A17,'BS.2 - F24'!F:F) -> 452364 | K17: =C17-E17 -> -291108 | L17: =IFERROR(K17/E17,1) -> -0.64352601 | O17: From the acquisition of Hallor Industries - was $397,450 on acquisition date; plus additions throughout Q1 | T17: =IF(C17<>"",MAX(T$13:T16)+1,"") -> 205 | U17: =IF(E17<>"",MAX(U$13:U16)+1,"") -> 105
A18: Due from related parties | C18: =SUMIF('BS.1 - F25'!G:G,FS.1!A18,'BS.1 - F25'!F:F) -> 0 | E18: =SUMIF('BS.2 - F24'!G:G,A18,'BS.2 - F24'!F:F) -> 0 | K18: =C18-E18 -> 0 | L18: =IFERROR(K18/E18,0) -> 0 | T18: =IF(C18<>"",MAX(T$13:T17)+1,"") -> 206 | U18: =IF(E18<>"",MAX(U$13:U17)+1,"") -> 106
A19: Current portion of loan receivable | C19: =SUMIF('BS.1 - F25'!G:G,FS.1!A19,'BS.1 - F25'!F:F) -> 0 | E19: =SUMIF('BS.2 - F24'!G:G,A19,'BS.2 - F24'!F:F) -> 0 | K19: =C19-E19 -> 0 | L19: =IFERROR(K19/E19,0) -> 0 | O19: Post-acquisition of Hallor Industries this became an inter-company balance and eliminates on consolidation | T19: =IF(C19<>"",MAX(T$13:T18)+1,"") -> 207 | U19: =IF(E19<>"",MAX(U$13:U18)+1,"") -> 107
A20: Total current assets | B20: $ | C20: =SUM(C13:C19) -> 199553 | D20: $ | E20: =SUM(E13:E19) -> 488418
A21: Non-current assets
A23: Equipment | C23: =SUMIF('BS.1 - F25'!G:G,FS.1!A23,'BS.1 - F25'!F:F) -> 5341 | E23: =SUMIF('BS.2 - F24'!G:G,A23,'BS.2 - F24'!F:F) -> 5341 | K23: =C23-E23 -> 0 | L23: =IFERROR(K23/E23,1) -> 0 | O23: From the acquisition of Hallor Industries - was $6,108 on acquisition date less depreciation | T23: =IF(C23<>"",MAX(T$13:T22)+1,"") -> 208 | U23: =IF(E23<>"",MAX(U$13:U22)+1,"") -> 108
A24: Intangible assets | C24: =SUMIF('BS.1 - F25'!G:G,FS.1!A24,'BS.1 - F25'!F:F) -> 4271442 | E24: =SUMIF('BS.2 - F24'!G:G,A24,'BS.2 - F24'!F:F) -> 5527806 | K24: =C24-E24 -> -1256364 | L24: =IFERROR(K24/E24,1) -> -0.22728077 | O24: From the acquisition of Hallor Industries | T24: =IF(C24<>"",MAX(T$13:T23)+1,"") -> 209 | U24: =IF(E24<>"",MAX(U$13:U23)+1,"") -> 109
A25: Goodwill | C25: =SUMIF('BS.1 - F25'!G:G,FS.1!A25,'BS.1 - F25'!F:F) -> 0 | E25: =SUMIF('BS.2 - F24'!G:G,A25,'BS.2 - F24'!F:F) -> 0 | K25: =C25-E25 -> 0
A26: Total non-current assets | B26: $ | C26: =SUM(C23:C25) -> 4276783 | D26: $ | E26: =SUM(E23:E25) -> 5533147
A27: Total Assets | B27: $ | C27: =SUM(C20,C26) -> 4476336 | D27: $ | E27: =SUM(E20,E26) -> 6021565
A28: LIABILITIES
A29: Current liabilities
A30: Accounts payables and accrued liabilities | C30: =-SUMIF('BS.1 - F25'!G:G,FS.1!A30,'BS.1 - F25'!F:F) -> 603276 | E30: =-SUMIF('BS.2 - F24'!G:G,A30,'BS.2 - F24'!F:F) -> 349791 | K30: =C30-E30 -> 253485 | L30: =IFERROR(K30/E30,1) -> 0.72467559 | O30: Opening bal of $67k from YE: Net accrual increase: $44k for accrued legal (McMillian) and accounitng expenses (MNP) in Hallor Group; Add; $178k of AP assumed on acquisition of Hallor Industries; Net increase in AP of $62k in Hallor Group YTD 6 mths Net decrease in AP of $14k in Hallor industries YTD 6 mths | T30: =IF(C30<>"",MAX(T$13:T29)+1,"") -> 210 | U30: =IF(E30<>"",MAX(U$13:U29)+1,"") -> 110
A31: Warranty liability | C31: =-SUMIF('BS.1 - F25'!G:G,FS.1!A31,'BS.1 - F25'!F:F) -> 0 | E31: =-SUMIF('BS.2 - F24'!G:G,A31,'BS.2 - F24'!F:F) -> 0 | K31: =C31-E31 -> 0 | L31: =IFERROR(K31/E31,0) -> 0 | T31: =IF(C31<>"",MAX(T$13:T30)+1,"") -> 211 | U31: =IF(E31<>"",MAX(U$13:U30)+1,"") -> 111
A32: Convertible debt | C32: =-SUMIF('BS.1 - F25'!G:G,FS.1!A32,'BS.1 - F25'!F:F) -> 274099 | E32: =-SUMIF('BS.2 - F24'!G:G,A32,'BS.2 - F24'!F:F) -> 204577 | K32: =C32-E32 -> 69522 | L32: =IFERROR(K32/E32,1) -> 0.33983292 | O32: $225k of convertible note subscription occurred in Q1; the conversion feature recognized as derivative liability, FV'd first and residual of face-value on note allocated to host debt liability ($150,000). Convertiblenote balance is accreted up and includes interest payable amount. See Tab COV.DEBT for more details | T32: =IF(C32<>"",MAX(T$13:T31)+1,"") -> 212 | U32: =IF(E32<>"",MAX(U$13:U31)+1,"") -> 112
A33: Derivative liability | C33: =-SUMIF('BS.1 - F25'!G:G,FS.1!A33,'BS.1 - F25'!F:F) -> 0 | E33: =-SUMIF('BS.2 - F24'!G:G,A33,'BS.2 - F24'!F:F) -> 0 | K33: =C33-E33 -> 0 | L33: =IFERROR(K33/E33,1) -> 1 | O33: $225k of convertible note subscription occurred in Q1; the conversion feature recognized as derivative liability, FV'd first and residual of face-value on note allocated to host debt liability. Refer to Tab DER.V in this workbook for valuation of derivative. | T33: =IF(C33<>"",MAX(T$13:T32)+1,"") -> 213 | U33: =IF(E33<>"",MAX(U$13:U32)+1,"") -> 113
A34: Income tax payable | C34: =-SUMIF('BS.1 - F25'!G:G,FS.1!A34,'BS.1 - F25'!F:F) -> 0 | E34: =-SUMIF('BS.2 - F24'!G:G,A34,'BS.2 - F24'!F:F) -> 0 | K34: =C34-E34 -> 0 | L34: =IFERROR(K34/E34,0) -> 0 | T34: =IF(C34<>"",MAX(T$13:T33)+1,"") -> 214 | U34: =IF(E34<>"",MAX(U$13:U33)+1,"") -> 114
A35: Due to related parties | C35: =-SUMIF('BS.1 - F25'!G:G,FS.1!A35,'BS.1 - F25'!F:F) -> 5338 | E35: =-SUMIF('BS.2 - F24'!G:G,A35,'BS.2 - F24'!F:F) -> 1838 | K35: =C35-E35 -> 3500 | L35: =IFERROR(K35/E35,0) -> 1.9042437 | T35: =IF(C35<>"",MAX(T$13:T34)+1,"") -> 215 | U35: =IF(E35<>"",MAX(U$13:U34)+1,"") -> 115
A36: Total current liabilities | B36: $ | C36: =SUM(C30:C35) -> 882713 | D36: $ | E36: =SUM(E30:E35) -> 556206
A37: Non-current liabilities
A38: Loans and borrowings | C38: =-SUMIF('BS.1 - F25'!G:G,FS.1!A38,'BS.1 - F25'!F:F) -> 0 | E38: =-SUMIF('BS.2 - F24'!G:G,A38,'BS.2 - F24'!F:F) -> 0 | K38: =C38-E38 -> 0 | L38: =IFERROR(K38/E38,0) -> 0
A39: Total Liabilities | B39: $ | C39: =SUM(C36:C38) -> 882713 | D39: $ | E39: =SUM(E36:E38) -> 556206
A40: EQUITY
A41: Share capital | B41: $ | C41: =-SUMIF('BS.1 - F25'!G:G,FS.1!A41,'BS.1 - F25'!F:F) -> 8224099 | D41: $ | E41: =-SUMIF('BS.2 - F24'!G:G,A41,'BS.2 - F24'!F:F) -> 8224099 | K41: =C41-E41 -> 0 | L41: =IFERROR(K41/E41,0) -> 0 | O41: $6M share consideration to acquire Hallor Industries; $450k finders fee on closing of acquisition | T41: =IF(C41<>"",MAX(T$13:T40)+1,"") -> 216 | U41: =IF(E41<>"",MAX(U$13:U40)+1,"") -> 116
A42: Contributed surplus | C42: =-SUMIF('BS.1 - F25'!G:G,FS.1!A42,'BS.1 - F25'!F:F) -> 308750 | E42: =-SUMIF('BS.2 - F24'!G:G,A42,'BS.2 - F24'!F:F) -> 308750 | K42: =C42-E42 -> 0 | L42: =IFERROR(K42/E42,0) -> 0 | T42: =IF(C42<>"",MAX(T$13:T41)+1,"") -> 217 | U42: =IF(E42<>"",MAX(U$13:U41)+1,"") -> 117
A43: Accumulated deficit | C43: =-SUMIF('BS.1 - F25'!I:I,FS.1!A43,'BS.1 - F25'!F:F) -> -4939226 | E43: =-SUMIF('BS.2 - F24'!I:I,FS.1!A43,'BS.2 - F24'!F:F) -> #REF! | K43: =C43-E43 -> #REF! | L43: =IFERROR(K43/E43,0) -> 0 | O43: Net loss in the period - see P&L variance analysis for details | T43: =IF(C43<>"",MAX(T$13:T42)+1,"") -> 218 | U43: =IF(E43<>"",MAX(U$13:U42)+1,"") -> #REF!
A44: Total Shareholders’ (deficit) equity | B44: $ | C44: =SUM(C41:C43) -> 3593623 | D44: $ | E44: =SUM(E41:E43) -> #REF!
A45: Total Equity | B45: $ | C45: =SUM(C44:C44) -> 3593623 | D45: $ | E45: =SUM(E44:E44) -> #REF!
A46: Total Liabilities and equity | B46: $ | C46: =SUM(C39,C45) -> 4476336 | D46: $ | E46: =SUM(E39,E45) -> #REF!
A48: Balance CHECK | C48: =C27-C46 -> 0 | E48: =E27-E46 -> #REF!
A50: =company_name -> Consolidated Hallor Group Inc.
A52: =IS_Descr -> Statement of Loss and Comprehensive Loss | C52: 3 months | E52: =C52 -> 3 months | G52: =_xlfn.XLOOKUP(INPUTS!$B$3,INPUTS!$A$16:$A$19,INPUTS!$B$16:$B$19,"n/a",0,1) -> year ended | I52: =G52 -> year ended | K52: Change $ | L52: Change % | M52: Change $ | N52: Change %
C53: =C8 -> June 30, 2025 | E53: =TEXT(comp_period_1,"MMMM DD, YYYY") -> June 30, 2024 | G53: =C53 -> June 30, 2025 | I53: =E53 -> June 30, 2024 | K53: 3 months | L53: =K53 -> 3 months | M53: =G52 -> year ended | N53: =M53 -> year ended | O53: Movement explanation
A54: Revenues | B54: $ | D54: $ | F54: $ | G54: =-SUMIF('BS.1 - F25'!G:G,A54,'BS.1 - F25'!F:F) -> 360000 | H54: $ | I54: =-SUMIF('BS.2 - F24'!G:G,FS.1!A54,'BS.2 - F24'!F:F) -> 0 | K54: =C54-E54 -> 0 | L54: =IFERROR(K54/E54,0) -> 0 | M54: =G54-I54 -> 360000 | N54: =IFERROR(M54/I54,0) -> 0 | O54: no movement
A55: Cost of goods sold | G55: =-SUMIF('BS.1 - F25'!G:G,A55,'BS.1 - F25'!F:F) -> -328158 | I55: =-SUMIF('BS.2 - F24'!G:G,FS.1!A55,'BS.2 - F24'!F:F) -> 0 | K55: =G55-I55 -> -328158 | L55: =IFERROR(K55/E55,0) -> 0 | M55: =G55-I55 -> -328158 | N55: =IFERROR(M55/I55,0) -> 0 | O55: no movement
A56: Net profit | B56: $ | D56: $ | F56: $ | G56: =SUM(G54:G55) -> 31842 | H56: $ | I56: =SUM(I54:I55) -> 0 | K56: =SUM(K54:K55) -> -328158 | M56: =SUM(M54:M55) -> 31842
A58: Operating expenses
A59: General and administration | B59: $ | D59: $ | F59: $ | G59: =SUMIF('BS.1 - F25'!G:G,A59,'BS.1 - F25'!F:F) -> 1755445 | H59: $ | I59: =SUMIF('BS.2 - F24'!G:G,FS.1!A59,'BS.2 - F24'!F:F) -> #REF! | K59: =C59-E59 -> 0 | L59: =IFERROR(K59/E59,0) -> 0 | M59: =G59-I59 -> #REF! | N59: =IFERROR(M59/I59,0) -> 0 | O59: Refer to Tab 'Note Disclosures'
A60: Sales and marketing | G60: =SUMIF('BS.1 - F25'!G:G,A60,'BS.1 - F25'!F:F) -> 70958 | I60: =SUMIF('BS.2 - F24'!G:G,FS.1!A60,'BS.2 - F24'!F:F) -> #REF! | K60: =C60-E60 -> 0 | L60: =IFERROR(K60/E60,1) -> 1 | M60: =G60-I60 -> #REF! | N60: =IFERROR(M60/I60,0) -> 0 | O60: Not material
A61: Total operating expenses | B61: $ | C61: =-SUM(C59:C60) -> 0 | D61: $ | E61: =-SUM(E59:E60) -> 0 | F61: $ | G61: =-SUM(G59:G60) -> -1826403 | H61: $ | I61: =-SUM(I59:I60) -> #REF! | K61: =-SUM(K59:K60) -> 0 | M61: =-SUM(M59:M60) -> #REF!
A62: Operating income / (loss) | B62: $ | C62: =SUM(C56,C61) -> 0 | D62: $ | E62: =SUM(E56,E61) -> 0 | F62: $ | G62: =SUM(G56,G61) -> -1794561 | H62: $ | I62: =SUM(I56,I61) -> #REF! | K62: =SUM(K56,K61) -> -328158 | M62: =SUM(M56,M61) -> #REF!
A63: Other income (expenses)
A64: Other income | G64: =-SUMIF('BS.1 - F25'!G:G,A64,'BS.1 - F25'!F:F) -> 0 | I64: =-SUMIF('BS.2 - F24'!G:G,FS.1!A64,'BS.2 - F24'!F:F) -> 3150 | K64: =C64-E64 -> 0 | L64: =IFERROR(K64/E64,0) -> 0 | M64: =G64-I64 -> -3150 | N64: =IFERROR(M64/I64,0) -> -1 | O64: no movement
A65: Interest income | G65: =-SUMIF('BS.1 - F25'!G:G,A65,'BS.1 - F25'!F:F) -> 14 | I65: =-SUMIF('BS.2 - F24'!G:G,FS.1!A65,'BS.2 - F24'!F:F) -> #REF! | K65: =C65-E65 -> 0 | L65: =IFERROR(K65/E65,1) -> 1 | M65: =G65-I65 -> #REF! | N65: =IFERROR(M65/I65,0) -> 0 | O65: Not material
A66: Net financial expenses | G66: =-SUMIF('BS.1 - F25'!G:G,A66,'BS.1 - F25'!F:F) -> -31957 | I66: =-SUMIF('BS.2 - F24'!G:G,FS.1!A66,'BS.2 - F24'!F:F) -> 50062 | K66: =C66-E66 -> 0 | L66: =IFERROR(K66/E66,1) -> 1 | M66: =G66-I66 -> -82019 | N66: =IFERROR(M66/I66,0) -> -1.6383484
A67: Accretion expense | G67: =-SUMIF('BS.1 - F25'!G:G,A67,'BS.1 - F25'!F:F) -> 0 | I67: =-SUMIF('BS.2 - F24'!G:G,FS.1!A67,'BS.2 - F24'!F:F) -> 0 | K67: =C67-E67 -> 0 | L67: =IFERROR(K67/E67,1) -> 1 | M67: =G67-I67 -> 0 | N67: =IFERROR(M67/I67,1) -> 1 | O67: There was no covertible note and corresponding accretion expense in the comparative period
A68: Interest expense | G68: =-SUMIF('BS.1 - F25'!G:G,A68,'BS.1 - F25'!F:F) -> -45232 | I68: =-SUMIF('BS.2 - F24'!G:G,FS.1!A68,'BS.2 - F24'!F:F) -> -33787 | K68: =C68-E68 -> 0 | L68: =IFERROR(K68/E68,1) -> 1 | M68: =G68-I68 -> -11445 | N68: =IFERROR(M68/I68,1) -> 0.33873975 | O68: There was no covertible note and corresponding interest expense in the comparative period
A69: Loss before tax | B69: $ | C69: =SUM(C62:C68) -> 0 | D69: $ | E69: =SUM(E62:E68) -> 0 | F69: $ | G69: =SUM(G62:G68) -> -1871736 | H69: $ | I69: =SUM(I62:I68) -> #REF! | K69: =SUM(K62:K68) -> -328158 | M69: =SUM(M62:M68) -> #REF!
A70: Current tax recovery (expense) | G70: =SUMIF('IS - F25'!N:N,FS.1!A70,'IS - F25'!M:M) -> 0 | I70: =SUMIF('IS - F24'!L:L,A70,'IS - F24'!K:K) -> 0 | K70: =G70-I70 -> 0 | L70: =IFERROR(K70/E70,0) -> 0 | M70: =G70-I70 -> 0 | N70: =IFERROR(M70/I70,0) -> 0 | O70: no movement
A71: Deferred tax recovery (expense) | G71: =SUMIF('IS - F25'!N:N,FS.1!A71,'IS - F25'!M:M) -> 0 | I71: =SUMIF('IS - F24'!L:L,A71,'IS - F24'!K:K) -> 0 | K71: =G71-I71 -> 0 | L71: =IFERROR(K71/E71,0) -> 0 | M71: =G71-I71 -> 0 | N71: =IFERROR(M71/I71,0) -> 0 | O71: no movement
A72: Net income / (loss) for the year | B72: $ | C72: =SUM(C69:C71) -> 0 | D72: $ | E72: =SUM(E69:E71) -> 0 | F72: $ | G72: =SUM(G69:G71) -> -1871736 | H72: $ | I72: =SUM(I69:I71) -> #REF! | K72: =SUM(K69:K71) -> -328158 | M72: =SUM(M69:M71) -> #REF!
A73: Comprehensive income / (loss) for the year | B73: $ | C73: =SUM(C72:C72) -> 0 | D73: $ | E73: =SUM(E72:E72) -> 0 | F73: $ | G73: =SUM(G72:G72) -> -1871736 | H73: $ | I73: =SUM(I72:I72) -> #REF! | K73: =SUM(K72:K72) -> -328158 | M73: =SUM(M72:M72) -> #REF!
A75: CHECK TO BS.1/2 | G75: ='BS.1 - F25'!F4+G73 -> 0 | I75: ='BS.2 - F24'!F4+I73 -> #REF!
A77: Income (loss) per share – basic and diluted | B77: $ | C77: =C72/C78 -> 0 | D77: $ | E77: =E72/E78 -> 0 | F77: $ | G77: =G72/G78 -> -0.060112744 | H77: $ | I77: =I72/I78 -> #REF!
A78: WASO – basic and diluted | C78: 31912501 | E78: 6542479 | G78: 31137091 | I78: 6486787.3
A80: CHECK to IS.1 | C80: =C73+'IS - F25'!G91 -> 195204 | E80: =E73+'IS - F24'!F89 -> 17475 | G80: =G73+'IS - F25'!M91 -> -209719 | I80: ='BS.2 - F24'!F4+I72 -> #REF!
A83: =company_name -> Consolidated Hallor Group Inc.
A84: =SOCE_descr -> Statements of Changes in Shareholders's Equity
C85: Share capital | E85: Contributed Surplus | G85: Accumulated Deficit | I85: Total equity
A86: ="Balance - "&TEXT(comp_period_2,"MMMM D, YYYY") -> Balance - June 30, 2023 | B86: $ | C86: 1774099 | D86: $ | E86: 308750 | F86: $ | G86: -1474472 | H86: $ | I86: =ROUND(SUM(C86:G86),0) -> 608377
A87: Shares issued on acquisition of Hallor Industries Inc. | C87: 6000000 | E87: 0 | G87: 0 | I87: =ROUND(SUM(C87:G87),0) -> 6000000
A88: Acquisition costs of acquiring Hallor Industries Inc. | C88: 450000 | E88: 0 | G88: 0 | I88: =ROUND(SUM(C88:G88),0) -> 450000
A89: Net loss for period | C89: 0 | E89: 0 | G89: =I73 -> #REF! | I89: =ROUND(SUM(C89:G89),0) -> #REF!
A90: ="Balance - "&TEXT(comp_period_1,"MMMM D, YYYY") -> Balance - June 30, 2024 | B90: $ | C90: =ROUND(SUM(C86:C89),0) -> 8224099 | D90: $ | E90: =ROUND(SUM(E86:E89),0) -> 308750 | F90: $ | G90: =ROUND(SUM(G86:G89),0) -> #REF! | H90: $ | I90: =ROUND(SUM(I86:I89),0) -> #REF!
A92: Balance - July 1, 2024 | B92: $ | C92: =C90 -> 8224099 | D92: $ | E92: =E90 -> 308750 | F92: $ | G92: =G90 -> #REF! | H92: $ | I92: =ROUND(SUM(C92:G92),0) -> #REF!
A93: Shares issued on acquisition of Hallor Industries Inc. | C93: 0 | E93: 0 | G93: 0 | I93: =ROUND(SUM(C93:G93),0) -> 0
A94: Acquisition costs of acquiring Hallor Industries Inc. | C94: 0 | E94: 0 | I94: =ROUND(SUM(C94:G94),0) -> 0
A95: Net loss for period | C95: 0 | E95: 0 | G95: =G72 -> -1871736 | I95: =ROUND(SUM(C95:G95),0) -> -1871736
A96: ="Balance - "&TEXT(currentperiod_end_date,"MMMM D, YYYY") -> Balance - June 30, 2025 | B96: $ | C96: =ROUND(SUM(C92:C95),0) -> 8224099 | D96: $ | E96: =ROUND(SUM(E92:E95),0) -> 308750 | F96: $ | G96: =ROUND(SUM(G92:G95),0) -> #REF! | I96: =ROUND(SUM(I92:I95),0) -> #REF!
A98: Check - Prior Period | C98: =C90-E41 -> 0 | E98: =E90-E42 -> 0 | G98: =G90-E43 -> #REF! | I98: =I90-E44 -> #REF!
A99: Check - Current Period | C99: =C96-C41 -> 0 | E99: =E96-C42 -> 0 | G99: =G96-C43 -> #REF! | I99: =I96-C45 -> #REF!
A102: =CFS_Descr -> Statement of Cash Flows | E102: RE-LINK
C103: =TEXT(currentperiod_end_date,"MMMM DD, YYYY") -> June 30, 2025 | E103: =TEXT(comp_period_1,"MMMM DD, YYYY") -> June 30, 2024
A104: OPERATING ACTIVITIES
A105: Net loss for the year | B105: $ | C105: =G72 -> -1871736 | D105: $ | E105: =I72 -> #REF!
A107: Non-cash items:
A108: ='BS.1 - F25'!K199 -> Depreciation and amortization | C108: =_xlfn.XLOOKUP(A108,'BS.1 - F25'!$K$189:$K$244,'BS.1 - F25'!$L$189:$L$244,0,0,1) -> 1256364 | E108: =_xlfn.XLOOKUP(A108,'BS.2 - F24'!$K$191:$K$244,'BS.2 - F24'!$L$191:$L$244,0,0,1) -> #REF!
A109: Interest income | C109: =_xlfn.XLOOKUP(A109,'BS.1 - F25'!$K$189:$K$244,'BS.1 - F25'!$L$189:$L$244,0,0,1) -> 0 | E109: =_xlfn.XLOOKUP(A109,'BS.2 - F24'!$K$191:$K$244,'BS.2 - F24'!$L$191:$L$244,0,0,1) -> 0
A110: ='BS.1 - F25'!K195 -> Accretion expense | C110: =_xlfn.XLOOKUP(A110,'BS.1 - F25'!$K$189:$K$244,'BS.1 - F25'!$L$189:$L$244,0,0,1) -> 31957 | E110: =_xlfn.XLOOKUP(A110,'BS.2 - F24'!$K$191:$K$244,'BS.2 - F24'!$L$191:$L$244,0,0,1) -> 24938
A111: ='BS.1 - F25'!K196 -> Interest expense | C111: =_xlfn.XLOOKUP(A111,'BS.1 - F25'!$K$189:$K$244,'BS.1 - F25'!$L$189:$L$244,0,0,1) -> 37565 | E111: =_xlfn.XLOOKUP(A111,'BS.2 - F24'!$K$191:$K$244,'BS.2 - F24'!$L$191:$L$244,0,0,1) -> 30800
A112: ='BS.2 - F24'!K195 -> Gain on re-measurement of derivative liability | C112: =_xlfn.XLOOKUP(A112,'BS.1 - F25'!$K$189:$K$244,'BS.1 - F25'!$L$189:$L$244,0,0,1) -> 0 | E112: =_xlfn.XLOOKUP(A112,'BS.2 - F24'!$K$191:$K$244,'BS.2 - F24'!$L$191:$L$244,0,0,1) -> -75000
A114: Changes in non-cash working capital items:
A115: ='BS.1 - F25'!K203 -> Receivables | C115: =_xlfn.XLOOKUP(A115,'BS.1 - F25'!$K$189:$K$244,'BS.1 - F25'!$L$189:$L$244,0,0,1) -> 0 | E115: =_xlfn.XLOOKUP(A115,'BS.2 - F24'!$K$191:$K$244,'BS.2 - F24'!$L$191:$L$244,0,0,1) -> 12375
A116: ='BS.1 - F25'!K204 -> Prepaid expenses | C116: =_xlfn.XLOOKUP(A116,'BS.1 - F25'!$K$189:$K$244,'BS.1 - F25'!$L$189:$L$244,0,0,1) -> 0 | E116: =_xlfn.XLOOKUP(A116,'BS.2 - F24'!$K$191:$K$244,'BS.2 - F24'!$L$191:$L$244,0,0,1) -> 2240
A117: ='BS.1 - F25'!K205 -> Sales tax receivable | C117: =_xlfn.XLOOKUP(A117,'BS.1 - F25'!$K$189:$K$244,'BS.1 - F25'!$L$189:$L$244,0,0,1) -> -7455 | E117: =_xlfn.XLOOKUP(A117,'BS.2 - F24'!$K$191:$K$244,'BS.2 - F24'!$L$191:$L$244,0,0,1) -> -4177
A118: ='BS.1 - F25'!K206 -> Inventory | C118: =_xlfn.XLOOKUP(A118,'BS.1 - F25'!$K$189:$K$244,'BS.1 - F25'!$L$189:$L$244,0,0,1) -> 291108 | E118: =_xlfn.XLOOKUP(A118,'BS.2 - F24'!$K$191:$K$244,'BS.2 - F24'!$L$191:$L$244,0,0,1) -> -54914
A119: Accounts payables and accrued liabilities | C119: =_xlfn.XLOOKUP(A119,'BS.1 - F25'!$K$189:$K$244,'BS.1 - F25'!$L$189:$L$244,0,0,1) -> 253485 | E119: =_xlfn.XLOOKUP(A119,'BS.2 - F24'!$K$191:$K$244,'BS.2 - F24'!$L$191:$L$244,0,0,1) -> 102329
...

Sheet Note Disclosures
A1: =company_name -> Consolidated Hallor Group Inc.
A2: Note Disclosures
A4: SELECT Current Reporting Period >> | B4: =INPUTS!B3 -> Q4
A6: EXPAND BELOW - UNUSED NOTES
A8: Segment Reporting - NOT USED
C9: =currentperiod_end_date -> 45838 | D9: =priorperiod_end_date -> 45473
A10: Canada
A11: USA
A12: Europe
A13: Asia
A14: Total revenue | C14: =SUM(C10:C12) -> 0 | D14: =SUM(D10:D12) -> 0
A16: Check | C16: =C14-#REF! -> #REF! | D16: =D14-#REF! -> #REF!
C18: =currentperiod_end_date -> 45838 | D18: =priorperiod_end_date -> 45473
A19: Canada
A21: Total non-current assets | C21: =SUM(C19:C20) -> 0 | D21: =SUM(D19:D20) -> 0
A23: Check | C23: =C21-#REF! -> #REF! | D23: =D21-#REF! -> #REF!
A25: Trade and other receivables - NOT USED
C26: =currentperiod_end_date -> 45838 | D26: =priorperiod_end_date -> 45473
A27: Trade receivables from contracts with customers | C27: =SUMIF('FY Current'!I:I,'Note Disclosures'!$A27,'FY Current'!G:G) -> 0 | D27: =SUMIF(#REF!,$A27,#REF!) -> #REF!
A28: Sales taxes receivable | C28: =SUMIF('FY Current'!I:I,'Note Disclosures'!$A28,'FY Current'!G:G) -> 0 | D28: =SUMIF(#REF!,$A28,#REF!) -> #REF!
A29: Other receivables | C29: =SUMIF('FY Current'!I:I,'Note Disclosures'!$A29,'FY Current'!G:G) -> 0 | D29: =SUMIF(#REF!,$A29,#REF!) -> #REF!
A30: Loss allowance | C30: =SUMIF('FY Current'!I:I,'Note Disclosures'!$A30,'FY Current'!G:G) -> 0 | D30: =SUMIF(#REF!,$A30,#REF!) -> #REF!
A31: Total trade and other receivables | C31: =SUM(C27:C30) -> 0 | D31: =SUM(D27:D30) -> #REF!
A33: Check | C33: =C31-#REF! -> #REF! | D33: =D31-#REF! -> #REF!
A35: Prepaid expenses and deposits - NOT USED
C36: =currentperiod_end_date -> 45838 | D36: =priorperiod_end_date -> 45473
A37: Prepaid listing expenses | C37: =SUMIF('FY Current'!I:I,'Note Disclosures'!$A37,'FY Current'!G:G) -> 0 | D37: =SUMIF(#REF!,$A37,#REF!) -> #REF!
A38: Other prepaid expenses | C38: =SUMIF('FY Current'!I:I,'Note Disclosures'!$A38,'FY Current'!G:G) -> 0 | D38: =SUMIF(#REF!,$A38,#REF!) -> #REF!
A39: Deposit | C39: =SUMIF('FY Current'!I:I,'Note Disclosures'!$A39,'FY Current'!G:G) -> 0 | D39: =SUMIF(#REF!,$A39,#REF!) -> #REF!
A40: Total prepaid expenses and deposits | C40: =SUM(C37:C39) -> 0 | D40: =SUM(D37:D39) -> #REF!
A41: Current portion of prepaid expenses and deposits | C41: 204945 | D41: 5644
A42: Non-current portion of prepaid expenses and deposits | C42: =C40-C41 -> -204945 | D42: =D40-D41 -> #REF!
A44: Check | C44: =C41-#REF! -> #REF! | D44: =D41-#REF! -> #REF!
A45: Check | C45: =C42-#REF! -> #REF! | D45: =D42-#REF! -> #REF!
A47: Property and equipment- NOT USED
C48: Computer Equipment | D48: Furniture and Equipment | E48: Leasehold improvements | F48: Open | G48: Total
A49: Cost
A50: =IFRS_adopt -> 45930 | F50: 0 | G50: =SUM(C50:F50) -> 0
A51: Additions | F51: 0 | G51: =SUM(C51:F51) -> 0
A52: =comp_period_1 -> 45473 | C52: =SUM(C50:C51) -> 0 | D52: =SUM(D50:D51) -> 0 | E52: =SUM(E50:E51) -> 0 | F52: =SUM(F50:F51) -> 0 | G52: =SUM(C52:F52) -> 0
A53: Additions | F53: 0 | G53: =SUM(C53:F53) -> 0
A54: =currentperiod_end_date -> 45838 | C54: =SUM(C52:C53) -> 0 | D54: =SUM(D52:D53) -> 0 | E54: =SUM(E52:E53) -> 0 | F54: =SUM(F52:F53) -> 0 | G54: =SUM(G52:G53) -> 0
A56: Accumulated amortization
A57: 43830 | F57: 0 | G57: =SUM(C57:F57) -> 0
A58: Amortization | F58: 0 | G58: =SUM(C58:F58) -> 0
A59: =A52 -> 45473 | C59: =SUM(C57:C58) -> 0 | D59: =SUM(D57:D58) -> 0 | E59: =SUM(E57:E58) -> 0 | F59: =SUM(F57:F58) -> 0 | G59: =SUM(C59:F59) -> 0
A60: Amortization | F60: 0 | G60: =SUM(C60:F60) -> 0
A61: =A54 -> 45838 | C61: =SUM(C59:C60) -> 0 | D61: =SUM(D59:D60) -> 0 | E61: =SUM(E59:E60) -> 0 | F61: =SUM(F59:F60) -> 0 | G61: =SUM(G59:G60) -> 0
A63: Carrying amounts
A64: =IFRS_adopt -> 45930 | C64: =C50-C57 -> 0 | D64: =D50-D57 -> 0 | E64: =E50-E57 -> 0 | F64: =F50-F57 -> 0 | G64: =G50-G57 -> 0
A65: =comp_period_1 -> 45473 | C65: =C52-C59 -> 0 | D65: =D52-D59 -> 0 | E65: =E52-E59 -> 0 | F65: =F52-F59 -> 0 | G65: =G52-G59 -> 0
A66: =currentperiod_end_date -> 45838 | C66: =C54-C61 -> 0 | D66: =D54-D61 -> 0 | E66: =E54-E61 -> 0 | F66: =F54-F61 -> 0 | G66: =G54-G61 -> 0
A68: Check | G68: =G64-#REF! -> #REF!
A69: Check | G69: =G65-#REF! -> #REF!
A70: Check | G70: =G66-#REF! -> #REF!
A73: Intangible assets - NOT USED
C74: [Placeholder] | D74: [Placeholder] | E74: [Placeholder] | F74: [Placeholder] | G74: Total
A75: Cost
A76: 43646 | C76: 0 | D76: 0 | E76: 0 | F76: 0 | G76: =SUM(C76:F76) -> 0
A77: Additions | C77: 0 | D77: 0 | E77: 0 | F77: 0 | G77: =SUM(C77:F77) -> 0
A78: 44012 | C78: =SUM(C76:C77) -> 0 | D78: =SUM(D76:D77) -> 0 | E78: =SUM(E76:E77) -> 0 | F78: =SUM(F76:F77) -> 0 | G78: =SUM(C78:F78) -> 0
A79: Additions | C79: 0 | D79: 0 | E79: 0 | F79: 0 | G79: =SUM(C79:F79) -> 0
A80: 44377 | C80: =SUM(C78:C79) -> 0 | D80: =SUM(D78:D79) -> 0 | E80: =SUM(E78:E79) -> 0 | F80: =SUM(F78:F79) -> 0 | G80: =SUM(G78:G79) -> 0
A82: Accumulated amortization
A83: 43646 | C83: 0 | D83: 0 | E83: 0 | F83: 0 | G83: =SUM(C83:F83) -> 0
A84: Amortization | C84: 0 | D84: 0 | E84: 0 | F84: 0 | G84: =SUM(C84:F84) -> 0
A85: 44012 | C85: =SUM(C83:C84) -> 0 | D85: =SUM(D83:D84) -> 0 | E85: =SUM(E83:E84) -> 0 | F85: =SUM(F83:F84) -> 0 | G85: =SUM(C85:F85) -> 0
A86: Amortization | C86: 0 | D86: 0 | E86: 0 | F86: 0 | G86: =SUM(C86:F86) -> 0
A87: 44377 | C87: =SUM(C85:C86) -> 0 | D87: =SUM(D85:D86) -> 0 | E87: =SUM(E85:E86) -> 0 | F87: =SUM(F85:F86) -> 0 | G87: =SUM(G85:G86) -> 0
A89: Carrying amounts
A90: 43646 | C90: =C76-C83 -> 0 | D90: =D76-D83 -> 0 | E90: =E76-E83 -> 0 | F90: =F76-F83 -> 0 | G90: =G76-G83 -> 0
A91: 44012 | C91: =C78-C85 -> 0 | D91: =D78-D85 -> 0 | E91: =E78-E85 -> 0 | F91: =F78-F85 -> 0 | G91: =G78-G85 -> 0
A92: 44377 | C92: =C80-C87 -> 0 | D92: =D80-D87 -> 0 | E92: =E80-E87 -> 0 | F92: =F80-F87 -> 0 | G92: =G80-G87 -> 0
A94: Check | G94: =G91-#REF! -> #REF!
A95: Check | G95: =G92-#REF! -> #REF!
A98: Right-of-use assets - NOT USED
C99: Property | D99: Vehicles | E99: [Placeholder] | F99: [Placeholder] | G99: Total
A100: =IFRS_adopt -> 45930 | G100: =SUM(C100:F100) -> 0
A101: Additions | G101: =SUM(C101:F101) -> 0
A102: Depreciation charge for the period | G102: =SUM(C102:F102) -> 0
A103: =priorperiod_end_date -> 45473 | C103: =SUM(C100:C102) -> 0 | D103: =SUM(D100:D102) -> 0 | E103: =SUM(E100:E102) -> 0 | F103: =SUM(F100:F102) -> 0 | G103: =SUM(C103:F103) -> 0
A104: Additions | G104: =SUM(C104:F104) -> 0
A105: Depreciation charge for the period | G105: =SUM(C105:F105) -> 0
A106: =currentperiod_end_date -> 45838 | C106: =SUM(C103:C105) -> 0 | D106: =SUM(D103:D105) -> 0 | E106: =SUM(E103:E105) -> 0 | F106: =SUM(F103:F105) -> 0 | G106: =SUM(G103:G105) -> 0
A108: Check | G108: =G100-#REF! -> #REF!
A109: Check | G109: =G103-#REF! -> #REF!
A110: Check | G110: =G106-#REF! -> #REF!
A113: Lease liabilities - NOT USED
C114: =currentperiod_end_date -> 45838 | D114: =priorperiod_end_date -> 45473 | E114: =IFRS_adopt -> 45930
A115: Balance, beginning of year
A116: Additions
A117: Payments of lease obligations
A118: Finance cost on lease liabilities
A119: Effect from currency translation
A120: Balance, end of year | C120: =SUM(C115:C119) -> 0 | D120: =SUM(D115:D119) -> 0 | E120: =SUM(E115:E119) -> 0
A122: Check | C122: 0 | D122: 0 | E122: =E120-SUM(#REF!,#REF!) -> #REF!
C125: =currentperiod_end_date -> 45838 | D125: =priorperiod_end_date -> 45473 | E125: =IFRS_adopt -> 45930
A126: Maturity analysis – contractual undiscounted cash outflows
A127: Less than on year
A128: One to five years
...

Sheet Cash Flow Proof
A1: =company_name -> Consolidated Hallor Group Inc.
A2: Cash Flow Proof
D4: AJEs | E4: [Placeholder] | F4: Reclass | G4: Total
A5: =priorperiod_end_date -> 45473 | B5: =_xlfn.XLOOKUP(A5,#REF!,#REF!,0,0,1) -> #REF! | C5: =_xlfn.XLOOKUP(A5,#REF!,#REF!,0,0,1) -> #REF! | D5: 0 | G5: =SUM(B5:F5) -> #REF!
A6: =currentperiod_end_date -> 45838 | B6: =_xlfn.XLOOKUP(A6,#REF!,#REF!,0,0,1) -> #REF! | C6: =_xlfn.XLOOKUP(A6,#REF!,#REF!,0,0,1) -> #REF! | D6: 0 | G6: =SUM(B6:F6) -> #REF!
A7: Net Change | B7: =B6-B5 -> #REF! | C7: =C6-C5 -> #REF! | D7: =D6-D5 -> 0 | E7: =E6-E5 -> 0 | F7: =F6-F5 -> 0 | G7: =G6-G5 -> #REF!
A9: Operating activities
A10: Net loss for the period | B10: =_xlfn.XLOOKUP(A10,#REF!,#REF!,0,0,1) -> #REF! | C10: =_xlfn.XLOOKUP(A10,#REF!,#REF!,0,0,1) -> #REF! | D10: =-122911-92253 -> -215164 | G10: =ROUND(SUM(B10:F10),0) -> #REF! | J10: =#REF! -> #REF! | K10: =J10-G10 -> #REF!
A12: Items not affecting cash:
A13: Depreciation and amortization | B13: =_xlfn.XLOOKUP(A13,#REF!,#REF!,0,0,1) -> #REF! | C13: =_xlfn.XLOOKUP(A13,#REF!,#REF!,0,0,1) -> #REF! | D13: ='FY Current'!#REF! -> #REF! | G13: =ROUND(SUM(B13:F13),0) -> #REF!
A14: Bad debt | B14: =_xlfn.XLOOKUP(A14,#REF!,#REF!,0,0,1) -> #REF! | C14: =_xlfn.XLOOKUP(A14,#REF!,#REF!,0,0,1) -> #REF! | G14: =ROUND(SUM(B14:F14),0) -> #REF!
A15: Gain from debt forgiveness | B15: =_xlfn.XLOOKUP(A15,#REF!,#REF!,0,0,1) -> #REF! | C15: =_xlfn.XLOOKUP(A15,#REF!,#REF!,0,0,1) -> #REF! | G15: =ROUND(SUM(B15:F15),0) -> #REF!
A16: Net financing cost | B16: =_xlfn.XLOOKUP(A16,#REF!,#REF!,0,0,1) -> #REF! | C16: =_xlfn.XLOOKUP(A16,#REF!,#REF!,0,0,1) -> #REF! | D16: -4643 | G16: =ROUND(SUM(B16:F16),0) -> #REF!
A17: Share-based payments | B17: =_xlfn.XLOOKUP(A17,#REF!,#REF!,0,0,1) -> #REF! | C17: =_xlfn.XLOOKUP(A17,#REF!,#REF!,0,0,1) -> #REF! | G17: =SUM(B17:F17) -> #REF!
A18: Foreign currency exchange | B18: =_xlfn.XLOOKUP(A18,#REF!,#REF!,0,0,1) -> #REF! | C18: =_xlfn.XLOOKUP(A18,#REF!,#REF!,0,0,1) -> #REF! | G18: =ROUND(SUM(B18:F18),0) -> #REF!
A19: Current tax recovery (expense) | B19: =_xlfn.XLOOKUP(A19,#REF!,#REF!,0,0,1) -> #REF! | C19: =_xlfn.XLOOKUP(A19,#REF!,#REF!,0,0,1) -> #REF! | G19: =ROUND(SUM(B19:F19),0) -> #REF!
A20: Deferred tax recovery (expense) | B20: =_xlfn.XLOOKUP(A20,#REF!,#REF!,0,0,1) -> #REF! | C20: =_xlfn.XLOOKUP(A20,#REF!,#REF!,0,0,1) -> #REF! | G20: =ROUND(SUM(B20:F20),0) -> #REF!
A22: Net change in non-cash working capital items:
A23: Bank indebtedness | B23: =_xlfn.XLOOKUP(A23,#REF!,#REF!,0,0,1) -> #REF! | C23: =_xlfn.XLOOKUP(A23,#REF!,#REF!,0,0,1) -> #REF! | G23: =SUM(B23:F23) -> #REF!
A24: Trade and other receivables | B24: =_xlfn.XLOOKUP(A24,#REF!,#REF!,0,0,1) -> #REF! | C24: =_xlfn.XLOOKUP(A24,#REF!,#REF!,0,0,1) -> #REF! | G24: =ROUND(SUM(B24:F24),0) -> #REF!
A25: Deferred tax asset | B25: =_xlfn.XLOOKUP(A25,#REF!,#REF!,0,0,1) -> #REF! | C25: =_xlfn.XLOOKUP(A25,#REF!,#REF!,0,0,1) -> #REF! | G25: =ROUND(SUM(B25:F25),0) -> #REF!
A26: Prepaid expenses and deposits | B26: =_xlfn.XLOOKUP(A26,#REF!,#REF!,0,0,1) -> #REF! | C26: =_xlfn.XLOOKUP(A26,#REF!,#REF!,0,0,1) -> #REF! | G26: =ROUND(SUM(B26:F26),0) -> #REF!
A27: Trade payables and accrued liabilities | B27: =_xlfn.XLOOKUP(A27,#REF!,#REF!,0,0,1) -> #REF! | C27: =_xlfn.XLOOKUP(A27,#REF!,#REF!,0,0,1) -> #REF! | D27: =-D10-D13+1-D47-D16 -> #REF! | G27: =ROUND(SUM(B27:F27),0) -> #REF! | J27: =#REF! -> #REF!
A28: Due to/from related parties | B28: =_xlfn.XLOOKUP(A28,#REF!,#REF!,0,0,1) -> #REF! | C28: =_xlfn.XLOOKUP(A28,#REF!,#REF!,0,0,1) -> #REF! | G28: =ROUND(SUM(B28:F28),0) -> #REF! | I28: =G28/averageFX_period -> #REF!
A29: Taxes paid | B29: =_xlfn.XLOOKUP(A29,#REF!,#REF!,0,0,1) -> #REF! | C29: =_xlfn.XLOOKUP(A29,#REF!,#REF!,0,0,1) -> #REF! | G29: =ROUND(SUM(B29:F29),0) -> #REF!
A30: Cash used in operating activities: | G30: =SUM(G10:G29) -> #REF!
A32: Investing activities
A33: Acquisition of property and equipment | B33: =_xlfn.XLOOKUP(A33,#REF!,#REF!,0,0,1) -> #REF! | C33: =_xlfn.XLOOKUP(A33,#REF!,#REF!,0,0,1) -> #REF! | G33: =ROUND(SUM(B33:F33),0) -> #REF!
A34: Expenditures on intangible assets | B34: =_xlfn.XLOOKUP(A34,#REF!,#REF!,0,0,1) -> #REF! | C34: =_xlfn.XLOOKUP(A34,#REF!,#REF!,0,0,1) -> #REF! | G34: =ROUND(SUM(B34:F34),0) -> #REF!
A35: Interest received | B35: =_xlfn.XLOOKUP(A35,#REF!,#REF!,0,0,1) -> #REF! | C35: =_xlfn.XLOOKUP(A35,#REF!,#REF!,0,0,1) -> #REF! | G35: =ROUND(SUM(B35:F35),0) -> #REF!
A37: Net cash flows from investing activities | G37: =SUM(G33:G36) -> #REF!
A39: Financing activities
A40: Repayment of lease liabilities | B40: =_xlfn.XLOOKUP(A40,#REF!,#REF!,0,0,1) -> #REF! | C40: =_xlfn.XLOOKUP(A40,#REF!,#REF!,0,0,1) -> #REF! | G40: =ROUND(SUM(B40:F40),0) -> #REF!
A41: Repayment of loans and borrowings | B41: =_xlfn.XLOOKUP(A41,#REF!,#REF!,0,0,1) -> #REF! | C41: =_xlfn.XLOOKUP(A41,#REF!,#REF!,0,0,1) -> #REF! | G41: =ROUND(SUM(B41:F41),0) -> #REF!
A42: Interest paid | B42: =_xlfn.XLOOKUP(A42,#REF!,#REF!,0,0,1) -> #REF! | C42: =_xlfn.XLOOKUP(A42,#REF!,#REF!,0,0,1) -> #REF! | G42: =ROUND(SUM(B42:F42),0) -> #REF!
A43: Proceeds from loans, net of transaction costs | B43: =_xlfn.XLOOKUP(A43,#REF!,#REF!,0,0,1) -> #REF! | C43: =_xlfn.XLOOKUP(A43,#REF!,#REF!,0,0,1) -> #REF! | G43: =ROUND(SUM(B43:F43),0) -> #REF!
A44: Increase (decrease) of bank indebtedness | B44: =_xlfn.XLOOKUP(A44,#REF!,#REF!,0,0,1) -> #REF! | C44: =_xlfn.XLOOKUP(A44,#REF!,#REF!,0,0,1) -> #REF! | G44: =ROUND(SUM(B44:F44),0) -> #REF!
A45: Proceeds from private placements | B45: =_xlfn.XLOOKUP(A45,#REF!,#REF!,0,0,1) -> #REF! | C45: =_xlfn.XLOOKUP(A45,#REF!,#REF!,0,0,1) -> #REF! | G45: =ROUND(SUM(B45:F45),0) -> #REF!
A46: Share issue costs | B46: =_xlfn.XLOOKUP(A46,#REF!,#REF!,0,0,1) -> #REF! | C46: =_xlfn.XLOOKUP(A46,#REF!,#REF!,0,0,1) -> #REF! | G46: =ROUND(SUM(B46:F46),0) -> #REF!
A47: (Repayment of) advances from related party | B47: =_xlfn.XLOOKUP(A47,#REF!,#REF!,0,0,1) -> #REF! | C47: =_xlfn.XLOOKUP(A47,#REF!,#REF!,0,0,1) -> #REF! | D47: =-539223 -> -539223 | G47: =ROUND(SUM(B47:F47),0) -> #REF! | J47: =#REF! -> #REF! | L47: =G47-J47 -> #REF!
A48: (Repayment of) advances from shareholders | B48: =_xlfn.XLOOKUP(A48,#REF!,#REF!,0,0,1) -> #REF! | C48: =_xlfn.XLOOKUP(A48,#REF!,#REF!,0,0,1) -> #REF! | G48: =ROUND(SUM(B48:F48),0) -> #REF!
A49: Proceeds from exercise of share purchase warrants, net of issuance costs | B49: =_xlfn.XLOOKUP(A49,#REF!,#REF!,0,0,1) -> #REF! | C49: =_xlfn.XLOOKUP(A49,#REF!,#REF!,0,0,1) -> #REF! | G49: =ROUND(SUM(B49:F49),0) -> #REF!
A50: Net cash flows from financing activities | G50: =SUM(G40:G49) -> #REF!
A52: Non-cash items (which have no impact on CFS):
A53: Initial recognition of ROU assets and lease liabilities | B53: =_xlfn.XLOOKUP(A53,#REF!,#REF!,0,0,1) -> #REF! | C53: =_xlfn.XLOOKUP(A53,#REF!,#REF!,0,0,1) -> #REF! | G53: =ROUND(SUM(B53:F53),0) -> #REF!
A54: Shares issued to settle liabilities | B54: =_xlfn.XLOOKUP(A54,#REF!,#REF!,0,0,1) -> #REF! | C54: =_xlfn.XLOOKUP(A54,#REF!,#REF!,0,0,1) -> #REF! | G54: =ROUND(SUM(B54:F54),0) -> #REF!
A55: Shares issued in business combination | B55: =_xlfn.XLOOKUP(A55,#REF!,#REF!,0,0,1) -> #REF! | C55: =_xlfn.XLOOKUP(A55,#REF!,#REF!,0,0,1) -> #REF! | G55: =ROUND(SUM(B55:F55),0) -> #REF!
A57: Increase (decrease) in cash during the year | G57: =SUM(G30,G37,G50) -> #REF!
A58: Foreign exchange effect on cash held in other currencies | B58: =_xlfn.XLOOKUP(A58,#REF!,#REF!,0,0,1) -> #REF! | C58: =_xlfn.XLOOKUP(A58,#REF!,#REF!,0,0,1) -> #REF! | G58: =ROUND(SUM(B58:F58),0) -> #REF!
A59: Cash, beginning of period | B59: =_xlfn.XLOOKUP(A59,#REF!,#REF!,0,0,1) -> #REF! | C59: =_xlfn.XLOOKUP(A59,#REF!,#REF!,0,0,1) -> #REF! | G59: =ROUND(SUM(B59:F59),0) -> #REF!
A60: Cash, end of period | B60: =ROUND(SUM(B10:B59),0) -> #REF! | C60: =ROUND(SUM(C10:C59),0) -> #REF! | D60: =ROUND(SUM(D10:D59),0) -> #REF! | E60: =ROUND(SUM(E10:E59),0) -> 0 | F60: =ROUND(SUM(F10:F59),0) -> 0 | G60: =SUM(G57:G59) -> #REF!
A62: Check | B62: =B60-B6 -> #REF! | C62: =C60-C6 -> #REF! | D62: =D60-D6 -> #REF! | E62: =E60-E6 -> 0 | F62: =F60-F6 -> 0 | G62: =G60-G6 -> #REF!

Sheet WASO - 2022
D2: Weighted Average Shares Outstanding Calculations
F3: for the year ending | H3: =EDATE(J4,12) -> 44926
G4: (previous year end | J4: 44561
G6: 12 Months | H6: 3 months | K6: 9 months | L6: 3 months | O6: 6 months | P6: 3 months | S6: 3 months
F7: 12 mos. | G7: =H7 -> 44926 | H7: =H3 -> 44926 | J7: 9 mos. | K7: =L7 -> 44834 | L7: =EDATE(J4,9) -> 44834 | N7: 6 mos. | O7: =P7 -> 44742 | P7: =EDATE(J4,6) -> 44742 | R7: 3 mos. | S7: =EDATE(J4,3) -> 44651
F8: days | G8: WTD. AVG. | H8: WTD. AVG. | J8: days | K8: WTD. AVG. | L8: WTD. AVG. | N8: days | O8: WTD. AVG. | P8: WTD. AVG. | R8: days | S8: WTD. AVG.
D9: # Shares | G9: =G7-J4 -> 365 | H9: =H7-L7 -> 92 | K9: =K7-J4 -> 273 | L9: =L7-P7 -> 92 | O9: =O7-J4 -> 181 | P9: =P7-S7 -> 91 | S9: =S7-J4 -> 90
B10: =J4+1 -> 44562 | C10: OPENING BALANCE | D10: 26000000
F11: =IF(D11>0,G$7-B11+1," ") | G11: =IF(D11>0,F11/G$9*$D11," ") | J11: =IF(D11>0,K$7-B11+1," ") | K11: =IF(D11>0,J11/K$9*$D11," ") | N11: =IF(D11>0,O$7-B11+1," ") | O11: =IF(D11>0,N11/O$9*$D11," ") | R11: =IF(D11>0,S$7-B11+1," ") | S11: =IF(D11>0,R11/S$9*$D11," ")
F12: =IF(D12>0,G$7-B12+1," ") | G12: =IF(D12>0,F12/G$9*$D12," ") | J12: =IF(D12>0,K$7-B12+1," ") | K12: =IF(D12>0,J12/K$9*$D12," ") | N12: =IF(D12>0,O$7-B12+1," ") | O12: =IF(D12>0,N12/O$9*$D12," ") | R12: =IF(D12>0,S$7-B12+1," ") | S12: =IF(D12>0,R12/S$9*D12," ")
F13: =IF(D13>0,G$7-B13+1," ") | G13: =IF(D13>0,F13/G$9*$D13," ") | J13: =IF(D13>0,K$7-B13+1," ") | K13: =IF(D13>0,J13/K$9*$D13," ") | N13: =IF(D13>0,O$7-B13+1," ") | O13: =IF(D13>0,N13/O$9*$D13," ") | R13: =IF(D13>0,S$7-B13+1," ") | S13: =IF(D13>0,R13/S$9*D13," ")
F14: =IF(D14>0,G$7-B14+1," ") | G14: =IF(D14>0,F14/G$9*$D14," ") | J14: =IF(D14>0,K$7-B14+1," ") | K14: =IF(D14>0,J14/K$9*$D14," ") | N14: =IF(D14>0,O$7-B14+1," ") | O14: =IF(D14>0,N14/O$9*$D14," ") | R14: =IF(D14>0,S$7-B14+1," ") | S14: =IF(D14>0,R14/S$9*$D14," ")
C15: WEIGHTED AVG. SHARES O/S FOR 3 MO.S | S15: =SUM(S10:S14)+D10 -> 26000000
B17: =EDATE(B10,3) -> 44652 | C17: OPENING BALANCE | D17: =SUM(D10:D14) -> 26000000
G19: =IF(D19>0,F19/G$9*$D19," ") | J19: =IF(D19>0,K$7-B19+1," ") | K19: =IF(D19>0,J19/K$9*$D19," ") | N19: =IF(D19>0,O$7-B19+1," ") | O19: =IF(D19>0,N19/O$9*$D19," ") | P19: =IF(D19>0,N19/P$9*D19," ")
F20: =IF(D20>0,G$7-B20+1," ") | G20: =IF(D20>0,F20/G$9*$D20," ") | J20: =IF(D20>0,K$7-B20+1," ") | K20: =IF(D20>0,J20/K$9*$D20," ") | N20: =IF(D20>0,O$7-B20+1," ") | O20: =IF(D20>0,N20/O$9*$D20," ") | P20: =IF(D20>0,N20/P$9*D20," ")
C22: WEIGHTED AVG. SHARES O/S FOR 6 MO.S | O22: =SUM(O10:O21)+D10 -> 26000000
C23: WEIGHTED AVG. SHARES O/S FOR 3 MO.S | P23: =SUM(P18:P21)+D17 -> 26000000
B25: =EDATE(B17,3) -> 44743 | C25: OPENING BALANCE | D25: =SUM(D17:D21) -> 26000000
K26: =IF(D26>0,J26/K$9*$D26," ") | L26: =IF(D26>0,J26/L$9*D26," ")
F27: =IF(D27>0,G$7-B27+1," ") | G27: =IF(D27>0,F27/G$9*$D27," ") | J27: =IF(D27>0,K$7-B27+1," ") | K27: =IF(D27>0,J27/K$9*$D27," ") | L27: =IF(D27>0,J27/L$9*D27," ")
F28: =IF(D28>0,G$7-B28+1," ") | G28: =IF(D28>0,F28/G$9*$D28," ") | J28: =IF(D28>0,K$7-B28+1," ") | K28: =IF(D28>0,J28/K$9*$D28," ") | L28: =IF(D28>0,J28/L$9*D28," ") | N28: =IF(D28>0,O$7-B28+1," ")
C29: WEIGHTED AVG. SHARES O/S FOR 9 MO.S | K29: =SUM(K10:K28)+D10 -> 26000000
C30: WEIGHTED AVG. SHARES O/S FOR 3 MO.S | L30: =SUM(L24:L28)+D25 -> 26000000
B31: =EDATE(B25,3) -> 44835 | C31: OPENING BALANCE | D31: =SUM(D25:D28) -> 26000000
F33: =IF(D33>0,G$7-B33+1," ") | G33: =IF(D33>0,F33/365*$D33," ") | H33: =IF(D33>0,F33/H$9*D33," ")
F34: =IF(D34>0,G$7-#REF!+1," ") | G34: =IF(D34>0,F34/365*$D34," ") | H34: =IF(D34>0,F34/H$9*D34," ") | J34: =IF(D34>0,K$7-#REF!+1," ")
C35: WEIGHTED AVG. SHARES O/S FOR 12 MO.S | G35: =SUM(G10:G34)+D10 -> 26000000
C36: WEIGHTED AVG. SHARES O/S FOR 3 MO.S | H36: =SUM(H32:H34)+D31 -> 26000000
B38: =B31+91 -> 44926 | C38: CLOSING BALANCE | D38: =SUM(D31:D34) -> 26000000
D41: =#REF! -> #REF! | E41: =#REF! -> #REF! | G41: =#REF! -> #REF! | H41: =#REF! -> #REF!
D42: =E42 -> 45473 | E42: =EOMONTH(EDATE(G42,-12),0) -> 45473 | G42: =currentperiod_end_date -> 45838 | H42: =currentperiod_end_date -> 45838
C43: Ending WASO | D43: 14478261 | E43: 6887671.2 | G43: =H36 -> 26000000 | H43: =G35 -> 26000000
C45: Total Loss | E45: =#REF! -> #REF! | H45: =#REF! -> #REF!
C46: Basic and diluted loss per share | D46: =IFERROR(D45/D43,0) -> 0 | E46: =IFERROR(E45/E43,0) -> 0 | G46: =IFERROR(G45/G43,0) -> 0 | H46: =IFERROR(H45/H43,0) -> 0

Sheet Prospectus Table
A1: WITH FINANCING REFLECTED
A2: Sources of Available Funds | B2: Available Funds ($)
A3: Working capital of Company | B3: 288310 | H3: as at November 30, 2023
A4: Committed convertible debenture financing per Convertible Note | B4: =500000 -> 500000
A5: Committed production financing ($CAD) | B5: =2500000*I5 -> 3400000 | H5: USD to CAD FX rate | I5: 1.36
A6: Total pro forma working capital (unaudited) | B6: =SUM(B3:B5) -> 4188310
A9: Principal Purposes | B9: Funds ($)
A10: Total working capital available | B10: =B6 -> 4188310
A11: Less: Estimated product commercialization | B11: =-50000-2800000-50000 -> -2900000
A12: Less: Advertising and marketing | B12: =-60000 -> -60000
A13: Less: Estimated test-trial expenses | B13: -18000
A14: Less: Estimated expenses related to the development of additional modular components | B14: =-20000+5500 -> -14500
A15: Less: Estimated salaries | B15: =-372000 -> -372000
A16: Less: Estimated transaction fees (legal, accounting, listing fee, etc.) | B16: =-100000+55000 -> -45000
A17: Total use of proceeds | B17: =SUM(B11:B16) -> -3409500
A18: Unallocated funds (unaudited) | B18: =SUM(B10,B17) -> 778810 | C18: << must be positive $100k
A21: WITHOUT FINANCING REFLECTED | H21: [A] | I21: proforma exclude | J21: [A] | K21: [A] | L21: [A] | M21: [A] | N21: [A] | O21: proforma exclude
A22: Sources of Available Funds | B22: Available Funds ($) | D22: Proforma WC of Company | F22: Accounting WC | H22: Cash | I22: Ashik funds | J22: GST Rec | K22: Inventory | L22: Oth Asset | M22: Accounts Payable | N22: Due to RPT | O22: Conv Debt
A23: Working capital of Company | B23: =FS.1!C5+FS.1!C32+FS.1!C33 -> -409061 | D23: =SUM(H23,J23:N23) -> -446966 | E23: [A] | F23: =SUM(H23:O23) -> -721065 | H23: =H26 -> 392 | I23: 0 | J23: =J26 -> 0 | K23: =K26 -> 161256 | L23: 0 | M23: =M26 -> -603276 | N23: =N26 -> -5338 | O23: =O26 -> -274099
A24: Committed convertible debenture financing per Convertible Note | B24: =B4 -> 500000
A25: Committed production financing ($CAD) | B25: 0 | C25: NOV 2023 | D25: =SUM(H25,J25:N25) -> 288310 | E25: [A] | F25: =SUM(H25,J25:O25) -> 734 | H25: 44447 | I25: 500000 | J25: 49282 | K25: 427134 | L25: 0 | M25: -231653 | N25: -900 | O25: -287576 | P25: << NOV numbers as previously calc'd and communicated to Habib via email
A26: Total pro forma working capital (unaudited) | B26: =SUM(B23:B25) -> 90939 | C26: DEC 2023 | D26: =SUM(H26,J26:N26) -> -446966 | E26: [A] | F26: =SUM(H26,J26:O26) -> -721065 | H26: =FS.1!C13 -> 392 | I26: =I25 -> 500000 | J26: =FS.1!C14 -> 0 | K26: =FS.1!C17 -> 161256 | L26: 0 | M26: =-FS.1!C30 -> -603276 | N26: =-FS.1!C35 -> -5338 | O26: =-FS.1!C32-FS.1!C33 -> -274099 | P26: << current as of Dec 31 - QBO
C27: Change | D27: =SUM(H27:N27) -> -735276 | H27: =(H26-H25) -> -44055 | I27: =I26-I25 -> 0 | J27: =J26-J25 -> -49282 | K27: =K26-K25 -> -265878 | L27: =L26-L25 -> 0 | M27: =M26-M25 -> -371623 | N27: =N26-N25 -> -4438 | O27: =O26-O25 -> 13477
A29: Principal Purposes | B29: Funds ($)
A30: Total working capital available | B30: =B26 -> 90939
A31: Less: Estimated product commercialization | B31: =-50000 -> -50000
A32: Less: Advertising and marketing | B32: =-60000 -> -60000
A33: Less: Estimated test-trial expenses | B33: -18000
A34: Less: Estimated expenses related to the development of additional modular components | B34: =-20000 -> -20000
A35: Less: Estimated salaries | B35: =-372000 -> -372000
A36: Less: Estimated transaction fees (legal, accounting, listing fee, etc.) | B36: =-100000+55000-22000 -> -67000
A37: Total use of proceeds | B37: =SUM(B31:B36) -> -587000
A38: Unallocated funds (unaudited) | B38: =SUM(B30,B37) -> -496061 | C38: << must be positive $100k
A40: Minimum unallocated funds requirement | B40: =100000 -> 100000
A41: Cash short-fall to meet $100k requirment | B41: =IF((B38-B40)<0,B38-B40,0) -> -596061

Sheet Assumptions
A1: Assumptions | C1: input
C2: calculated
A4: 1) | B4: Estimate the # of sales agents to hire
B5: Avg # of units sold per agent each year | C5: 150
B6: Annual base salary | C6: 125000
B7: Commission % of gross profits per unit | C7: 0.1
B8: Gross profit per unit | C8: =#REF! -> #REF!
B9: Commission $ per unit | C9: =C7*C8 -> #REF!
B10: Potential total annual salary per agent | C10: =C6+(C5*C9) -> #REF!
B12: Ext- commission per unit sold | C12: 5000
C15: 2023 | D15: 2024 | E15: 2025 | F15: 2026 | H15: 45138 | I15: =EDATE(H15,12) -> 45504 | J15: =EDATE(I15,12) -> 45869 | K15: =EDATE(J15,12) -> 46234
C16: Year One | D16: Year Two | E16: Year Three | F16: Year Four | H16: Year One | I16: Year Two | J16: Year Three | K16: Year Four
B18: Projected unit sales | C18: =#REF! -> #REF! | D18: =#REF! -> #REF! | E18: =#REF! -> #REF! | F18: =#REF! -> #REF! | H18: =#REF! -> #REF! | I18: =SUM(#REF!,#REF!) -> #REF! | J18: =SUM(#REF!,#REF!) -> #REF! | K18: =SUM(#REF!,#REF!) -> #REF!
B19: # units allocated Gary | C19: =C18 -> #REF! | D19: 200 | E19: 200 | F19: 0 | H19: =H18 -> #REF! | I19: 200 | J19: 200 | K19: 0
B20: # units remaining | C20: =C18-C19 -> #REF! | D20: =D18-D19 -> #REF! | E20: =E18-E19 -> #REF! | F20: =F18-F19 -> #REF! | H20: =H18-H19 -> #REF! | I20: =I18-I19 -> #REF! | J20: =J18-J19 -> #REF! | K20: =K18-K19 -> #REF!
B21: # of sales agent needed | C21: =ROUND(C20/$C$5,0) -> #REF! | D21: =ROUND(D20/$C$5,0) -> #REF! | E21: =ROUND(E20/$C$5,0) -> #REF! | F21: =ROUND(F20/$C$5,0) -> #REF! | H21: =ROUND(H20/$C$5,0) -> #REF! | I21: =ROUND(I20/$C$5,0) -> #REF! | J21: =ROUND(J20/$C$5,0) -> #REF! | K21: =ROUND(K20/$C$5,0) -> #REF!
B23: Estimated Commissions | C23: =C19*$C$12 -> #REF! | D23: =D19*$C$12 -> 1000000 | E23: =E19*$C$12 -> 1000000 | F23: =F19*$C$12 -> 0 | H23: =H19*$C$12 -> #REF! | I23: =I19*$C$12 -> 1000000 | J23: =J19*$C$12 -> 1000000 | K23: =K19*$C$12 -> 0
B24: Estimated Payroll | C24: =C21*C10 -> #REF! | D24: =D21*$C$10 -> #REF! | E24: =E21*$C$10 -> #REF! | F24: =F21*$C$10 -> #REF! | H24: =H21*H10 -> #REF! | I24: =I21*$C$10 -> #REF! | J24: =J21*$C$10 -> #REF! | K24: =K21*$C$10 -> #REF!
B25: Total selling expense | C25: =SUM(C23:C24) -> #REF! | D25: =SUM(D23:D24) -> #REF! | E25: =SUM(E23:E24) -> #REF! | F25: =SUM(F23:F24) -> #REF! | H25: =SUM(H23:H24) -> #REF! | I25: =SUM(I23:I24) -> #REF! | J25: =SUM(J23:J24) -> #REF! | K25: =SUM(K23:K24) -> #REF!
C27: 2023 | D27: 2024 | E27: 2025 | F27: 2026 | H27: 2023 | I27: 2024 | J27: 2025 | K27: 2026
A28: 2 | B28: Payroll vs Commission structure | C28: Year One | D28: Year Two | E28: Year Three | F28: Year Four | H28: Year One | I28: Year Two | J28: Year Three | K28: Year Four
A30: a) | B30: Projected unit sales | C30: =C18 -> #REF! | D30: =D18 -> #REF! | E30: =E18 -> #REF! | F30: =F18 -> #REF! | H30: =H18 -> #REF! | I30: =I18 -> #REF! | J30: =J18 -> #REF! | K30: =K18 -> #REF!
B31: Commission per unit | C31: 5000 | D31: 5000 | E31: 5000 | F31: 5000 | H31: 5000 | I31: 5000 | J31: 5000 | K31: 5000
B32: Total Commission expense | C32: =C30*C31 -> #REF! | D32: =D30*D31 -> #REF! | E32: =E30*E31 -> #REF! | F32: =F30*F31 -> #REF! | H32: =H30*H31 -> #REF! | I32: =I30*I31 -> #REF! | J32: =J30*J31 -> #REF! | K32: =K30*K31 -> #REF!
A34: b) | B34: Projected unit sales | C34: =C18 -> #REF! | D34: =D18 -> #REF! | E34: =E18 -> #REF! | F34: =F18 -> #REF! | H34: =H18 -> #REF! | I34: =I18 -> #REF! | J34: =J18 -> #REF! | K34: =K18 -> #REF!
B35: # of sales agent needed | C35: =ROUNDUP(C34/$C$5,0) -> #REF! | D35: =ROUNDUP(D34/$C$5,0) -> #REF! | E35: =ROUNDUP(E34/$C$5,0) -> #REF! | F35: =ROUNDUP(F34/$C$5,0) -> #REF! | H35: =ROUNDUP(H34/$C$5,0) -> #REF! | I35: =ROUNDUP(I34/$C$5,0) -> #REF! | J35: =ROUNDUP(J34/$C$5,0) -> #REF! | K35: =ROUNDUP(K34/$C$5,0) -> #REF!
B36: Annual base salary | C36: =$C$6 -> 125000 | D36: =$C$6 -> 125000 | E36: =$C$6 -> 125000 | F36: =$C$6 -> 125000 | H36: =$C$6 -> 125000 | I36: =$C$6 -> 125000 | J36: =$C$6 -> 125000 | K36: =$C$6 -> 125000
B37: Commission $ per unit | C37: =$C$9 -> #REF! | D37: =$C$9 -> #REF! | E37: =$C$9 -> #REF! | F37: =$C$9 -> #REF! | H37: =$C$9 -> #REF! | I37: =$C$9 -> #REF! | J37: =$C$9 -> #REF! | K37: =$C$9 -> #REF!
B38: Total payroll expense (exluding benefits) | C38: =(C35*C36)+(C34*C37) -> #REF! | D38: =(D35*D36)+(D34*D37) -> #REF! | E38: =(E35*E36)+(E34*E37) -> #REF! | F38: =(F35*F36)+(F34*F37) -> #REF! | H38: =(H35*H36)+(H34*H37) -> #REF! | I38: =(I35*I36)+(I34*I37) -> #REF! | J38: =(J35*J36)+(J34*J37) -> #REF! | K38: =(K35*K36)+(K34*K37) -> #REF!
B40: Savings from hiring sales agent (a - b) | C40: =C32-C38 -> #REF! | D40: =D32-D38 -> #REF! | E40: =E32-E38 -> #REF! | F40: =F32-F38 -> #REF! | H40: =H32-H38 -> #REF! | I40: =I32-I38 -> #REF! | J40: =J32-J38 -> #REF! | K40: =K32-K38 -> #REF!

Sheet EXPORT >>
B2: This page intentionally blank

Sheet PROFORMA
A1: Balance Sheet | M1: Income Statement - Annual | O1: =O5/O3 -> 0.25206774 | Q1: =Q5/Q3 -> 0.25333328 | S1: =S5/S3 -> 0.25333333 | U1: =U5/U3 -> 0.25333334 | W1: =W5/W3 -> 0.25333333
A2: ="As at" -> As at | C2: =TEXT(FS.PRO!C8,"MMMM, DD, YYYY")&" (forecasted)" -> June, 30, 2026 (forecasted) | E2: =TEXT(FS.PRO!E8,"MMMM, DD, YYYY")&" (forecasted)" -> June, 30, 2027 (forecasted) | G2: =TEXT(FS.PRO!G8,"MMMM, DD, YYYY")&" (forecasted)" -> June, 30, 2028 (forecasted) | I2: =TEXT(FS.PRO!I8,"MMMM, DD, YYYY")&" (forecasted)" -> June, 30, 2029 (forecasted) | K2: =TEXT(FS.PRO!K8,"MMMM, DD, YYYY")&" (forecasted)" -> June, 30, 2030 (forecasted) | M2: For the years ended | O2: June, 30, 2026 (forecasted) | Q2: June, 30, 2027 (forecasted) | S2: June, 30, 2028 (forecasted) | U2: June, 30, 2029 (forecasted) | W2: June, 30, 2030 (forecasted) | AC2: Share Capital | AE2: Contributed Surplus | AG2: Accumulated Deficit | AI2: Total Shareholder's Equity
A3: ASSETS | M3: Sale of electric vehicle | N3: $ | O3: =_xlfn.XLOOKUP($M3,FS.PRO!$A:$A,FS.PRO!C:C,0,0,1) -> 507800 | P3: $ | Q3: =_xlfn.XLOOKUP($M3,FS.PRO!$A:$A,FS.PRO!E:E,0,0,1) -> 6531250 | R3: $ | S3: =_xlfn.XLOOKUP($M3,FS.PRO!$A:$A,FS.PRO!G:G,0,0,1) -> 29812500 | T3: $ | U3: =_xlfn.XLOOKUP($M3,FS.PRO!$A:$A,FS.PRO!I:I,0,0,1) -> 70812500 | V3: $ | W3: =_xlfn.XLOOKUP($M3,FS.PRO!$A:$A,FS.PRO!K:K,0,0,1) -> 124500000 | AA3: =FS.PRO!A102 -> Balance - June 30, 2025 | AB3: $ | AC3: =FS.PRO!C102 -> 8224099 | AD3: $ | AE3: =FS.PRO!E102 -> 308750 | AF3: $ | AG3: =FS.PRO!G102 -> -4977690 | AH3: $ | AI3: =ROUND(SUM(AC3:AG3),0) -> 3555159
A4: Current | M4: Cost of goods sold | N4: $ | O4: =_xlfn.XLOOKUP($M4,FS.PRO!$A:$A,FS.PRO!C:C,0,0,1) -> -379800 | P4: $ | Q4: =_xlfn.XLOOKUP($M4,FS.PRO!$A:$A,FS.PRO!E:E,0,0,1) -> -4876667 | R4: $ | S4: =_xlfn.XLOOKUP($M4,FS.PRO!$A:$A,FS.PRO!G:G,0,0,1) -> -22260000 | T4: $ | U4: =_xlfn.XLOOKUP($M4,FS.PRO!$A:$A,FS.PRO!I:I,0,0,1) -> -52873333 | V4: $ | W4: =_xlfn.XLOOKUP($M4,FS.PRO!$A:$A,FS.PRO!K:K,0,0,1) -> -92960000 | AA4: =FS.PRO!A103 -> Conversion of convertible debt to common shares | AC4: =FS.PRO!C103 -> 331121 | AE4: =FS.PRO!E103 -> 0 | AG4: =FS.PRO!G103 -> 0 | AI4: =ROUND(SUM(AC4:AG4),0) -> 331121
A5: =FS.1!A13 -> Cash | B5: $ | C5: =_xlfn.XLOOKUP($A5,FS.PRO!$A:$A,FS.PRO!C:C,0,0,1) -> 1942431 | D5: $ | E5: =_xlfn.XLOOKUP($A5,FS.PRO!$A:$A,FS.PRO!E:E,0,0,1) -> 1813362 | F5: $ | G5: =_xlfn.XLOOKUP($A5,FS.PRO!$A:$A,FS.PRO!G:G,0,0,1) -> 1408703 | H5: $ | I5: =_xlfn.XLOOKUP($A5,FS.PRO!$A:$A,FS.PRO!I:I,0,0,1) -> 9856641 | J5: $ | K5: =_xlfn.XLOOKUP($A5,FS.PRO!$A:$A,FS.PRO!K:K,0,0,1) -> 25432405 | M5: Gross profit (loss) | N5: $ | O5: =SUM(O3:O4) -> 128000 | P5: $ | Q5: =SUM(Q3:Q4) -> 1654583 | R5: $ | S5: =SUM(S3:S4) -> 7552500 | T5: $ | U5: =SUM(U3:U4) -> 17939167 | V5: $ | W5: =SUM(W3:W4) -> 31540000 | AA5: =FS.PRO!A104 -> Net loss for year | AC5: =FS.PRO!C104 -> 0 | AE5: =FS.PRO!E104 -> 0 | AG5: =FS.PRO!G104 -> -1831200 | AI5: =ROUND(SUM(AC5:AG5),0) -> -1831200
A6: =FS.PRO!A14 -> Receivables | C6: =_xlfn.XLOOKUP($A6,FS.PRO!$A:$A,FS.PRO!C:C,0,0,1) -> 18 | E6: =_xlfn.XLOOKUP($A6,FS.PRO!$A:$A,FS.PRO!E:E,0,0,1) -> 18 | G6: =_xlfn.XLOOKUP($A6,FS.PRO!$A:$A,FS.PRO!G:G,0,0,1) -> 18 | I6: =_xlfn.XLOOKUP($A6,FS.PRO!$A:$A,FS.PRO!I:I,0,0,1) -> 18 | K6: =_xlfn.XLOOKUP($A6,FS.PRO!$A:$A,FS.PRO!K:K,0,0,1) -> 18 | M6: Operating expenses | AA6: =FS.PRO!A105 -> Balance - June 30, 2026 | AB6: $ | AC6: =ROUND(SUM(AC3:AC5),0) -> 8555220 | AD6: $ | AE6: =ROUND(SUM(AE3:AE5),0) -> 308750 | AF6: $ | AG6: =ROUND(SUM(AG3:AG5),0) -> -6808890 | AH6: $ | AI6: =ROUND(SUM(AI3:AI5),0) -> 2055080
A7: =FS.PRO!A17 -> Inventory | C7: =_xlfn.XLOOKUP($A7,FS.PRO!$A:$A,FS.PRO!C:C,0,0,1) -> 159517 | E7: =_xlfn.XLOOKUP($A7,FS.PRO!$A:$A,FS.PRO!E:E,0,0,1) -> 602850 | G7: =_xlfn.XLOOKUP($A7,FS.PRO!$A:$A,FS.PRO!G:G,0,0,1) -> 2142850 | I7: =_xlfn.XLOOKUP($A7,FS.PRO!$A:$A,FS.PRO!I:I,0,0,1) -> 5269517 | K7: =_xlfn.XLOOKUP($A7,FS.PRO!$A:$A,FS.PRO!K:K,0,0,1) -> 10309517 | M7: =FS.PRO!A60 -> Bank fees | N7: $ | O7: =_xlfn.XLOOKUP($M7,FS.PRO!$A:$A,FS.PRO!C:C,0,0,1) -> 2074 | P7: $ | Q7: =_xlfn.XLOOKUP($M7,FS.PRO!$A:$A,FS.PRO!E:E,0,0,1) -> 2514 | R7: $ | S7: =_xlfn.XLOOKUP($M7,FS.PRO!$A:$A,FS.PRO!G:G,0,0,1) -> 2639 | T7: $ | U7: =_xlfn.XLOOKUP($M7,FS.PRO!$A:$A,FS.PRO!I:I,0,0,1) -> 2772 | V7: $ | W7: =_xlfn.XLOOKUP($M7,FS.PRO!$A:$A,FS.PRO!K:K,0,0,1) -> 2910 | AA7: Net loss for year | AC7: =FS.PRO!C106 -> 0 | AE7: =FS.PRO!E106 -> 0 | AG7: =FS.PRO!G106 -> -1647899 | AI7: =ROUND(SUM(AC7:AG7),0) -> -1647899
A8: =FS.1!A20 -> Total current assets | B8: $ | C8: =SUM(C5:C7) -> 2101966 | D8: $ | E8: =SUM(E5:E7) -> 2416230 | F8: $ | G8: =SUM(G5:G7) -> 3551571 | H8: $ | I8: =SUM(I5:I7) -> 15126176 | J8: $ | K8: =SUM(K5:K7) -> 35741940 | M8: =FS.PRO!A61 -> Professional fees | O8: =_xlfn.XLOOKUP($M8,FS.PRO!$A:$A,FS.PRO!C:C,0,0,1) -> 111500 | Q8: =_xlfn.XLOOKUP($M8,FS.PRO!$A:$A,FS.PRO!E:E,0,0,1) -> 90000 | S8: =_xlfn.XLOOKUP($M8,FS.PRO!$A:$A,FS.PRO!G:G,0,0,1) -> 90000 | U8: =_xlfn.XLOOKUP($M8,FS.PRO!$A:$A,FS.PRO!I:I,0,0,1) -> 108000 | W8: =_xlfn.XLOOKUP($M8,FS.PRO!$A:$A,FS.PRO!K:K,0,0,1) -> 129600 | AA8: =FS.PRO!A107 -> Balance - June 30, 2027 | AB8: $ | AC8: =SUM(AC6:AC7) -> 8555220 | AD8: $ | AE8: =SUM(AE6:AE7) -> 308750 | AF8: $ | AG8: =SUM(AG6:AG7) -> -8456789 | AH8: $ | AI8: =SUM(AI6:AI7) -> 407181
A9: =FS.1!A21 -> Non-current assets | M9: =FS.PRO!A62 -> Consulting expense | O9: =_xlfn.XLOOKUP($M9,FS.PRO!$A:$A,FS.PRO!C:C,0,0,1) -> 273417 | Q9: =_xlfn.XLOOKUP($M9,FS.PRO!$A:$A,FS.PRO!E:E,0,0,1) -> 276000 | S9: =_xlfn.XLOOKUP($M9,FS.PRO!$A:$A,FS.PRO!G:G,0,0,1) -> 276000 | U9: =_xlfn.XLOOKUP($M9,FS.PRO!$A:$A,FS.PRO!I:I,0,0,1) -> 276000 | W9: =_xlfn.XLOOKUP($M9,FS.PRO!$A:$A,FS.PRO!K:K,0,0,1) -> 276000 | AA9: Net loss for year | AC9: =FS.PRO!C108 -> 0 | AE9: =FS.PRO!E108 -> 0 | AG9: =FS.PRO!G108 -> 336928 | AI9: =ROUND(SUM(AC9:AG9),0) -> 336928
A10: =FS.PRO!A23 -> Equipment | C10: =_xlfn.XLOOKUP($A10,FS.PRO!$A:$A,FS.PRO!C:C,0,0,1) -> 3442 | E10: =_xlfn.XLOOKUP($A10,FS.PRO!$A:$A,FS.PRO!E:E,0,0,1) -> 3442 | G10: =_xlfn.XLOOKUP($A10,FS.PRO!$A:$A,FS.PRO!G:G,0,0,1) -> 3442 | I10: =_xlfn.XLOOKUP($A10,FS.PRO!$A:$A,FS.PRO!I:I,0,0,1) -> 3442 | K10: =_xlfn.XLOOKUP($A10,FS.PRO!$A:$A,FS.PRO!K:K,0,0,1) -> 3442 | M10: =FS.PRO!A63 -> Dues, licenses, and permits | O10: =_xlfn.XLOOKUP($M10,FS.PRO!$A:$A,FS.PRO!C:C,0,0,1) -> 2194 | Q10: =_xlfn.XLOOKUP($M10,FS.PRO!$A:$A,FS.PRO!E:E,0,0,1) -> 1812 | S10: =_xlfn.XLOOKUP($M10,FS.PRO!$A:$A,FS.PRO!G:G,0,0,1) -> 1849 | U10: =_xlfn.XLOOKUP($M10,FS.PRO!$A:$A,FS.PRO!I:I,0,0,1) -> 1886 | W10: =_xlfn.XLOOKUP($M10,FS.PRO!$A:$A,FS.PRO!K:K,0,0,1) -> 1923 | AA10: =FS.PRO!A109 -> Balance - June 30, 2028 | AB10: $ | AC10: =SUM(AC8:AC9) -> 8555220 | AD10: $ | AE10: =SUM(AE8:AE9) -> 308750 | AF10: $ | AG10: =SUM(AG8:AG9) -> -8119861 | AH10: $ | AI10: =SUM(AI8:AI9) -> 744109
A11: =FS.PRO!A24 -> Intangible assets | C11: =_xlfn.XLOOKUP($A11,FS.PRO!$A:$A,FS.PRO!C:C,0,0,1) -> 3015078 | E11: =_xlfn.XLOOKUP($A11,FS.PRO!$A:$A,FS.PRO!E:E,0,0,1) -> 1758714 | G11: =_xlfn.XLOOKUP($A11,FS.PRO!$A:$A,FS.PRO!G:G,0,0,1) -> 502350 | I11: =_xlfn.XLOOKUP($A11,FS.PRO!$A:$A,FS.PRO!I:I,0,0,1) -> 314091 | K11: =_xlfn.XLOOKUP($A11,FS.PRO!$A:$A,FS.PRO!K:K,0,0,1) -> 314091 | M11: =FS.PRO!A64 -> Advertising and marketing | O11: =_xlfn.XLOOKUP($M11,FS.PRO!$A:$A,FS.PRO!C:C,0,0,1) -> 78640 | Q11: =_xlfn.XLOOKUP($M11,FS.PRO!$A:$A,FS.PRO!E:E,0,0,1) -> 434250 | S11: =_xlfn.XLOOKUP($M11,FS.PRO!$A:$A,FS.PRO!G:G,0,0,1) -> 1671750 | U11: =_xlfn.XLOOKUP($M11,FS.PRO!$A:$A,FS.PRO!I:I,0,0,1) -> 3828000 | W11: =_xlfn.XLOOKUP($M11,FS.PRO!$A:$A,FS.PRO!K:K,0,0,1) -> 6640500 | AA11: Net income for year | AC11: =FS.PRO!C110 -> 0 | AE11: =FS.PRO!E110 -> 0 | AG11: =FS.PRO!G110 -> 5998846 | AI11: =ROUND(SUM(AC11:AG11),0) -> 5998846
A12: =FS.1!A26 -> Total non-current assets | B12: $ | C12: =SUM(C10:C11) -> 3018520 | D12: $ | E12: =SUM(E10:E11) -> 1762156 | F12: $ | G12: =SUM(G10:G11) -> 505792 | H12: $ | I12: =SUM(I10:I11) -> 317533 | J12: $ | K12: =SUM(K10:K11) -> 317533 | M12: =FS.PRO!A65 -> Meals and entertainment | O12: =_xlfn.XLOOKUP($M12,FS.PRO!$A:$A,FS.PRO!C:C,0,0,1) -> 3000 | Q12: =_xlfn.XLOOKUP($M12,FS.PRO!$A:$A,FS.PRO!E:E,0,0,1) -> 3300 | S12: =_xlfn.XLOOKUP($M12,FS.PRO!$A:$A,FS.PRO!G:G,0,0,1) -> 3630 | U12: =_xlfn.XLOOKUP($M12,FS.PRO!$A:$A,FS.PRO!I:I,0,0,1) -> 3993 | W12: =_xlfn.XLOOKUP($M12,FS.PRO!$A:$A,FS.PRO!K:K,0,0,1) -> 4392 | AA12: =FS.PRO!A111 -> Balance - June 30, 2029 | AB12: $ | AC12: =SUM(AC10:AC11) -> 8555220 | AD12: $ | AE12: =SUM(AE10:AE11) -> 308750 | AF12: $ | AG12: =SUM(AG10:AG11) -> -2121015 | AH12: $ | AI12: =SUM(AI10:AI11) -> 6742955
A13: =FS.1!A27 -> Total Assets | B13: $ | C13: =C12+C8 -> 5120486 | D13: $ | E13: =E12+E8 -> 4178386 | F13: $ | G13: =G12+G8 -> 4057363 | H13: $ | I13: =I12+I8 -> 15443709 | J13: $ | K13: =K12+K8 -> 36059473 | M13: =FS.PRO!A66 -> Travel expenses | O13: =_xlfn.XLOOKUP($M13,FS.PRO!$A:$A,FS.PRO!C:C,0,0,1) -> 6000 | Q13: =_xlfn.XLOOKUP($M13,FS.PRO!$A:$A,FS.PRO!E:E,0,0,1) -> 6600 | S13: =_xlfn.XLOOKUP($M13,FS.PRO!$A:$A,FS.PRO!G:G,0,0,1) -> 7260 | U13: =_xlfn.XLOOKUP($M13,FS.PRO!$A:$A,FS.PRO!I:I,0,0,1) -> 7986 | W13: =_xlfn.XLOOKUP($M13,FS.PRO!$A:$A,FS.PRO!K:K,0,0,1) -> 8785 | AA13: Net income for year | AC13: =FS.PRO!C112 -> 0 | AE13: =FS.PRO!E112 -> 0 | AG13: =FS.PRO!G112 -> 11765764 | AI13: =ROUND(SUM(AC13:AG13),0) -> 11765764
A14: LIABILITIES | M14: =FS.PRO!A67 -> Transfer agent and regulatory expenses | O14: =_xlfn.XLOOKUP($M14,FS.PRO!$A:$A,FS.PRO!C:C,0,0,1) -> 9000 | Q14: =_xlfn.XLOOKUP($M14,FS.PRO!$A:$A,FS.PRO!E:E,0,0,1) -> 9450 | S14: =_xlfn.XLOOKUP($M14,FS.PRO!$A:$A,FS.PRO!G:G,0,0,1) -> 9923 | U14: =_xlfn.XLOOKUP($M14,FS.PRO!$A:$A,FS.PRO!I:I,0,0,1) -> 10419 | W14: =_xlfn.XLOOKUP($M14,FS.PRO!$A:$A,FS.PRO!K:K,0,0,1) -> 10940 | AA14: =FS.PRO!A113 -> Balance - June 30, 2030 | AB14: $ | AC14: =SUM(AC12:AC13) -> 8555220 | AD14: $ | AE14: =SUM(AE12:AE13) -> 308750 | AF14: $ | AG14: =SUM(AG12:AG13) -> 9644749 | AH14: $ | AI14: =SUM(AI12:AI13) -> 18508719
A15: Current liabilities | M15: =FS.PRO!A68 -> Insurance | O15: =_xlfn.XLOOKUP($M15,FS.PRO!$A:$A,FS.PRO!C:C,0,0,1) -> 30204 | Q15: =_xlfn.XLOOKUP($M15,FS.PRO!$A:$A,FS.PRO!E:E,0,0,1) -> 31500 | S15: =_xlfn.XLOOKUP($M15,FS.PRO!$A:$A,FS.PRO!G:G,0,0,1) -> 33075 | U15: =_xlfn.XLOOKUP($M15,FS.PRO!$A:$A,FS.PRO!I:I,0,0,1) -> 34729 | W15: =_xlfn.XLOOKUP($M15,FS.PRO!$A:$A,FS.PRO!K:K,0,0,1) -> 36465
A16: =FS.PRO!A31 -> Accrued Warranty Liability | C16: =_xlfn.XLOOKUP($A16,FS.PRO!$A:$A,FS.PRO!C:C,0,0,1) -> 64506 | E16: =_xlfn.XLOOKUP($A16,FS.PRO!$A:$A,FS.PRO!E:E,0,0,1) -> 176555 | G16: =_xlfn.XLOOKUP($A16,FS.PRO!$A:$A,FS.PRO!G:G,0,0,1) -> 656104 | I16: =_xlfn.XLOOKUP($A16,FS.PRO!$A:$A,FS.PRO!I:I,0,0,1) -> 1856104 | K16: =_xlfn.XLOOKUP($A16,FS.PRO!$A:$A,FS.PRO!K:K,0,0,1) -> 3956104 | M16: =FS.PRO!A69 -> Office expenses | O16: =_xlfn.XLOOKUP($M16,FS.PRO!$A:$A,FS.PRO!C:C,0,0,1) -> 24589 | Q16: =_xlfn.XLOOKUP($M16,FS.PRO!$A:$A,FS.PRO!E:E,0,0,1) -> 26400 | S16: =_xlfn.XLOOKUP($M16,FS.PRO!$A:$A,FS.PRO!G:G,0,0,1) -> 29040 | U16: =_xlfn.XLOOKUP($M16,FS.PRO!$A:$A,FS.PRO!I:I,0,0,1) -> 31944 | W16: =_xlfn.XLOOKUP($M16,FS.PRO!$A:$A,FS.PRO!K:K,0,0,1) -> 35138 | AA16: CHECK | AC16: =FS.PRO!C105-AC6 -> 0 | AE16: =FS.PRO!E105-AE6 -> 0 | AG16: =FS.PRO!G105-AG6 -> 0 | AI16: =FS.PRO!I105-AI6 -> 0
A17: =FS.PRO!A33 -> Deferred revenue | C17: =_xlfn.XLOOKUP($A17,FS.PRO!$A:$A,FS.PRO!C:C,0,0,1) -> 0 | E17: =_xlfn.XLOOKUP($A17,FS.PRO!$A:$A,FS.PRO!E:E,0,0,1) -> 593750 | G17: =_xlfn.XLOOKUP($A17,FS.PRO!$A:$A,FS.PRO!G:G,0,0,1) -> 2656250 | I17: =_xlfn.XLOOKUP($A17,FS.PRO!$A:$A,FS.PRO!I:I,0,0,1) -> 6843750 | K17: =_xlfn.XLOOKUP($A17,FS.PRO!$A:$A,FS.PRO!K:K,0,0,1) -> 13593750 | M17: =FS.PRO!A70 -> Selling expense | O17: =_xlfn.XLOOKUP($M17,FS.PRO!$A:$A,FS.PRO!C:C,0,0,1) -> 0 | Q17: =_xlfn.XLOOKUP($M17,FS.PRO!$A:$A,FS.PRO!E:E,0,0,1) -> 60000 | S17: =_xlfn.XLOOKUP($M17,FS.PRO!$A:$A,FS.PRO!G:G,0,0,1) -> 1275000 | U17: =_xlfn.XLOOKUP($M17,FS.PRO!$A:$A,FS.PRO!I:I,0,0,1) -> 3000000 | W17: =_xlfn.XLOOKUP($M17,FS.PRO!$A:$A,FS.PRO!K:K,0,0,1) -> 5250000 | AA17: CHECK | AC17: =FS.PRO!C107-AC8 -> 0 | AE17: =FS.PRO!E107-AE8 -> 0 | AG17: =FS.PRO!G107-AG8 -> 0 | AI17: =FS.PRO!I107-AI8 -> 0
A18: =FS.PRO!A34 -> Due to related parties | C18: =_xlfn.XLOOKUP($A18,FS.PRO!$A:$A,FS.PRO!C:C,0,0,1) -> 900 | E18: =_xlfn.XLOOKUP($A18,FS.PRO!$A:$A,FS.PRO!E:E,0,0,1) -> 900 | G18: =_xlfn.XLOOKUP($A18,FS.PRO!$A:$A,FS.PRO!G:G,0,0,1) -> 900 | I18: =_xlfn.XLOOKUP($A18,FS.PRO!$A:$A,FS.PRO!I:I,0,0,1) -> 900 | K18: =_xlfn.XLOOKUP($A18,FS.PRO!$A:$A,FS.PRO!K:K,0,0,1) -> 900 | M18: =FS.PRO!A71 -> Shipping expense | O18: =_xlfn.XLOOKUP($M18,FS.PRO!$A:$A,FS.PRO!C:C,0,0,1) -> 6000 | Q18: =_xlfn.XLOOKUP($M18,FS.PRO!$A:$A,FS.PRO!E:E,0,0,1) -> 142500 | S18: =_xlfn.XLOOKUP($M18,FS.PRO!$A:$A,FS.PRO!G:G,0,0,1) -> 637500 | U18: =_xlfn.XLOOKUP($M18,FS.PRO!$A:$A,FS.PRO!I:I,0,0,1) -> 1500000 | W18: =_xlfn.XLOOKUP($M18,FS.PRO!$A:$A,FS.PRO!K:K,0,0,1) -> 2625000 | AA18: CHECK | AC18: =FS.PRO!C109-AC10 -> 0 | AE18: =FS.PRO!E109-AE10 -> 0 | AG18: =FS.PRO!G109-AG10 -> 0 | AI18: =FS.PRO!I109-AI10 -> 0
A19: =FS.1!A37 -> Non-current liabilities | B19: $ | C19: =SUM(C16:C18) -> 65406 | D19: $ | E19: =SUM(E16:E18) -> 771205 | F19: $ | G19: =SUM(G16:G18) -> 3313254 | H19: $ | I19: =SUM(I16:I18) -> 8700754 | J19: $ | K19: =SUM(K16:K18) -> 17550754 | M19: =FS.PRO!A72 -> Shop supplies | O19: =_xlfn.XLOOKUP($M19,FS.PRO!$A:$A,FS.PRO!C:C,0,0,1) -> 3633 | Q19: =_xlfn.XLOOKUP($M19,FS.PRO!$A:$A,FS.PRO!E:E,0,0,1) -> 86292 | S19: =_xlfn.XLOOKUP($M19,FS.PRO!$A:$A,FS.PRO!G:G,0,0,1) -> 386042 | U19: =_xlfn.XLOOKUP($M19,FS.PRO!$A:$A,FS.PRO!I:I,0,0,1) -> 908333 | W19: =_xlfn.XLOOKUP($M19,FS.PRO!$A:$A,FS.PRO!K:K,0,0,1) -> 1589583 | AA19: CHECK | AC19: =FS.PRO!C111-AC12 -> 0 | AE19: =FS.PRO!E111-AE12 -> 0 | AG19: =FS.PRO!G111-AG12 -> 0 | AI19: =FS.PRO!I111-AI12 -> 0
A20: =FS.PRO!A39 -> Loans and borrowings | C20: =_xlfn.XLOOKUP($A20,FS.PRO!$A:$A,FS.PRO!C:C,0,0,1) -> 3000000 | E20: =_xlfn.XLOOKUP($A20,FS.PRO!$A:$A,FS.PRO!E:E,0,0,1) -> 3000000 | G20: =_xlfn.XLOOKUP($A20,FS.PRO!$A:$A,FS.PRO!G:G,0,0,1) -> 0 | I20: =_xlfn.XLOOKUP($A20,FS.PRO!$A:$A,FS.PRO!I:I,0,0,1) -> 0 | K20: =_xlfn.XLOOKUP($A20,FS.PRO!$A:$A,FS.PRO!K:K,0,0,1) -> 0 | M20: =FS.PRO!A73 -> Warranty expense | O20: =_xlfn.XLOOKUP($M20,FS.PRO!$A:$A,FS.PRO!C:C,0,0,1) -> 9756 | Q20: =_xlfn.XLOOKUP($M20,FS.PRO!$A:$A,FS.PRO!E:E,0,0,1) -> 142500 | S20: =_xlfn.XLOOKUP($M20,FS.PRO!$A:$A,FS.PRO!G:G,0,0,1) -> 637500 | U20: =_xlfn.XLOOKUP($M20,FS.PRO!$A:$A,FS.PRO!I:I,0,0,1) -> 1500000 | W20: =_xlfn.XLOOKUP($M20,FS.PRO!$A:$A,FS.PRO!K:K,0,0,1) -> 2625000 | AA20: CHECK | AC20: =FS.PRO!C113-AC14 -> 0 | AE20: =FS.PRO!E113-AE14 -> 0 | AG20: =FS.PRO!G113-AG14 -> 0 | AI20: =FS.PRO!I113-AI14 -> 0
A21: =FS.1!A39 -> Total Liabilities | C21: =SUM(C19:C20) -> 3065406 | E21: =SUM(E19:E20) -> 3771205 | G21: =SUM(G19:G20) -> 3313254 | I21: =SUM(I19:I20) -> 8700754 | K21: =SUM(K19:K20) -> 17550754 | M21: =FS.PRO!A74 -> Amortization expense | O21: =_xlfn.XLOOKUP($M21,FS.PRO!$A:$A,FS.PRO!C:C,0,0,1) -> 1256364 | Q21: =_xlfn.XLOOKUP($M21,FS.PRO!$A:$A,FS.PRO!E:E,0,0,1) -> 1256364 | S21: =_xlfn.XLOOKUP($M21,FS.PRO!$A:$A,FS.PRO!G:G,0,0,1) -> 1256364 | U21: =_xlfn.XLOOKUP($M21,FS.PRO!$A:$A,FS.PRO!I:I,0,0,1) -> 188259 | W21: =_xlfn.XLOOKUP($M21,FS.PRO!$A:$A,FS.PRO!K:K,0,0,1) -> 0
A22: SHAREHOLDERS’ EQUITY | M22: =FS.PRO!A75 -> Foreign exchange | O22: =_xlfn.XLOOKUP($M22,FS.PRO!$A:$A,FS.PRO!C:C,0,0,1) -> -69 | Q22: =_xlfn.XLOOKUP($M22,FS.PRO!$A:$A,FS.PRO!E:E,0,0,1) -> 0 | S22: =_xlfn.XLOOKUP($M22,FS.PRO!$A:$A,FS.PRO!G:G,0,0,1) -> 0 | U22: =_xlfn.XLOOKUP($M22,FS.PRO!$A:$A,FS.PRO!I:I,0,0,1) -> 0 | W22: =_xlfn.XLOOKUP($M22,FS.PRO!$A:$A,FS.PRO!K:K,0,0,1) -> 0
A23: =FS.1!A41 -> Share capital | B23: $ | C23: =_xlfn.XLOOKUP($A23,FS.PRO!$A:$A,FS.PRO!C:C,0,0,1) -> 8555220 | D23: $ | E23: =_xlfn.XLOOKUP($A23,FS.PRO!$A:$A,FS.PRO!E:E,0,0,1) -> 8555220 | F23: $ | G23: =_xlfn.XLOOKUP($A23,FS.PRO!$A:$A,FS.PRO!G:G,0,0,1) -> 8555220 | H23: $ | I23: =_xlfn.XLOOKUP($A23,FS.PRO!$A:$A,FS.PRO!I:I,0,0,1) -> 8555220 | J23: $ | K23: =_xlfn.XLOOKUP($A23,FS.PRO!$A:$A,FS.PRO!K:K,0,0,1) -> 8555220 | M23: =FS.PRO!A76 -> Rent | O23: =_xlfn.XLOOKUP($M23,FS.PRO!$A:$A,FS.PRO!C:C,0,0,1) -> 12000 | Q23: =_xlfn.XLOOKUP($M23,FS.PRO!$A:$A,FS.PRO!E:E,0,0,1) -> 63000 | S23: =_xlfn.XLOOKUP($M23,FS.PRO!$A:$A,FS.PRO!G:G,0,0,1) -> 228000 | U23: =_xlfn.XLOOKUP($M23,FS.PRO!$A:$A,FS.PRO!I:I,0,0,1) -> 228000 | W23: =_xlfn.XLOOKUP($M23,FS.PRO!$A:$A,FS.PRO!K:K,0,0,1) -> 228000
A24: =FS.1!A42 -> Contributed surplus | C24: =_xlfn.XLOOKUP($A24,FS.PRO!$A:$A,FS.PRO!C:C,0,0,1) -> 308750 | E24: =_xlfn.XLOOKUP($A24,FS.PRO!$A:$A,FS.PRO!E:E,0,0,1) -> 308750 | G24: =_xlfn.XLOOKUP($A24,FS.PRO!$A:$A,FS.PRO!G:G,0,0,1) -> 308750 | I24: =_xlfn.XLOOKUP($A24,FS.PRO!$A:$A,FS.PRO!I:I,0,0,1) -> 308750 | K24: =_xlfn.XLOOKUP($A24,FS.PRO!$A:$A,FS.PRO!K:K,0,0,1) -> 308750 | M24: =FS.PRO!A77 -> Research and development | O24: =_xlfn.XLOOKUP($M24,FS.PRO!$A:$A,FS.PRO!C:C,0,0,1) -> 0 | Q24: =_xlfn.XLOOKUP($M24,FS.PRO!$A:$A,FS.PRO!E:E,0,0,1) -> 310000 | S24: =_xlfn.XLOOKUP($M24,FS.PRO!$A:$A,FS.PRO!G:G,0,0,1) -> 310000 | U24: =_xlfn.XLOOKUP($M24,FS.PRO!$A:$A,FS.PRO!I:I,0,0,1) -> 310000 | W24: =_xlfn.XLOOKUP($M24,FS.PRO!$A:$A,FS.PRO!K:K,0,0,1) -> 310000
A25: =FS.1!A43 -> Accumulated deficit | C25: =_xlfn.XLOOKUP($A25,FS.PRO!$A:$A,FS.PRO!C:C,0,0,1) -> -6808890 | E25: =_xlfn.XLOOKUP($A25,FS.PRO!$A:$A,FS.PRO!E:E,0,0,1) -> -8456789 | G25: =_xlfn.XLOOKUP($A25,FS.PRO!$A:$A,FS.PRO!G:G,0,0,1) -> -8119861 | I25: =_xlfn.XLOOKUP($A25,FS.PRO!$A:$A,FS.PRO!I:I,0,0,1) -> -2121015 | K25: =_xlfn.XLOOKUP($A25,FS.PRO!$A:$A,FS.PRO!K:K,0,0,1) -> 9644749 | M25: Total operating expenses | N25: $ | O25: =-SUM(O7:O24) -> -1828302 | P25: $ | Q25: =-SUM(Q7:Q24) -> -2942482 | R25: $ | S25: =-SUM(S7:S24) -> -6855572 | T25: $ | U25: =-SUM(U7:U24) -> -11940321 | V25: $ | W25: =-SUM(W7:W24) -> -19774236
A26: TOTAL SHAREHOLDERS’ EQUITY | B26: $ | C26: =SUM(C23:C25) -> 2055080 | D26: $ | E26: =SUM(E23:E25) -> 407181 | F26: $ | G26: =SUM(G23:G25) -> 744109 | H26: $ | I26: =SUM(I23:I25) -> 6742955 | J26: $ | K26: =SUM(K23:K25) -> 18508719 | M26: Net operating income / (loss) | N26: $ | O26: =SUM(O5,O25) -> -1700302 | P26: $ | Q26: =SUM(Q5,Q25) -> -1287899 | R26: $ | S26: =SUM(S5,S25) -> 696928 | T26: $ | U26: =SUM(U5,U25) -> 5998846 | V26: $ | W26: =SUM(W5,W25) -> 11765764
A27: TOTAL LIABILITIES AND SHAREHOLDERS’ EQUITY | B27: $ | C27: =C26+C21 -> 5120486 | D27: $ | E27: =E26+E21 -> 4178386 | F27: $ | G27: =G26+G21 -> 4057363 | H27: $ | I27: =I26+I21 -> 15443709 | J27: $ | K27: =K26+K21 -> 36059473 | M27: =FS.PRO!A81 -> Other income (expenses)
M28: Other income | O28: =_xlfn.XLOOKUP($M28,FS.PRO!$A:$A,FS.PRO!C:C,0,0,1) -> 47085 | Q28: =_xlfn.XLOOKUP($M28,FS.PRO!$A:$A,FS.PRO!E:E,0,0,1) -> 0 | S28: =_xlfn.XLOOKUP($M28,FS.PRO!$A:$A,FS.PRO!G:G,0,0,1) -> 0 | U28: =_xlfn.XLOOKUP($M28,FS.PRO!$A:$A,FS.PRO!I:I,0,0,1) -> 0 | W28: =_xlfn.XLOOKUP($M28,FS.PRO!$A:$A,FS.PRO!K:K,0,0,1) -> 0
A29: CHECK | C29: =FS.PRO!C47-C27 -> 0 | E29: =FS.PRO!E47-E27 -> 0 | G29: =FS.PRO!G47-G27 -> 0 | I29: =FS.PRO!I47-I27 -> 0 | K29: =FS.PRO!K47-K27 -> 0 | M29: =FS.PRO!A84 -> Net financial expenses | O29: =_xlfn.XLOOKUP($M29,FS.PRO!$A:$A,FS.PRO!C:C,0,0,1) -> -36210 | Q29: =_xlfn.XLOOKUP($M29,FS.PRO!$A:$A,FS.PRO!E:E,0,0,1) -> 0 | S29: =_xlfn.XLOOKUP($M29,FS.PRO!$A:$A,FS.PRO!G:G,0,0,1) -> 0 | U29: =_xlfn.XLOOKUP($M29,FS.PRO!$A:$A,FS.PRO!I:I,0,0,1) -> 0 | W29: =_xlfn.XLOOKUP($M29,FS.PRO!$A:$A,FS.PRO!K:K,0,0,1) -> 0
A30: CHECK | C30: =C27-C13 -> 0 | E30: =E27-E13 -> 0 | G30: =G27-G13 -> 0 | I30: =I27-I13 -> 0 | K30: =K27-K13 -> 0 | M30: =FS.PRO!A86 -> Interest expense | O30: =_xlfn.XLOOKUP($M30,FS.PRO!$A:$A,FS.PRO!C:C,0,0,1) -> -141773 | Q30: =_xlfn.XLOOKUP($M30,FS.PRO!$A:$A,FS.PRO!E:E,0,0,1) -> -360000 | S30: =_xlfn.XLOOKUP($M30,FS.PRO!$A:$A,FS.PRO!G:G,0,0,1) -> -360000 | U30: =_xlfn.XLOOKUP($M30,FS.PRO!$A:$A,FS.PRO!I:I,0,0,1) -> 0 | W30: =_xlfn.XLOOKUP($M30,FS.PRO!$A:$A,FS.PRO!K:K,0,0,1) -> 0
M31: Income (loss) before tax | N31: $ | O31: =SUM(O26:O30) -> -1831200 | P31: $ | Q31: =SUM(Q26:Q30) -> -1647899 | R31: $ | S31: =SUM(S26:S30) -> 336928 | T31: $ | U31: =SUM(U26:U30) -> 5998846 | V31: $ | W31: =SUM(W26:W30) -> 11765764
M32: CHECK | O32: =FS.PRO!C91-O31 -> 0 | Q32: =FS.PRO!E91-Q31 -> 0 | S32: =FS.PRO!G91-S31 -> 0 | U32: =FS.PRO!I91-U31 -> 0 | W32: =FS.PRO!K91-W31 -> 0

Sheet BS & IS
A1: Balance Sheet | G1: Income Statement - Annual | M1: Income Statement - Interim | W1: PROFORMA BS | AG1: PROFORMA ADJ
A2: ="As at" -> As at | B2: Notes | D2: =FS.1!C10 -> June 30, 2025 | F2: =FS.1!E8 -> June 30, 2024 | G2: For the year ended | H2: Notes | J2: =FS.1!G53 -> June 30, 2025 | L2: =FS.1!I53 -> June 30, 2024 | O2: Three-months ended | S2: Six-months ended | W2: As at | X2: Notes | Z2: June 30, 2024 (unaudited) | AB2: June 30, 2025 (unaudited) | AD2: June 30, 2026 (forecasted) | AG2: ADJ 1 | AH2: ADJ 2 | AI2: ADJ 3 | AJ2: ADJ 4 | AK2: ADJ 5 | AL2: ADJ 6 | AM2: SUM
A3: ASSETS | G3: Vehicle sales | I3: $ | J3: =FS.1!G54 -> 360000 | K3: $ | L3: =FS.1!I54 -> 0 | M3: For the period | N3: Notes | P3: =FS.1!C53 -> June 30, 2025 | R3: =FS.1!E53 -> June 30, 2024 | T3: =FS.1!G53 -> June 30, 2025 | V3: =FS.1!I53 -> June 30, 2024 | W3: ASSETS
A4: Current | G4: Cost of sales | I4: $ | J4: =FS.1!G55 -> -328158 | K4: $ | L4: =FS.1!I55 -> 0 | W4: Current | AM4: =SUM(AG4:AL4) -> 0
A5: =FS.1!A13 -> Cash | C5: $ | D5: =_xlfn.XLOOKUP(A5,FS.1!A11:A46,FS.1!C11:C46,0,0,1) -> 392 | E5: $ | F5: =_xlfn.XLOOKUP(A5,FS.1!$A$11:$A$46,FS.1!$E$11:$E$46,0,0,1) -> 5604 | G5: Gross profit (loss) | I5: $ | J5: =SUM(J3:J4) -> 31842 | K5: $ | L5: =SUM(L3:L4) -> 0 | M5: Operating expenses | W5: Cash | Y5: $ | Z5: =F5 -> 5604 | AA5: $ | AB5: =D5 -> 392 | AC5: $ | AD5: =AB5+AM5 -> 3744 | AG5: =AG46 -> 1014800 | AH5: =-AH18 -> -720000 | AI5: =-AI18 -> -280000 | AJ5: =-SUM(AJ47:AJ58) -> -5448 | AL5: =-SUM(AL47:AL58) -> -6000 | AM5: =SUM(AG5:AL5) -> 3352
A6: Sales tax receivable | D6: =_xlfn.XLOOKUP(A6,FS.1!A12:A47,FS.1!C12:C47,0,0,1) -> 37905 | F6: =_xlfn.XLOOKUP(A6,FS.1!$A$11:$A$46,FS.1!$E$11:$E$46,0,0,1) -> 30450 | G6: Operating expenses | M6: =G7 -> General and administration | N6: 13 | O6: $ | P6: =_xlfn.XLOOKUP($M6,FS.1!$A$54:$A$78,FS.1!C$54:C$78,0,0,1) -> 0 | Q6: $ | R6: =_xlfn.XLOOKUP($M6,FS.1!$A$54:$A$78,FS.1!E$54:E$78,0,0,1) -> 0 | S6: $ | T6: =_xlfn.XLOOKUP($M6,FS.1!$A$54:$A$78,FS.1!G$54:G$78,0,0,1) -> 1755445 | U6: $ | V6: =_xlfn.XLOOKUP($M6,FS.1!$A$54:$A$78,FS.1!I$54:I$78,0,0,1) -> #REF! | W6: Sales tax receivable | Z6: =F6 -> 30450 | AB6: =D6 -> 37905 | AD6: =AB6+AM6 -> 37905 | AM6: =SUM(AG6:AL6) -> 0
A7: =FS.1!A17 -> Inventory | B7: 8 | D7: =_xlfn.XLOOKUP(A7,FS.1!A13:A48,FS.1!C13:C48,0,0,1) -> 161256 | F7: =_xlfn.XLOOKUP(A7,FS.1!$A$11:$A$46,FS.1!$E$11:$E$46,0,0,1) -> 452364 | G7: =FS.1!A59 -> General and administration | H7: 9 | I7: $ | J7: =_xlfn.XLOOKUP(G7,FS.1!$A$54:$A$73,FS.1!$G$54:$G$73,0,0,1) -> 1755445 | K7: $ | L7: =_xlfn.XLOOKUP(G7,FS.1!$A$54:$A$73,FS.1!$I$54:$I$73,0,0,1) -> #REF! | M7: =G8 -> Sales and marketing | N7: 13 | P7: =_xlfn.XLOOKUP($M7,FS.1!$A$54:$A$78,FS.1!C$54:C$78,0,0,1) -> 0 | R7: =_xlfn.XLOOKUP($M7,FS.1!$A$54:$A$78,FS.1!E$54:E$78,0,0,1) -> 0 | T7: =_xlfn.XLOOKUP($M7,FS.1!$A$54:$A$78,FS.1!G$54:G$78,0,0,1) -> 70958 | V7: =_xlfn.XLOOKUP($M7,FS.1!$A$54:$A$78,FS.1!I$54:I$78,0,0,1) -> #REF! | W7: Inventory | X7: 8 | Z7: =F7 -> 452364 | AB7: =D7 -> 161256 | AD7: =AB7+AM7 -> 141256 | AK7: =-AK55 -> -20000 | AM7: =SUM(AG7:AL7) -> -20000
A8: =FS.1!A20 -> Total current assets | C8: $ | D8: =SUM(D5:D7) -> 199553 | E8: $ | F8: =SUM(F5:F7) -> 488418 | G8: =FS.1!A60 -> Sales and marketing | J8: =_xlfn.XLOOKUP(G8,FS.1!$A$54:$A$73,FS.1!$G$54:$G$73,0,0,1) -> 70958 | L8: =_xlfn.XLOOKUP(G8,FS.1!$A$54:$A$73,FS.1!$I$54:$I$73,0,0,1) -> #REF! | M8: Loss from operating activities | O8: $ | P8: =-SUM(P6:P7) -> 0 | Q8: $ | R8: =-SUM(R6:R7) -> 0 | S8: $ | T8: =-SUM(T6:T7) -> -1826403 | U8: $ | V8: =-SUM(V6:V7) -> #REF! | W8: Total current assets | Y8: $ | Z8: =SUM(Z5:Z7) -> 488418 | AA8: $ | AB8: =SUM(AB5:AB7) -> 199553 | AC8: $ | AD8: =SUM(AD5:AD7) -> 182905 | AM8: =SUM(AG8:AL8) -> 0
G9: Operating loss | I9: $ | J9: =J5-SUM(J6:J8) -> -1794561 | K9: $ | L9: =L5-SUM(L6:L8) -> #REF! | AM9: =SUM(AG9:AL9) -> 0
A10: =FS.1!A21 -> Non-current assets | G10: =FS.1!A63 -> Other income (expenses) | M10: =G10 -> Other income (expenses) | W10: Non-current assets | AM10: =SUM(AG10:AL10) -> 0
A11: =FS.1!A23 -> Equipment | D11: =_xlfn.XLOOKUP(A11,FS.1!A18:A53,FS.1!C18:C53,0,0,1) -> 5341 | F11: =_xlfn.XLOOKUP(A11,FS.1!$A$11:$A$46,FS.1!$E$11:$E$46,0,0,1) -> 5341 | G11: =FS.1!A64 -> Other income | J11: =_xlfn.XLOOKUP(G11,FS.1!$A$54:$A$73,FS.1!$G$54:$G$73,0,0,1) -> 0 | L11: =_xlfn.XLOOKUP(G11,FS.1!$A$54:$A$73,FS.1!$I$54:$I$73,0,0,1) -> 3150 | M11: =G12 -> Interest income | P11: =_xlfn.XLOOKUP($M11,FS.1!$A$54:$A$78,FS.1!C$54:C$78,0,0,1) -> 0 | R11: =_xlfn.XLOOKUP($M11,FS.1!$A$54:$A$78,FS.1!E$54:E$78,0,0,1) -> 0 | T11: =_xlfn.XLOOKUP($M11,FS.1!$A$54:$A$78,FS.1!G$54:G$78,0,0,1) -> 14 | V11: =_xlfn.XLOOKUP($M11,FS.1!$A$54:$A$78,FS.1!I$54:I$78,0,0,1) -> #REF! | W11: Equipment | Z11: =F11 -> 5341 | AB11: =D11 -> 5341 | AD11: =AB11+AM11 -> 5341 | AM11: =SUM(AG11:AL11) -> 0
A12: =FS.1!A24 -> Intangible assets | B12: 4,5 | D12: =_xlfn.XLOOKUP(A12,FS.1!A19:A54,FS.1!C19:C54,0,0,1) -> 4271442 | F12: =_xlfn.XLOOKUP(A12,FS.1!$A$11:$A$46,FS.1!$E$11:$E$46,0,0,1) -> 5527806 | G12: =FS.1!A65 -> Interest income | J12: =_xlfn.XLOOKUP(G12,FS.1!$A$54:$A$73,FS.1!$G$54:$G$73,0,0,1) -> 14 | L12: =_xlfn.XLOOKUP(G12,FS.1!$A$54:$A$73,FS.1!$I$54:$I$73,0,0,1) -> #REF! | M12: =G13 -> Net financial expenses | N12: 10 | P12: =_xlfn.XLOOKUP($M12,FS.1!$A$54:$A$78,FS.1!C$54:C$78,0,0,1) -> 0 | R12: =_xlfn.XLOOKUP($M12,FS.1!$A$54:$A$78,FS.1!E$54:E$78,0,0,1) -> 0 | T12: =_xlfn.XLOOKUP($M12,FS.1!$A$54:$A$78,FS.1!G$54:G$78,0,0,1) -> -31957 | V12: =_xlfn.XLOOKUP($M12,FS.1!$A$54:$A$78,FS.1!I$54:I$78,0,0,1) -> 50062 | W12: Intangible assets | X12: 4,5 | Z12: =F12 -> 5527806 | AB12: =D12 -> 4271442 | AD12: =AB12+AM12 -> 3015078 | AK12: =-AK50 -> -1256364 | AM12: =SUM(AG12:AL12) -> -1256364
A13: =FS.1!A26 -> Total non-current assets | C13: $ | D13: =SUM(D11:D12) -> 4276783 | E13: $ | F13: =SUM(F11:F12) -> 5533147 | G13: Net financial expenses | H13: 10 | J13: =_xlfn.XLOOKUP(G13,FS.1!$A$54:$A$73,FS.1!$G$54:$G$73,0,0,1) -> -31957 | L13: =_xlfn.XLOOKUP(G13,FS.1!$A$54:$A$73,FS.1!$I$54:$I$73,0,0,1) -> 50062 | M13: =G14 -> Interest expense | N13: 10 | P13: =_xlfn.XLOOKUP($M13,FS.1!$A$54:$A$78,FS.1!C$54:C$78,0,0,1) -> 0 | R13: =_xlfn.XLOOKUP($M13,FS.1!$A$54:$A$78,FS.1!E$54:E$78,0,0,1) -> 0 | T13: =_xlfn.XLOOKUP($M13,FS.1!$A$54:$A$78,FS.1!G$54:G$78,0,0,1) -> -45232 | V13: =_xlfn.XLOOKUP($M13,FS.1!$A$54:$A$78,FS.1!I$54:I$78,0,0,1) -> -33787 | W13: Total non-current assets | Y13: $ | Z13: =SUM(Z11:Z12) -> 5533147 | AA13: $ | AB13: =SUM(AB11:AB12) -> 4276783 | AC13: $ | AD13: =SUM(AD11:AD12) -> 3020419 | AM13: =SUM(AG13:AL13) -> 0
A14: =FS.1!A27 -> Total Assets | C14: $ | D14: =D13+D8 -> 4476336 | E14: $ | F14: =F13+F8 -> 6021565 | G14: =FS.1!A68 -> Interest expense | H14: 7 | J14: =_xlfn.XLOOKUP(G14,FS.1!$A$54:$A$73,FS.1!$G$54:$G$73,0,0,1) -> -45232 | L14: =_xlfn.XLOOKUP(G14,FS.1!$A$54:$A$73,FS.1!$I$54:$I$73,0,0,1) -> -33787 | M14: Loss and comprehensive loss | O14: $ | P14: =SUM(P8:P13) -> 0 | Q14: $ | R14: =SUM(R8:R13) -> 0 | S14: $ | T14: =SUM(T8:T13) -> -1903578 | U14: $ | V14: =SUM(V8:V13) -> #REF! | W14: Total Assets | Y14: $ | Z14: =Z13+Z8 -> 6021565 | AA14: $ | AB14: =AB13+AB8 -> 4476336 | AC14: $ | AD14: =AD13+AD8 -> 3203324 | AM14: =SUM(AG14:AL14) -> 0
G15: Net Loss and comprehensive loss | I15: $ | J15: =SUM(J9:J14) -> -1871736 | K15: $ | L15: =SUM(L9:L14) -> #REF! | AM15: =SUM(AG15:AL15) -> 0
A16: LIABILITIES | M16: Basic and diluted loss per common share | O16: $ | P16: =P14/P17 -> 0 | Q16: $ | R16: =R14/R17 -> 0 | S16: $ | T16: =T14/T17 -> -0.061135383 | U16: $ | V16: =V14/V17 -> #REF! | W16: LIABILITIES | AM16: =SUM(AG16:AL16) -> 0
A17: Current liabilities | G17: CHECK | J17: =FS.1!G73-J15 -> 0 | L17: =FS.1!I73-L15 -> #REF! | M17: Weighted average number of common shares outstanding - basic and diluted | P17: =FS.1!C78 -> 31912501 | R17: =FS.1!E78 -> 6542479 | T17: =FS.1!G78 -> 31137091 | V17: =FS.1!I78 -> 6486787.3 | W17: Current liabilities | AM17: =SUM(AG17:AL17) -> 0
A18: =FS.1!A30 -> Accounts payables and accrued liabilities | C18: $ | D18: =_xlfn.XLOOKUP(A18,FS.1!A25:A60,FS.1!C25:C60,0,0,1) -> 603276 | E18: $ | F18: =_xlfn.XLOOKUP(A18,FS.1!$A$11:$A$46,FS.1!$E$11:$E$46,0,0,1) -> 349791 | W18: Accounts payables and accrued liabilities | Y18: $ | Z18: =F18 -> 349791 | AA18: $ | AB18: =D18 -> 603276 | AC18: $ | AD18: =AB18-AM18 -> 656276 | AG18: =-SUM(AG47:AG51) -> -1053000 | AH18: =AG47 -> 720000 | AI18: 280000 | AM18: =SUM(AG18:AL18) -> -53000
A19: =FS.1!A32 -> Convertible debt | B19: 7 | D19: =_xlfn.XLOOKUP(A19,FS.1!A26:A61,FS.1!C26:C61,0,0,1) -> 274099 | F19: =_xlfn.XLOOKUP(A19,FS.1!$A$11:$A$46,FS.1!$E$11:$E$46,0,0,1) -> 204577 | M19: CHECK | P19: =P14-FS.1!C73 -> 0 | R19: =R14-FS.1!E73 -> 0 | T19: =T14-FS.1!G73 -> -31842 | V19: =V14-FS.1!I73 -> #REF! | W19: Convertible debt | X19: 7 | Z19: =F19 -> 204577 | AB19: =D19 -> 274099 | AD19: =AB19-AM19 -> 313016.32 | AG19: =-SUM(AG57:AG58) -> -38917.316 | AM19: =SUM(AG19:AL19) -> -38917.316
A20: =FS.1!A35 -> Due to related parties | D20: =_xlfn.XLOOKUP(A20,FS.1!A28:A63,FS.1!C28:C63,0,0,1) -> 5338 | F20: =_xlfn.XLOOKUP(A20,FS.1!$A$11:$A$46,FS.1!$E$11:$E$46,0,0,1) -> 1838 | W20: Due to related parties | Z20: =F20 -> 1838 | AB20: =D20 -> 5338 | AD20: =AB20+AM20 -> 5338 | AM20: =SUM(AG20:AL20) -> 0
A21: TOTAL LIABILITES | C21: $ | D21: =SUM(D18:D20) -> 882713 | E21: $ | F21: =SUM(F18:F20) -> 556206 | W21: TOTAL LIABILITES | Y21: $ | Z21: =SUM(Z18:Z20) -> 556206 | AA21: $ | AB21: =SUM(AB18:AB20) -> 882713 | AC21: $ | AD21: =SUM(AD18:AD20) -> 974630.32 | AM21: =SUM(AG21:AL21) -> 0
AM22: =SUM(AG22:AL22) -> 0
A23: SHAREHOLDERS’ EQUITY | W23: SHAREHOLDERS’ EQUITY | AM23: =SUM(AG23:AL23) -> 0
A24: =FS.1!A41 -> Share capital | B24: 8 | C24: $ | D24: =_xlfn.XLOOKUP(A24,FS.1!A32:A69,FS.1!C32:C69,0,0,1) -> 8224099 | E24: $ | F24: =_xlfn.XLOOKUP(A24,FS.1!$A$11:$A$46,FS.1!$E$11:$E$46,0,0,1) -> 8224099 | W24: Share capital | X24: 8 | Y24: $ | Z24: =F24 -> 8224099 | AA24: $ | AB24: =D24 -> 8224099 | AC24: $ | AD24: =AB24+AM24 -> 8224099 | AM24: =SUM(AG24:AL24) -> 0
A25: =FS.1!A42 -> Contributed surplus | D25: =_xlfn.XLOOKUP(A25,FS.1!A33:A70,FS.1!C33:C70,0,0,1) -> 308750 | F25: =_xlfn.XLOOKUP(A25,FS.1!$A$11:$A$46,FS.1!$E$11:$E$46,0,0,1) -> 308750 | W25: Contributed surplus | Z25: =F25 -> 308750 | AB25: =D25 -> 308750 | AD25: =AB25+AM25 -> 308750 | AM25: =SUM(AG25:AL25) -> 0
A26: =FS.1!A43 -> Accumulated deficit | D26: =_xlfn.XLOOKUP(A26,FS.1!A34:A71,FS.1!C34:C71,0,0,1) -> -4939226 | F26: =_xlfn.XLOOKUP(A26,FS.1!$A$11:$A$46,FS.1!$E$11:$E$46,0,0,1) -> #REF! | W26: Accumulated deficit | Z26: =F26 -> #REF! | AB26: =D26 -> -4939226 | AD26: =AB26+AM26 -> -3574296.7 | AG26: =-AG5-AG18-AG19 -> 77117.316 | AJ26: =-AJ5 -> 5448 | AK26: =-AK7-AK12 -> 1276364 | AL26: =-AL5 -> 6000 | AM26: =SUM(AG26:AL26) -> 1364929.3
A27: TOTAL SHAREHOLDERS’ EQUITY | C27: $ | D27: =SUM(D24:D26) -> 3593623 | E27: $ | F27: =SUM(F24:F26) -> #REF! | W27: TOTAL SHAREHOLDERS’ EQUITY | Y27: $ | Z27: =SUM(Z24:Z26) -> #REF! | AA27: $ | AB27: =SUM(AB24:AB26) -> 3593623 | AC27: $ | AD27: =SUM(AD24:AD26) -> 4958552.3 | AM27: =SUM(AG27:AL27) -> 0
A28: TOTAL LIABILITIES AND SHAREHOLDERS’ EQUITY | C28: $ | D28: =D27+D21 -> 4476336 | E28: $ | F28: =F27+F21 -> #REF! | W28: TOTAL LIABILITIES AND SHAREHOLDERS’ EQUITY | Y28: $ | Z28: =Z27+Z21 -> #REF! | AA28: $ | AB28: =AB27+AB21 -> 4476336 | AC28: $ | AD28: =AD27+AD21 -> 5933182.6 | AM28: =SUM(AG28:AL28) -> 0
AG29: =SUM(AG3:AG28) -> 0 | AH29: =SUM(AH3:AH28) -> 0 | AI29: =SUM(AI3:AI28) -> 0 | AJ29: =SUM(AJ3:AJ28) -> 0 | AK29: =SUM(AK3:AK28) -> 0 | AL29: =SUM(AL3:AL28) -> 0 | AM29: =SUM(AM3:AM28) -> 0
A31: CHECK BALANCE | D31: =D28-D14 -> 0 | F31: =F28-F14 -> #REF!
A32: CHECK TO FS.1 | D32: =D28-FS.1!C46 -> 0 | F32: =F28-FS.1!E46 -> #REF!
W44: PROFORMA IS
W45: For the year ended | X45: Notes | Z45: June 30, 2024 (unaudited) | AB45: June 30, 2025 (unaudited) | AD45: June 30, 2026 (forecasted) | AG45: ADJ 1 | AH45: ADJ 2 | AI45: ADJ 3 | AJ45: ADJ 4 | AK45: ADJ 5 | AL45: ADJ 6 | AM45: SUM
W46: Vehicle sales | Y46: $ | Z46: =L3 -> 0 | AA46: $ | AB46: =J3 -> 360000 | AC46: $ | AD46: =AM46 -> 1014800 | AG46: =570800+(222000+222000) -> 1014800 | AM46: =SUM(AG46:AL46) -> 1014800
W47: Cost of sales | Y47: $ | Z47: =L4 -> 0 | AA47: $ | AB47: =J4 -> -328158 | AC47: $ | AD47: =-AM47 -> -814500 | AG47: =80000*(5+4) -> 720000 | AH47: =-AH50 -> 94500 | AM47: =SUM(AG47:AL47) -> 814500
W48: Gross profit (loss) | Y48: $ | Z48: =SUM(Z46:Z47) -> 0 | AA48: $ | AB48: =SUM(AB46:AB47) -> 31842 | AC48: $ | AD48: =SUM(AD46:AD47) -> 200300 | AM48: =SUM(AG48:AL48) -> 0
W49: Operating expenses | AM49: =SUM(AG49:AL49) -> 0
W50: General and administration | X50: 9 | Y50: $ | Z50: =L7 -> #REF! | AA50: $ | AB50: =J7 -> 1755445 | AC50: $ | AD50: =AM50 -> 1466312 | AG50: =((10000+10000)*12)+(6000*6)+(3000*6) -> 294000 | AH50: =-((10000*7*0.75)+(6000*7)) -> -94500 | AJ50: =2000+(154*12)+(50*12) -> 4448 | AK50: ='IA.1 - Intangible'!AP13 -> 1256364 | AL50: =5000+1000 -> 6000 | AM50: =SUM(AG50:AL50) -> 1466312
W51: Sales and marketing | Z51: =L8 -> #REF! | AB51: =J8 -> 70958 | AD51: =AM51 -> 39000 | AG51: =6500*6 -> 39000 | AM51: =SUM(AG51:AL51) -> 39000
W52: Operating loss | Y52: $ | Z52: =Z48-SUM(Z49:Z51) -> #REF! | AA52: $ | AB52: =AB48-SUM(AB49:AB51) -> -1794561 | AC52: $ | AD52: =AD48-SUM(AD49:AD51) -> -1305012 | AM52: =SUM(AG52:AL52) -> 0
W53: Other income (expenses) | AM53: =SUM(AG53:AL53) -> 0
W54: Other income | Z54: =L11 -> 3150 | AB54: =J11 -> 0 | AD54: =-AM54 -> 0 | AM54: =SUM(AG54:AL54) -> 0
W55: Impairment expense | Z55: 0 | AB55: 0 | AD55: =-AM55 -> -20000 | AK55: 20000 | AM55: =SUM(AG55:AL55) -> 20000
W56: Interest income | Z56: =L12 -> #REF! | AB56: =J12 -> 14 | AD56: =-AM56 -> 0 | AM56: =SUM(AG56:AL56) -> 0
W57: Net financial expenses | X57: 10 | Z57: =L13 -> 50062 | AB57: =J13 -> -31957 | AD57: =-AM57 -> -18105.072 | AG57: =SUM('[1]COV.DEBT - AMEND'!$D$52:$D$57) -> 18105.072 | AM57: =SUM(AG57:AL57) -> 18105.072
W58: Interest expense | X58: 7 | Z58: =L14 -> -33787 | AB58: =J14 -> -45232 | AD58: =-AM58 -> -21812.244 | AG58: =-SUM('[1]COV.DEBT - AMEND'!$E$52:$E$57) -> 20812.244 | AJ58: 1000 | AM58: =SUM(AG58:AL58) -> 21812.244
W59: Net Loss and comprehensive loss | Y59: $ | Z59: =SUM(Z52:Z58) -> #REF! | AA59: $ | AB59: =SUM(AB52:AB58) -> -1871736 | AC59: $ | AD59: =SUM(AD52:AD58) -> -1364929.3
AG60: =AG46-SUM(AG47:AG58) -> -77117.316 | AH60: =AH46-SUM(AH47:AH58) -> 0 | AI60: =AI46-SUM(AI47:AI58) -> 0 | AJ60: =AJ46-SUM(AJ47:AJ58) -> -5448 | AK60: =AK46-SUM(AK47:AK58) -> -1276364 | AL60: =AL46-SUM(AL47:AL58) -> -6000 | AM60: =AM46-SUM(AM47:AM58) -> -1364929.3
AL62: CHECK | AM62: =AM26+AM60 -> 0
AG64: motor - $8k - burnt out due to modfication
AG65: controller -$2.5k - re-program
A66: =C90 -> 0 | AG66: 2 x heater - $1k - broke
AG67: brake plate - $1.1k - burn-out
AG68: $6k battery - limited use testing req'd
AG69: $20k worth of parts

Sheet SOCE
B2: Notes | D2: Share Capital | F2: Contributed Surplus | H2: Accumulated Deficit | J2: Total Shareholder's Equity | L2: Notes | N2: Share Capital | P2: Contributed Surplus | R2: Accumulated Deficit | T2: Total Shareholder's Equity
A3: =FS.1!A86 -> Balance - June 30, 2023 | C3: $ | D3: =FS.1!C86 -> 1774099 | E3: $ | F3: =FS.1!E86 -> 308750 | G3: $ | H3: =FS.1!G86 -> -1474472 | I3: $ | J3: =ROUND(SUM(D3:H3),0) -> 608377 | K3: Balance - July 1, 2023 | M3: $ | N3: =FS.1!C86 -> 1774099 | O3: $ | P3: =FS.1!E86 -> 308750 | Q3: $ | R3: =FS.1!G86 -> -1474472 | S3: $ | T3: =ROUND(SUM(N3:R3),0) -> 608377
A4: =FS.1!A87 -> Shares issued on acquisition of Hallor Industries Inc. | B4: 4 | D4: =FS.1!C87 -> 6000000 | F4: =FS.1!E87 -> 0 | H4: =FS.1!G87 -> 0 | J4: =ROUND(SUM(D4:H4),0) -> 6000000 | K4: Shares issued on acquisition of Hallor Industries Inc. | L4: 5 | N4: =FS.1!C87 -> 6000000 | P4: =FS.1!E87 -> 0 | R4: =FS.1!G87 -> 0 | T4: =ROUND(SUM(N4:R4),0) -> 6000000
A5: Share issue costs | B5: 4 | D5: =FS.1!C88 -> 450000 | F5: =FS.1!E88 -> 0 | H5: =FS.1!G88 -> 0 | J5: =ROUND(SUM(D5:H5),0) -> 450000 | K5: Share issue costs | L5: 5 | N5: =FS.1!C88 -> 450000 | P5: =FS.1!E88 -> 0 | R5: =FS.1!G88 -> 0 | T5: =ROUND(SUM(N5:R5),0) -> 450000
A6: Net loss for the year | D6: =FS.1!C89 -> 0 | F6: =FS.1!E89 -> 0 | H6: =FS.1!G89 -> #REF! | J6: =ROUND(SUM(D6:H6),0) -> #REF! | K6: Net loss for the period | N6: =FS.1!C89 -> 0 | P6: =FS.1!E89 -> 0 | R6: =FS.1!G89 -> #REF! | T6: =ROUND(SUM(N6:R6),0) -> #REF!
A7: =FS.1!A90 -> Balance - June 30, 2024 | C7: $ | D7: =ROUND(SUM(D3:D6),0) -> 8224099 | E7: $ | F7: =ROUND(SUM(F3:F6),0) -> 308750 | G7: $ | H7: =ROUND(SUM(H3:H6),0) -> #REF! | I7: $ | J7: =ROUND(SUM(J3:J6),0) -> #REF! | K7: Balance - June 30, 2024 | M7: $ | N7: =ROUND(SUM(N3:N6),0) -> 8224099 | O7: $ | P7: =ROUND(SUM(P3:P6),0) -> 308750 | Q7: $ | R7: =ROUND(SUM(R3:R6),0) -> #REF! | S7: $ | T7: =ROUND(SUM(T3:T6),0) -> #REF!
A8: Net loss for year | D8: =FS.1!C95 -> 0 | F8: =FS.1!E95 -> 0 | H8: =FS.1!G95 -> -1871736 | J8: =ROUND(SUM(D8:H8),0) -> -1871736
A9: =FS.1!A96 -> Balance - June 30, 2025 | C9: $ | D9: =SUM(D7:D8) -> 8224099 | E9: $ | F9: =SUM(F7:F8) -> 308750 | G9: $ | H9: =SUM(H7:H8) -> #REF! | I9: $ | J9: =SUM(J7:J8) -> #REF! | K9: Balance - July 1, 2024 | M9: $ | N9: =FS.1!C92 -> 8224099 | O9: $ | P9: =FS.1!E92 -> 308750 | Q9: $ | R9: =FS.1!G92 -> #REF! | S9: $ | T9: =ROUND(SUM(N9:R9),0) -> #REF!
K10: Net loss for period | N10: =FS.1!C95 -> 0 | P10: =FS.1!E95 -> 0 | R10: =FS.1!G95 -> -1871736 | T10: =ROUND(SUM(N10:R10),0) -> -1871736
A11: CHECK | D11: =D7-FS.1!C90 -> 0 | F11: =FS.1!E90-F7 -> 0 | H11: =H7-FS.1!G90 -> #REF! | J11: =J7-FS.1!I90 -> #REF! | K11: Balance - June 30, 2025 | M11: $ | N11: =ROUND(SUM(N9:N10),0) -> 8224099 | O11: $ | P11: =ROUND(SUM(P9:P10),0) -> 308750 | Q11: $ | R11: =ROUND(SUM(R9:R10),0) -> #REF! | S11: $ | T11: =ROUND(SUM(T9:T10),0) -> #REF!
A12: CHECK | D12: =D9-FS.1!C41 -> 0 | F12: =F9-FS.1!C42 -> 0 | H12: =H9-FS.1!C43 -> #REF! | J12: =J9-FS.1!C44 -> #REF!
K13: CHECK | N13: =FS.1!C90-N7 -> 0 | P13: =FS.1!E90-P7 -> 0 | R13: =FS.1!G90-R7 -> #REF! | T13: =FS.1!I90-T7 -> #REF!
K14: CHECK | N14: =FS.1!C41-N11 -> 0 | P14: =FS.1!C42-P11 -> 0 | R14: =FS.1!C43-R11 -> #REF! | T14: =FS.1!C44-T11 -> #REF!

Sheet SCF
A1: *LINK FAIL - RE-EXPORT REQUIRED EVERYTIME
A2: Year ended | C2: June 30, 2025 (unaudited) | E2: June 30, 2024 (unaudited)
A3: Cash (used in) provided by:
A5: OPERATING ACTIVITIES
A6: Net loss for the period | B6: $ | C6: =FS.1!C105 -> -1871736 | D6: $ | E6: =FS.1!E105 -> #REF!
A8: Non-cash items:
A9: =FS.1!A108 -> Depreciation and amortization | C9: =_xlfn.XLOOKUP(A9,FS.1!$A$104:$A$138,FS.1!$C$104:$C$138,0,0,1) -> 1256364 | E9: =_xlfn.XLOOKUP(A9,FS.1!$A$104:$A$138,FS.1!$E$104:$E$138) -> #REF!
A10: =FS.1!A110 -> Accretion expense | C10: =_xlfn.XLOOKUP(A10,FS.1!$A$104:$A$138,FS.1!$C$104:$C$138,0,0,1) -> 31957 | E10: =_xlfn.XLOOKUP(A10,FS.1!$A$104:$A$138,FS.1!$E$104:$E$138) -> 24938
A11: =FS.1!A111 -> Interest expense | C11: =_xlfn.XLOOKUP(A11,FS.1!$A$104:$A$138,FS.1!$C$104:$C$138,0,0,1) -> 37565 | E11: =_xlfn.XLOOKUP(A11,FS.1!$A$104:$A$138,FS.1!$E$104:$E$138) -> 30800
A12: =FS.1!A112 -> Gain on re-measurement of derivative liability | C12: =_xlfn.XLOOKUP(A12,FS.1!$A$104:$A$138,FS.1!$C$104:$C$138,0,0,1) -> 0 | E12: =_xlfn.XLOOKUP(A12,FS.1!$A$104:$A$138,FS.1!$E$104:$E$138) -> -75000
A15: Changes in non-cash working capital items:
A16: =FS.1!A115 -> Receivables | C16: =_xlfn.XLOOKUP(A16,FS.1!$A$104:$A$138,FS.1!$C$104:$C$138,0,0,1) -> 0 | E16: =_xlfn.XLOOKUP(A16,FS.1!$A$104:$A$138,FS.1!$E$104:$E$138) -> 12375
A17: =FS.1!A116 -> Prepaid expenses | C17: =_xlfn.XLOOKUP(A17,FS.1!$A$104:$A$138,FS.1!$C$104:$C$138,0,0,1) -> 0 | E17: =_xlfn.XLOOKUP(A17,FS.1!$A$104:$A$138,FS.1!$E$104:$E$138) -> 2240
A18: =FS.1!A117 -> Sales tax receivable | C18: =_xlfn.XLOOKUP(A18,FS.1!$A$104:$A$138,FS.1!$C$104:$C$138,0,0,1) -> -7455 | E18: =_xlfn.XLOOKUP(A18,FS.1!$A$104:$A$138,FS.1!$E$104:$E$138) -> -4177
A19: =FS.1!A118 -> Inventory | C19: =_xlfn.XLOOKUP(A19,FS.1!$A$104:$A$138,FS.1!$C$104:$C$138,0,0,1) -> 291108 | E19: =_xlfn.XLOOKUP(A19,FS.1!$A$104:$A$138,FS.1!$E$104:$E$138) -> -54914
A20: =FS.1!A119 -> Accounts payables and accrued liabilities | C20: =_xlfn.XLOOKUP(A20,FS.1!$A$104:$A$138,FS.1!$C$104:$C$138,0,0,1) -> 253485 | E20: =_xlfn.XLOOKUP(A20,FS.1!$A$104:$A$138,FS.1!$E$104:$E$138) -> 102329
A21: =FS.1!A121 -> Due to related parties | C21: =_xlfn.XLOOKUP(A21,FS.1!$A$104:$A$138,FS.1!$C$104:$C$138,0,0,1) -> 3500 | E21: =_xlfn.XLOOKUP(A21,FS.1!$A$104:$A$138,FS.1!$E$104:$E$138) -> 938
A22: Net cash used in operating activities | B22: $ | C22: =SUM(C6:C21) -> -5212 | D22: $ | E22: =SUM(E6:E21) -> #REF!
A24: INVESTING ACTIVITIES
A25: =FS.1!A125 -> Purchase of equipment | B25: $ | C25: =_xlfn.XLOOKUP(A25,FS.1!$A$104:$A$138,FS.1!$C$104:$C$138,0,0,1) -> 0 | D25: $ | E25: =_xlfn.XLOOKUP(A25,FS.1!$A$104:$A$138,FS.1!$E$104:$E$138) -> #REF!
A26: =FS.1!A126 -> Cash received on acquisition of Hallor Industries Inc. | C26: =_xlfn.XLOOKUP(A26,FS.1!$A$104:$A$138,FS.1!$C$104:$C$138,0,0,1) -> 0 | E26: =_xlfn.XLOOKUP(A26,FS.1!$A$104:$A$138,FS.1!$E$104:$E$138) -> 21130
A27: Net cash provided from investing activities | B27: $ | C27: =SUM(C25:C26) -> 0 | D27: $ | E27: =SUM(E25:E26) -> #REF!
A29: FINANCING ACTIVITIES
A30: =FS.1!A131 -> Proceeds from convertibles notes, net of transaction costs | B30: $ | C30: =_xlfn.XLOOKUP(A30,FS.1!$A$104:$A$138,FS.1!$C$104:$C$138,0,0,1) -> 0 | D30: $ | E30: =_xlfn.XLOOKUP(A30,FS.1!$A$104:$A$138,FS.1!$E$104:$E$138) -> 225000
A31: Net cash provided by financing activities | B31: $ | C31: =SUM(C30:C30) -> 0 | D31: $ | E31: =SUM(E30:E30) -> 225000
A33: Net (decrease) increase in cash in the year | B33: $ | C33: =SUM(C22,C27,C31) -> -5212 | D33: $ | E33: =SUM(E22,E27,E31) -> #REF!
A34: Cash – beginning of the year | B34: $ | C34: =FS.1!E13 -> 5604 | D34: $ | E34: =FS.1!E137 -> 108180
A35: Cash – end of the year | B35: $ | C35: =C33+C34 -> 392 | D35: $ | E35: =E33+E34 -> #REF!
A37: CHECK to BS | C37: =FS.1!C13-C35 -> 0 | E37: =FS.1!E13-E35 -> #REF!

Sheet NOTES - TABLE
A1: Expenses by nature | F1: *LINK FAIL - RE-EXPORT REQUIRED EVERYTIME | L1: Inventory | T1: Share Capital | X1: Expenses by nature
C2: =FS.1!C53 -> June 30, 2025 | E2: =FS.1!E53 -> June 30, 2024 | G2: Total carrying amount | H2: Contractual cash flows | I2: Less than 1 year | J2: 1 to 5 years | K2: More than 5 years | N2: Raw Materials | P2: Work-in-Progress Inventory | R2: Total | T2: Issued and outstanding common shares | U2: Number of shares | W2: Amount | Y2: Three months ended | AC2: Six months ended
A3: ='Note Disclosures'!A248 -> Bank fees | B3: $ | C3: =_xlfn.XLOOKUP(A3,'Note Disclosures'!$A$248:$A$262,'Note Disclosures'!$E$248:$E$262,0,0,1) -> 2281 | D3: $ | E3: =_xlfn.XLOOKUP(A3,'Note Disclosures'!$A$248:$A$262,'Note Disclosures'!$F$248:$F$262,0,0,1) -> 2282 | G3: $ | H3: $ | I3: $ | J3: $ | K3: $ | L3: As at June 30, 2022 and 2023 | M3: $ | N3: 0 | O3: $ | P3: 0 | Q3: $ | R3: =SUM(N3,P3) -> 0 | T3: Balance, June 30, 2023 | U3: 19012501 | V3: $ | W3: 1774099 | Z3: ='Note Disclosures'!C247 -> June 30, 2025 | AB3: ='Note Disclosures'!D247 -> June 30, 2023 | AD3: ='Note Disclosures'!E247 -> June 30, 2025 | AF3: ='Note Disclosures'!F247 -> June 30, 2023
A4: ='Note Disclosures'!A249 -> Professional fees | C4: =_xlfn.XLOOKUP(A4,'Note Disclosures'!$A$248:$A$262,'Note Disclosures'!$E$248:$E$262,0,0,1) -> 133726 | E4: =_xlfn.XLOOKUP(A4,'Note Disclosures'!$A$248:$A$262,'Note Disclosures'!$F$248:$F$262,0,0,1) -> #REF! | F4: =FS.1!A30 -> Accounts payables and accrued liabilities | G4: =FS.1!C30 -> 603276 | H4: =G4 -> 603276 | I4: =G4 -> 603276 | J4: 0 | K4: 0 | L4: Acquired in the period (Note 5) | N4: ='TB.3 - Acq TB'!S4 -> 101516 | P4: ='TB.3 - Acq TB'!S5+1 -> 295934 | R4: =SUM(N4,P4) -> 397450 | T4: Common shares issued on acquisition of Hallor (Note 4) | U4: 12000000 | W4: 6000000 | X4: ='Note Disclosures'!A248 -> Bank fees | Y4: $ | Z4: =_xlfn.XLOOKUP(X4,'Note Disclosures'!$A$248:$A$262,'Note Disclosures'!$C$248:$C$262,0,0,1) -> 367 | AA4: $ | AB4: =_xlfn.XLOOKUP(X4,'Note Disclosures'!$A$248:$A$262,'Note Disclosures'!$D$248:$D$262,0,0,1) -> 0 | AC4: $ | AD4: ='Note Disclosures'!E248 -> 2281 | AE4: $ | AF4: ='Note Disclosures'!F248 -> 2282
A5: ='Note Disclosures'!A250 -> Consulting expense | C5: =_xlfn.XLOOKUP(A5,'Note Disclosures'!$A$248:$A$262,'Note Disclosures'!$E$248:$E$262,0,0,1) -> 318291 | E5: =_xlfn.XLOOKUP(A5,'Note Disclosures'!$A$248:$A$262,'Note Disclosures'!$F$248:$F$262,0,0,1) -> 134140 | F5: Convertible debt | G5: =FS.1!C32 -> 274099 | H5: ='COV.DEBT'!F33-'COV.DEBT'!E35 -> 237708.3 | I5: =H5 -> 237708.3 | J5: 0 | K5: 0 | L5: Additions in the period | N5: =ROUND((SUM('GL 5510'!G81:G126)+SUM('GL 5510'!G72:G79)),0) -> 33605 | P5: =ROUND((SUM('GL 5515'!I18:I24)+SUM('GL 5520'!I14:I21)+'GL 6016'!H34),0)-1 -> 39825 | R5: =SUM(N5,P5) -> 73430 | T5: Common shares issued as finders fee on Hallor acquisition (Note 4) | U5: 900000 | W5: 450000 | X5: ='Note Disclosures'!A249 -> Professional fees | Z5: =_xlfn.XLOOKUP(X5,'Note Disclosures'!$A$248:$A$262,'Note Disclosures'!$C$248:$C$262,0,0,1) -> 54025 | AB5: =_xlfn.XLOOKUP(X5,'Note Disclosures'!$A$248:$A$262,'Note Disclosures'!$D$248:$D$262,0,0,1) -> 5600 | AD5: ='Note Disclosures'!E249 -> 133726 | AF5: ='Note Disclosures'!F249 -> #REF!
A6: ='Note Disclosures'!A251 -> Dues, licenses, and permits | C6: =_xlfn.XLOOKUP(A6,'Note Disclosures'!$A$248:$A$262,'Note Disclosures'!$E$248:$E$262,0,0,1) -> 1742 | E6: =_xlfn.XLOOKUP(A6,'Note Disclosures'!$A$248:$A$262,'Note Disclosures'!$F$248:$F$262,0,0,1) -> 1253 | F6: =FS.1!A35 -> Due to related parties | G6: =FS.1!C35 -> 5338 | H6: =G6 -> 5338 | I6: =G6 -> 5338 | J6: 0 | K6: 0 | L6: Transferred to work-in-progress on assembly | N6: -63201 | P6: =-N6 -> 63201 | R6: =SUM(N6,P6) -> 0 | T6: Balance, June 30, 2024 and 2025 | U6: =SUM(U3:U5) -> 31912501 | V6: $ | W6: =SUM(W3:W5) -> 8224099 | X6: ='Note Disclosures'!A250 -> Consulting expense | Z6: =_xlfn.XLOOKUP(X6,'Note Disclosures'!$A$248:$A$262,'Note Disclosures'!$C$248:$C$262,0,0,1) -> 78800 | AB6: =_xlfn.XLOOKUP(X6,'Note Disclosures'!$A$248:$A$262,'Note Disclosures'!$D$248:$D$262,0,0,1) -> 10000 | AD6: ='Note Disclosures'!E250 -> 318291 | AF6: ='Note Disclosures'!F250 -> 134140
A7: ='Note Disclosures'!A252 -> Other miscellaneous | C7: =_xlfn.XLOOKUP(A7,'Note Disclosures'!$A$248:$A$262,'Note Disclosures'!$E$248:$E$262,0,0,1) -> 8370 | E7: =_xlfn.XLOOKUP(A7,'Note Disclosures'!$A$248:$A$262,'Note Disclosures'!$F$248:$F$262,0,0,1) -> #REF! | F7: Total | G7: =SUM(G4:G6) -> 882713 | H7: =SUM(H4:H6) -> 846322.3 | I7: =SUM(I4:I6) -> 846322.3 | J7: =SUM(J4:J6) -> 0 | K7: =SUM(K4:K6) -> 0 | L7: ="As at "&TEXT(currentperiod_end_date,"MMMM DD, YYYY") -> As at June 30, 2025 | M7: $ | N7: =SUM(N3:N6) -> 71920 | O7: $ | P7: =SUM(P3:P6) -> 398960 | Q7: $ | R7: =SUM(R3:R6) -> 470880 | X7: ='Note Disclosures'!A251 -> Dues, licenses, and permits | Z7: =_xlfn.XLOOKUP(X7,'Note Disclosures'!$A$248:$A$262,'Note Disclosures'!$C$248:$C$262,0,0,1) -> 191 | AB7: =_xlfn.XLOOKUP(X7,'Note Disclosures'!$A$248:$A$262,'Note Disclosures'!$D$248:$D$262,0,0,1) -> 0 | AD7: ='Note Disclosures'!E251 -> 1742 | AF7: ='Note Disclosures'!F251 -> 1253
A8: ='Note Disclosures'!A253 -> Office expenses | C8: =_xlfn.XLOOKUP(A8,'Note Disclosures'!$A$248:$A$262,'Note Disclosures'!$E$248:$E$262,0,0,1) -> 2747 | E8: =_xlfn.XLOOKUP(A8,'Note Disclosures'!$A$248:$A$262,'Note Disclosures'!$F$248:$F$262,0,0,1) -> #REF! | T8: CHECK | W8: =FS.1!C41-W6 -> 0 | X8: ='Note Disclosures'!A252 -> Other miscellaneous | Z8: =_xlfn.XLOOKUP(X8,'Note Disclosures'!$A$248:$A$262,'Note Disclosures'!$C$248:$C$262,0,0,1) -> 1460 | AB8: =_xlfn.XLOOKUP(X8,'Note Disclosures'!$A$248:$A$262,'Note Disclosures'!$D$248:$D$262,0,0,1) -> 0 | AD8: ='Note Disclosures'!E252 -> 8370 | AF8: ='Note Disclosures'!F252 -> #REF!
A9: ='Note Disclosures'!A254 -> Meals and entertainment | C9: =_xlfn.XLOOKUP(A9,'Note Disclosures'!$A$248:$A$262,'Note Disclosures'!$E$248:$E$262,0,0,1) -> 934 | E9: =_xlfn.XLOOKUP(A9,'Note Disclosures'!$A$248:$A$262,'Note Disclosures'!$F$248:$F$262,0,0,1)+1 -> #REF! | F9: CHECK | G9: =G7-SUM(FS.1!C30,FS.1!C32,FS.1!C35) -> 0 | L9: CHECK | R9: =FS.1!C17 -> 161256 | X9: ='Note Disclosures'!A253 -> Office expenses | Z9: =_xlfn.XLOOKUP(X9,'Note Disclosures'!$A$248:$A$262,'Note Disclosures'!$C$248:$C$262,0,0,1) -> 531 | AB9: =_xlfn.XLOOKUP(X9,'Note Disclosures'!$A$248:$A$262,'Note Disclosures'!$D$248:$D$262,0,0,1) -> 1875 | AD9: ='Note Disclosures'!E253 -> 2747 | AF9: ='Note Disclosures'!F253 -> #REF!
A10: ='Note Disclosures'!A255 -> Travel expenses | C10: =_xlfn.XLOOKUP(A10,'Note Disclosures'!$A$248:$A$262,'Note Disclosures'!$E$248:$E$262,0,0,1) -> 4524 | E10: =_xlfn.XLOOKUP(A10,'Note Disclosures'!$A$248:$A$262,'Note Disclosures'!$F$248:$F$262,0,0,1)-1 -> #REF! | X10: ='Note Disclosures'!A254 -> Meals and entertainment | Z10: =_xlfn.XLOOKUP(X10,'Note Disclosures'!$A$248:$A$262,'Note Disclosures'!$C$248:$C$262,0,0,1) -> 619 | AB10: =_xlfn.XLOOKUP(X10,'Note Disclosures'!$A$248:$A$262,'Note Disclosures'!$D$248:$D$262,0,0,1) -> 0 | AD10: ='Note Disclosures'!E254 -> 934 | AF10: ='Note Disclosures'!F254 -> #REF!
A11: ='Note Disclosures'!A256 -> Transfer agent and regulatory expenses | C11: =_xlfn.XLOOKUP(A11,'Note Disclosures'!$A$248:$A$262,'Note Disclosures'!$E$248:$E$262,0,0,1) -> 0 | E11: =_xlfn.XLOOKUP(A11,'Note Disclosures'!$A$248:$A$262,'Note Disclosures'!$F$248:$F$262,0,0,1) -> 10700 | X11: ='Note Disclosures'!A255 -> Travel expenses | Z11: =_xlfn.XLOOKUP(X11,'Note Disclosures'!$A$248:$A$262,'Note Disclosures'!$C$248:$C$262,0,0,1) -> 985 | AB11: =_xlfn.XLOOKUP(X11,'Note Disclosures'!$A$248:$A$262,'Note Disclosures'!$D$248:$D$262,0,0,1) -> 0 | AD11: ='Note Disclosures'!E255 -> 4524 | AF11: ='Note Disclosures'!F255 -> #REF!
A12: ='Note Disclosures'!A257 -> Insurance | C12: =_xlfn.XLOOKUP(A12,'Note Disclosures'!$A$248:$A$262,'Note Disclosures'!$E$248:$E$262,0,0,1) -> 26182 | E12: =_xlfn.XLOOKUP(A12,'Note Disclosures'!$A$248:$A$262,'Note Disclosures'!$F$248:$F$262,0,0,1) -> #REF! | X12: ='Note Disclosures'!A256 -> Transfer agent and regulatory expenses | Z12: =_xlfn.XLOOKUP(X12,'Note Disclosures'!$A$248:$A$262,'Note Disclosures'!$C$248:$C$262,0,0,1) -> 5250 | AB12: =_xlfn.XLOOKUP(X12,'Note Disclosures'!$A$248:$A$262,'Note Disclosures'!$D$248:$D$262,0,0,1) -> 0 | AD12: ='Note Disclosures'!E256 -> 0 | AF12: ='Note Disclosures'!F256 -> 10700
A13: ='Note Disclosures'!A258 -> Shipping expense | C13: =_xlfn.XLOOKUP(A13,'Note Disclosures'!$A$248:$A$262,'Note Disclosures'!$E$248:$E$262,0,0,1) -> 0 | E13: =_xlfn.XLOOKUP(A13,'Note Disclosures'!$A$248:$A$262,'Note Disclosures'!$F$248:$F$262,0,0,1) -> #REF! | X13: ='Note Disclosures'!A257 -> Insurance | Z13: =_xlfn.XLOOKUP(X13,'Note Disclosures'!$A$248:$A$262,'Note Disclosures'!$C$248:$C$262,0,0,1) -> 9696 | AB13: =_xlfn.XLOOKUP(X13,'Note Disclosures'!$A$248:$A$262,'Note Disclosures'!$D$248:$D$262,0,0,1) -> 0 | AD13: ='Note Disclosures'!E257 -> 26182 | AF13: ='Note Disclosures'!F257 -> #REF!
A14: ='Note Disclosures'!A259 -> Shop supplies | C14: =_xlfn.XLOOKUP(A14,'Note Disclosures'!$A$248:$A$262,'Note Disclosures'!$E$248:$E$262,0,0,1) -> 241 | E14: =_xlfn.XLOOKUP(A14,'Note Disclosures'!$A$248:$A$262,'Note Disclosures'!$F$248:$F$262,0,0,1) -> #REF! | X14: ='Note Disclosures'!A258 -> Shipping expense | Z14: =_xlfn.XLOOKUP(X14,'Note Disclosures'!$A$248:$A$262,'Note Disclosures'!$C$248:$C$262,0,0,1) -> 5494 | AB14: =_xlfn.XLOOKUP(X14,'Note Disclosures'!$A$248:$A$262,'Note Disclosures'!$D$248:$D$262,0,0,1) -> 0 | AD14: ='Note Disclosures'!E258 -> 0 | AF14: ='Note Disclosures'!F258 -> #REF!
A15: ='Note Disclosures'!A260 -> Depreciation and amortization | C15: =_xlfn.XLOOKUP(A15,'Note Disclosures'!$A$248:$A$262,'Note Disclosures'!$E$248:$E$262,0,0,1) -> 1256364 | E15: =_xlfn.XLOOKUP(A15,'Note Disclosures'!$A$248:$A$262,'Note Disclosures'!$F$248:$F$262,0,0,1) -> #REF! | X15: ='Note Disclosures'!A259 -> Shop supplies | Z15: =_xlfn.XLOOKUP(X15,'Note Disclosures'!$A$248:$A$262,'Note Disclosures'!$C$248:$C$262,0,0,1) -> 2728 | AB15: =_xlfn.XLOOKUP(X15,'Note Disclosures'!$A$248:$A$262,'Note Disclosures'!$D$248:$D$262,0,0,1) -> 0 | AD15: ='Note Disclosures'!E259 -> 241 | AF15: ='Note Disclosures'!F259 -> #REF!
A16: ='Note Disclosures'!A261 -> Foreign exchange | C16: =_xlfn.XLOOKUP(A16,'Note Disclosures'!$A$248:$A$262,'Note Disclosures'!$E$248:$E$262,0,0,1) -> 43 | E16: =_xlfn.XLOOKUP(A16,'Note Disclosures'!$A$248:$A$262,'Note Disclosures'!$F$248:$F$262,0,0,1) -> #REF! | X16: ='Note Disclosures'!A260 -> Depreciation and amortization | Z16: =_xlfn.XLOOKUP(X16,'Note Disclosures'!$A$248:$A$262,'Note Disclosures'!$C$248:$C$262,0,0,1) -> 509 | AB16: =_xlfn.XLOOKUP(X16,'Note Disclosures'!$A$248:$A$262,'Note Disclosures'!$D$248:$D$262,0,0,1) -> 0 | AD16: ='Note Disclosures'!E260 -> 1256364 | AF16: ='Note Disclosures'!F260 -> #REF!
A17: Total general and administration expenses | B17: $ | C17: =SUM(C3:C16) -> 1755445 | D17: $ | E17: =SUM(E3:E16) -> #REF! | X17: ='Note Disclosures'!A261 -> Foreign exchange | Z17: =_xlfn.XLOOKUP(X17,'Note Disclosures'!$A$248:$A$262,'Note Disclosures'!$C$248:$C$262,0,0,1) -> 48 | AB17: =_xlfn.XLOOKUP(X17,'Note Disclosures'!$A$248:$A$262,'Note Disclosures'!$D$248:$D$262,0,0,1) -> 0 | AD17: ='Note Disclosures'!E261 -> 43 | AF17: ='Note Disclosures'!F261 -> #REF!
X18: ='Note Disclosures'!A262 -> Acquisition expense | Z18: =_xlfn.XLOOKUP(X18,'Note Disclosures'!$A$248:$A$262,'Note Disclosures'!$C$248:$C$262,0,0,1) -> 0 | AB18: =_xlfn.XLOOKUP(X18,'Note Disclosures'!$A$248:$A$262,'Note Disclosures'!$D$248:$D$262,0,0,1) -> 0 | AD18: ='Note Disclosures'!E262 -> 0 | AF18: ='Note Disclosures'!F262 -> 0
A19: CHECK | C19: ='Note Disclosures'!E263-C17 -> 0 | E19: ='Note Disclosures'!F263-E17 -> #REF! | X19: Total general and administration and sales and marketing | Y19: $ | Z19: =SUM(Z4:Z18) -> 160703 | AA19: $ | AB19: =SUM(AB4:AB18) -> 17475 | AC19: $ | AD19: =SUM(AD4:AD18) -> 1755445 | AE19: $ | AF19: =SUM(AF4:AF18) -> #REF!
X21: CHECK | Z21: =Z19-'Note Disclosures'!C263 -> 0 | AB21: =AB19-'Note Disclosures'!D263 -> 0 | AD21: =AD19-'Note Disclosures'!E263 -> 0 | AF21: =AF19-'Note Disclosures'!F263 -> #REF!
A23: Equipment | L23: Intangibles
C24: Equipment | E24: Total | N24: Intellectual Property | P24: Total | X24: Related party transactions
A25: Cost: | L25: Cost: | Y25: Three months ended | AC25: Six months ended
A26: As at June 30, 2022 and 2023 | B26: $ | C26: 0 | D26: $ | E26: 0 | L26: As at June 30, 2023 | M26: $ | N26: 0 | O26: $ | P26: 0 | X26: Key management compensation | Z26: =Z3 -> June 30, 2025 | AB26: =AB3 -> June 30, 2023 | AD26: =AD3 -> June 30, 2025 | AF26: =AF3 -> June 30, 2023
A27: Acquired during the period | C27: ='Asset Acquisition'!B12 -> 6108 | E27: =C27 -> 6108 | L27: Acquired on acquisition of Hallor Industries | N27: ='Asset Acquisition'!H20+'Asset Acquisition'!H30 -> 6731822 | P27: =N27 -> 6731822 | X27: Consulting fees payable to a entity controlled by the CFO of the Company (1) | Y27: $ | Z27: 24099 | AA27: $ | AB27: 0 | AC27: $ | AD27: 59698 | AE27: $ | AF27: 0
A28: Additions in the period | C28: ='BS.1 - F25'!F35-C27 -> -7056 | E28: =C28 -> -7056 | L28: As at June 30, 2024 and 2025 | M28: $ | N28: =SUM(N26:N27) -> 6731822 | O28: $ | P28: =SUM(P26:P27) -> 6731822 | X28: Consulting fees paid to the CEO of the Company (2) | Z28: 0 | AB28: 22500 | AD28: =Z28 -> 0 | AF28: =AB28 -> 22500
A29: ="As at "&TEXT(currentperiod_end_date,"MMMM DD, YYYY") -> As at June 30, 2025 | B29: $ | C29: =SUM(C26:C28) -> -948 | D29: $ | E29: =SUM(E26:E28) -> -948 | X29: Total key management compensation | Y29: $ | Z29: =SUM(Z27:Z28) -> 24099 | AA29: $ | AB29: =SUM(AB27:AB28) -> 22500 | AC29: $ | AD29: =SUM(AD27:AD28) -> 59698 | AE29: $ | AF29: =SUM(AF27:AF28) -> 22500
L30: Accumulated Amortization:
A31: Accumulated Depreciation: | L31: =L26 -> As at June 30, 2023 | M31: $ | N31: 0 | O31: $ | P31: =N31 -> 0
A32: =A26 -> As at June 30, 2022 and 2023 | B32: $ | C32: 0 | D32: $ | E32: =C32 -> 0 | L32: Amortization in the year | N32: ='IA.1 - Intangible'!R13 -> 1204016 | P32: =N32 -> 1204016
A33: Depreciation in the period | C33: =ROUND('PL.1 - FY24'!J45,0) -> 948 | E33: =C33 -> 948 | L33: ="As at "&TEXT(comp_period_1,"MMMM DD, YYYY") -> As at June 30, 2024 | M33: $ | N33: =SUM(N31:N32) -> 1204016 | O33: $ | P33: =SUM(P31:P32) -> 1204016
A34: ="As at "&TEXT(currentperiod_end_date,"MMMM DD, YYYY") -> As at June 30, 2025 | B34: $ | C34: =SUM(C32:C33) -> 948 | D34: $ | E34: =SUM(E32:E33) -> 948 | L34: Amortization in the year | N34: ='IA.1 - Intangible'!AD13 -> 1256364 | P34: =N34 -> 1256364
L35: ="As at "&TEXT(currentperiod_end_date,"MMMM DD, YYYY") -> As at June 30, 2025 | M35: $ | N35: =SUM(N33:N34) -> 2460380 | O35: $ | P35: =SUM(P33:P34) -> 2460380
A36: Carrying Amount:
A37: ="As at "&TEXT(comp_period_1,"MMMM DD, YYYY") -> As at June 30, 2024 | B37: $ | C37: =C26-C32 -> 0 | D37: $ | E37: =E26-E32 -> 0 | L37: Carrying Amount:
A38: ="As at "&TEXT(currentperiod_end_date,"MMMM DD, YYYY") -> As at June 30, 2025 | B38: $ | C38: =C29-C34 -> -1896 | D38: $ | E38: =E29-E34 -> -1896 | L38: ="As at "&TEXT(comp_period_1,"MMMM DD, YYYY") -> As at June 30, 2024 | M38: $ | N38: =N28-N33 -> 5527806 | O38: $ | P38: =P28-P33 -> 5527806
L39: ="As at "&TEXT(currentperiod_end_date,"MMMM DD, YYYY") -> As at June 30, 2025 | M39: $ | N39: =N28-N35 -> 4271442 | O39: $ | P39: =P28-P35 -> 4271442
A40: CHECK | E40: =E37-FS.1!E23 -> -5341
A41: CHECK | E41: =E38-FS.1!C23 -> -7237 | L41: CHECK | P41: =FS.1!E24-P38 -> 0
L42: CHECK | P42: =FS.1!C24-P39 -> 0
G45: Black-scholes option model inputs | L45: Asset acquisition
F46: Share price at grant date ($) | G46: =DER.V!C19 -> 0.5 | L46: Purchase price consideration
F47: Exercise price ($) | G47: =DER.V!C20 -> 0.375 | L47: Fair value of 12,000,000 common shares issued at $0.50 | M47: $ | N47: ='NOTES - TEXT'!G39 -> 6000000
F48: Expected annual volatility (%) | G48: =DER.V!C22 -> 1 | L48: Settlement of pre-existing relationship | N48: ='Asset Acquisition'!H4 -> 556400
A49: Other expenses and income | F49: Expected life (in years) | G49: =DER.V!C21 -> 0.33333333 | L49: Total purchase price | M49: $ | N49: =SUM(N47:N48) -> 6556400
C50: =C2 -> June 30, 2025 | E50: =E2 -> June 30, 2024 | F50: Expected dividend yield (%) | G50: 0
A51: Convertible loan accretion expense | B51: $ | C51: =-'BS.1 - F25'!F178 -> -31957 | D51: $ | E51: =-'BS.2 - F24'!F178 -> -24938 | F51: Risk-free interest rate (%) | G51: =DER.V!C24 -> 0.0476 | L51: Assets acquired and liabilities assumed:
A52: Gain on re-measurement of derivative liability | C52: 0 | E52: =-'BS.2 - F24'!F179 -> 75000 | L52: ='Asset Acquisition'!G7 -> Cash | M52: $ | N52: ='Asset Acquisition'!H7 -> 21130
A53: Net financial expense | B53: $ | C53: =SUM(C51:C52) -> -31957 | D53: $ | E53: =SUM(E51:E52) -> 50062 | L53: ='Asset Acquisition'!G9 -> Prepaid expenses | N53: ='Asset Acquisition'!H9 -> 2240
L54: ='Asset Acquisition'!G10 -> Inventory | N54: ='Asset Acquisition'!H10 -> 397450
A55: CHECK | C55: =FS.1!G66-C53 -> 0 | E55: =FS.1!I66-E53 -> 0 | L55: ='Asset Acquisition'!G12 -> Equipment | N55: ='Asset Acquisition'!H12 -> 6108
L56: ='Asset Acquisition'!G13 -> Accounts payables and accrued liabilities | N56: ='Asset Acquisition'!H13 -> -178623
L57: ='Asset Acquisition'!G15 -> Sales tax receivable | N57: ='Asset Acquisition'!H15 -> 26371
G58: Geske compound option model inputs | L58: ='Asset Acquisition'!G17 -> Income tax payable | N58: ='Asset Acquisition'!H17 -> -98
F59: Share price at grant date ($) | G59: =G46 -> 0.5 | L59: ='Asset Acquisition'!G20 -> Intangible asset | N59: ='Asset Acquisition'!H20 -> 6281822
F60: Exercise price ($) | G60: 0.0001 | L60: Total purchase price allocated | M60: $ | N60: =SUM(N52:N59) -> 6556400
F61: Expected annual volatility (%) | G61: =DER.V!D54 -> 1
F62: Expected life (in years) | G62: 5.33
F63: Expected dividend yield (%) | G63: 0
F64: Risk-free interest rate (%) | G64: =DER.V!D55 -> 0.0476
A67: Related party transactions
A68: Key management compensation | C68: =C2 -> June 30, 2025 | E68: =E2 -> June 30, 2024
A69: Consulting fees payable to a entity controlled by the CFO of the Company (1) | B69: $ | C69: 25200 | D69: $ | E69: 0
A70: Total key management compensation | B70: $ | C70: =SUM(C69:C69) -> 25200 | D70: $ | E70: =SUM(E69:E69) -> 0
A73: Convertible Debt - LINKED
C74: =FS.1!C53 -> June 30, 2025 | E74: =FS.1!E53 -> June 30, 2024
A75: Opening balance | B75: $ | C75: =E79 -> 204577 | D75: $ | E75: 0
A76: Fair value of convertible notes on issuance | C76: 0 | E76: ='COV.DEBT'!C28 -> 150000
A77: Accretion expense | C77: =ROUND(SUM('[1]COV.DEBT - AMEND'!$D$40:$D$51),0) -> 31957 | E77: =ROUND(SUM('[1]COV.DEBT - AMEND'!$D$29:$D$39),0) -> 24938
A78: Interest expense | C78: =-ROUND(SUM('[1]COV.DEBT - AMEND'!$E$40:$E$51),0) -> 37565 | E78: =-ROUND(SUM('[1]COV.DEBT - AMEND'!$E$29:$E$39),0) -> 29639
A79: Ending balance | B79: $ | C79: =SUM(C75:C78) -> 274099 | D79: $ | E79: =SUM(E75:E78) -> 204577
A81: CHECK | C81: =FS.1!C32-C79 -> 0 | E81: =FS.1!E32-E79 -> 0

Sheet NOTES - TEXT
A1: LINKS TO WORD FS - DO NOT EDIT THIS TAB
F2: Quarter | G2: YTD / Year
A3: Note # | B3: Title | C3: Code | D3: Sequence | E3: Identififer | F3: Amount | G3: Amount | H3: Description
A4: 1 | B4: Nature of ops | C4: GEN | D4: 1 | E4: =C4&D4 -> GEN1 | G4: =-FS.1!C5 -> 683160 | H4: working capital Deficiency - CY
A5: =A4 -> 1 | B5: =B4 -> Nature of ops | C5: =C4 -> GEN | D5: =D4+1 -> 2 | E5: =C5&D5 -> GEN2 | G5: =FS.1!E5 -> -67788 | H5: working capital - PY
A6: =A5 -> 1 | B6: =B5 -> Nature of ops | C6: =C5 -> GEN | D6: =D5+1 -> 3 | E6: =C6&D6 -> GEN3 | G6: =-FS.1!G73 -> 1871736 | H6: net loss YTD - current
A7: =A6 -> 1 | B7: =B6 -> Nature of ops | C7: =C6 -> GEN | D7: =D6+1 -> 4 | E7: =C7&D7 -> GEN4 | G7: =-FS.1!I73 -> #REF! | H7: net loss YTD - prior
A8: =A7 -> 1 | B8: =B7 -> Nature of ops | C8: =C7 -> GEN | D8: =D7+1 -> 5 | E8: =C8&D8 -> GEN5 | G8: =-FS.1!C73 -> 0 | H8: net loss 3 mths - current
A9: =A8 -> 1 | B9: =B8 -> Nature of ops | C9: =C8 -> GEN | D9: =D8+1 -> 6 | E9: =C9&D9 -> GEN6 | G9: =-FS.1!E73 -> 0 | H9: net loss 3 mths - prior
A10: 7 | B10: RPT | C10: RPT | D10: 1 | E10: =C10&D10 -> RPT1 | G10: =ROUND((11339.85+10500+10500),0) -> 32340 | H10: AP balance - to CEO of the Company
A11: =A10 -> 7 | B11: =B10 -> RPT | C11: =C10 -> RPT | D11: =D10+1 -> 2 | E11: =C11&D11 -> RPT2 | G11: =ROUND((20717.55+46725),0) -> 67443 | H11: AP balance - to CFO
A12: =A11 -> 7 | B12: =B11 -> RPT | C12: =C11 -> RPT | D12: =D11+1 -> 3 | E12: =C12&D12 -> RPT3 | G12: 2500 | H12: AP balance - UpCapital
A13: =A12 -> 7 | B13: =B12 -> RPT | C13: =C12 -> RPT | D13: =D12+1 -> 4 | E13: =C13&D13 -> RPT4 | G13: ='NOTES - TABLE'!AD27 -> 59698 | H13: Total consulting expenses - CFO - CY YTD
A14: =A13 -> 7 | B14: =B13 -> RPT | C14: =C13 -> RPT | D14: =D13+1 -> 5 | E14: =C14&D14 -> RPT5 | G14: ='NOTES - TABLE'!Z27 -> 24099 | H14: Total consulting expenses - CFO - CY 3 mths
A15: =A14 -> 7 | B15: =B14 -> RPT | C15: =C14 -> RPT | D15: =D14+1 -> 6 | E15: =C15&D15 -> RPT6 | G15: Nil | H15: Total consulting expenses - CEO - - CY YTD
A16: =A15 -> 7 | B16: =B15 -> RPT | C16: =C15 -> RPT | D16: =D15+1 -> 7 | E16: =C16&D16 -> RPT7 | G16: Nil | H16: Total consulting expenses - CEO - - CY 3 mths
A17: =A16 -> 7 | B17: =B16 -> RPT | C17: =C16 -> RPT | D17: =D16+1 -> 8 | E17: =C17&D17 -> RPT8 | G17: Nil | H17: Total consulting expenses - UpCapital - CY YTD
A18: =A17 -> 7 | B18: =B17 -> RPT | C18: =C17 -> RPT | D18: =D17+1 -> 9 | E18: =C18&D18 -> RPT9 | G18: Nil | H18: Total consulting expenses - UpCapital - CY 3 mths
A19: =A18 -> 7 | B19: =B18 -> RPT | C19: =C18 -> RPT | D19: =D18+1 -> 10 | E19: =C19&D19 -> RPT10 | G19: Nil | H19: Total director fees - CY YTD
A20: =A19 -> 7 | B20: =B19 -> RPT | C20: =C19 -> RPT | D20: =D19+1 -> 11 | E20: =C20&D20 -> RPT11 | G20: Nil | H20: Total director fees - CY 3 mths
A21: =A20 -> 7 | B21: =B20 -> RPT | C21: =C20 -> RPT | D21: =D20+1 -> 12 | E21: =C21&D21 -> RPT12 | G21: Nil | H21: Total consulting expenses - CFO - PY YTD
A22: =A21 -> 7 | B22: =B21 -> RPT | C22: =C21 -> RPT | D22: =D21+1 -> 13 | E22: =C22&D22 -> RPT13 | G22: Nil | H22: Total consulting expenses - CFO - PY 3mths
A23: =A22 -> 7 | B23: =B22 -> RPT | C23: =C22 -> RPT | D23: =D22+1 -> 14 | E23: =C23&D23 -> RPT14 | G23: ='NOTES - TABLE'!AF28 -> 22500 | H23: Total consulting expenses - CEO - PY YTD
A24: =A23 -> 7 | B24: =B23 -> RPT | C24: =C23 -> RPT | D24: =D23+1 -> 15 | E24: =C24&D24 -> RPT15 | G24: ='NOTES - TABLE'!AB28 -> 22500 | H24: Total consulting expenses - CEO - PY 3 mths
A25: =A24 -> 7 | B25: =B24 -> RPT | C25: =C24 -> RPT | D25: =D24+1 -> 16 | E25: =C25&D25 -> RPT16 | G25: 1155080 | H25: Total consulting expenses - UpCapital - PY YTD
A26: =A25 -> 7 | B26: =B25 -> RPT | C26: =C25 -> RPT | D26: =D25+1 -> 17 | E26: =C26&D26 -> RPT17 | G26: =G25 -> 1155080 | H26: Total consulting expenses - UpCapital - PY 3 mths
A27: =A25 -> 7 | B27: =B25 -> RPT | C27: =C25 -> RPT | D27: =D25+1 -> 17 | E27: =C27&D27 -> RPT17 | G27: 0 | H27: Total director fees - PY
A28: 8 | B28: DEBT | C28: NN | D28: 1 | E28: =C28&D28 -> NN1 | G28: ='COV.DEBT'!B18 -> 12708 | H28: interest expense - convertible debt - CY
A29: =A28 -> 8 | B29: =B28 -> DEBT | C29: =C28 -> NN | D29: =D28+1 -> 2 | E29: =C29&D29 -> NN2 | G29: nil | H29: interest expense - convertible debt - PY
A30: =A29 -> 8 | B30: =B29 -> DEBT | C30: =C29 -> NN | D30: =D29+1 -> 3 | E30: =C30&D30 -> NN3 | G30: 225000 | H30: Convert note principal OS - CY
A31: =A30 -> 8 | B31: =B30 -> DEBT | C31: =C30 -> NN | D31: =D30+1 -> 4 | E31: =C31&D31 -> NN4 | G31: nil | H31: Convert note principal OS - PY
A32: =A31 -> 8 | B32: =B31 -> DEBT | C32: =C31 -> NN | D32: =D31+1 -> 5 | E32: =C32&D32 -> NN5 | G32: =G28 -> 12708 | H32: Interest payable Convert note - CY
A33: =A32 -> 8 | B33: =B32 -> DEBT | C33: =C32 -> NN | D33: =D32+1 -> 6 | E33: =C33&D33 -> NN6 | G33: nil | H33: Interest payable Convert note - PY
A34: =A33 -> 8 | B34: =B33 -> DEBT | C34: =C33 -> NN | D34: =D33+1 -> 7 | E34: =C34&D34 -> NN7 | G34: ='COV.DEBT'!B22 -> 75000 | H34: FV of derivative liability - initial recognition
A35: =A34 -> 8 | B35: =B34 -> DEBT | C35: =C34 -> NN | D35: =D34+1 -> 8 | E35: =C35&D35 -> NN8 | G35: ='COV.DEBT'!B23 -> 150000 | H35: host liability FV
A36: =A35 -> 8 | B36: =B35 -> DEBT | C36: =C35 -> NN | D36: =D35+1 -> 9 | E36: =C36&D36 -> NN9 | G36: ='COV.DEBT'!B39 -> 87708 | H36: Accretion expense
A37: 9 | B37: Share capital | C37: RR | D37: 1 | E37: =C37&D37 -> RR1 | G37: 12000000 | H37: Shares issued on acquisition of Hallor
A38: =A37 -> 9 | B38: =B37 -> Share capital | C38: =C37 -> RR | D38: =D37+1 -> 2 | E38: =C38&D38 -> RR2 | G38: 0.5 | H38: FV per share issued
A39: =A38 -> 9 | B39: =B38 -> Share capital | C39: =C38 -> RR | D39: =D38+1 -> 3 | E39: =C39&D39 -> RR3 | G39: =G37*G38 -> 6000000 | H39: Total FV of share consideration for Hallor
A40: =A39 -> 9 | B40: =B39 -> Share capital | C40: =C39 -> RR | D40: =D39+1 -> 4 | E40: =C40&D40 -> RR4 | G40: 900000 | H40: # of common shares issued as finders fee
A41: =A40 -> 9 | B41: =B40 -> Share capital | C41: =C40 -> RR | D41: =D40+1 -> 5 | E41: =C41&D41 -> RR5 | G41: =G38*G40 -> 450000 | H41: Total FV of finders fee for Hallor
A42: MDA | B42: MDA | C42: MDA | D42: 1 | E42: =C42&D42 -> MDA1 | G42: 31912501 | H42: # common shares at MDA report date
A43: =A42 -> MDA | B43: =B42 -> MDA | C43: =C42 -> MDA | D43: =D42+1 -> 2 | E43: =C43&D43 -> MDA2 | G43: 2687500 | H43: # SW OS at MDA report date
A44: =A43 -> MDA | B44: =B43 -> MDA | C44: =C43 -> MDA | D44: =D43+1 -> 3 | E44: =C44&D44 -> MDA3 | G44: =FS.1!C13 -> 392 | H44: cash balance at CY reporting date
A45: =A44 -> MDA | B45: =B44 -> MDA | C45: =C44 -> MDA | D45: =D44+1 -> 4 | E45: =C45&D45 -> MDA4 | G45: =FS.1!E13 -> 5604 | H45: cash balance at PY reporting date
A46: =A45 -> MDA | B46: =B45 -> MDA | C46: =C45 -> MDA | D46: =D45+1 -> 5 | E46: =C46&D46 -> MDA5 | G46: =FS.1!C36 -> 882713 | H46: current liabilities - CY
A47: =A46 -> MDA | B47: =B46 -> MDA | C47: =C46 -> MDA | D47: =D46+1 -> 6 | E47: =C47&D47 -> MDA6 | G47: =FS.1!E36 -> 556206 | H47: current liabilities - PY
A48: =A47 -> MDA | B48: =B47 -> MDA | C48: =C47 -> MDA | D48: =D47+1 -> 7 | E48: =C48&D48 -> MDA7 | G48: ='COV.DEBT'!B7 -> 225000 | H48: Funds raised on convertible debentures
A49: =A48 -> MDA | B49: =B48 -> MDA | C49: =C48 -> MDA | D49: =D48+1 -> 8 | E49: =C49&D49 -> MDA8 | G49: ='NOTES - TABLE'!N52 -> 21130 | H49: Cash received on acquisition of Hallor

Sheet MDA
A1: SELECT ANNUAL INFORMATION | G1: SELECT ANNUAL INFORMATION | L1: For the three-months period ended | T1: Three months ended
A2: As at | B2: =TEXT(priorperiod_end_date,"MMMM DD, YYYY") -> June 30, 2024 | C2: =TEXT(EDATE(B2,-12),"MMMM DD, YYYY") -> June 30, 2023 | H2: Three-month periods ended | N2: =TEXT(currentperiod_end_date,"MMMM DD, YYYY") -> June 30, 2025 | P2: =TEXT(EDATE(N2,-12),"MMMM DD, YYYY") -> June 30, 2024 | Q2: $ Movement | R2: % Movement | S2: Cash provided by (used in): | U2: =N2 -> June 30, 2025 | W2: =P2 -> June 30, 2024
B3: $ | C3: $ | H3: =TEXT(currentperiod_end_date,"MMMM DD, YYYY") -> June 30, 2025 | I3: =TEXT(EOMONTH(EDATE(H3,-3),0),"MMMM DD, YYYY") -> March 31, 2025 | J3: =TEXT(EOMONTH(EDATE(I3,-3),0),"MMMM DD, YYYY") -> December 31, 2024 | K3: =TEXT(EOMONTH(EDATE(J3,-3),0),"MMMM DD, YYYY") -> September 30, 2024 | L3: Operating Expenses | S3: Operating activities | T3: $ | U3: =FS.1!C122 -> -5212 | V3: $ | W3: =FS.1!E122 -> #REF!
A4: Revenues | B4: 0 | C4: 0 | H4: $ | I4: $ | J4: $ | K4: $ | L4: ='NOTES - TABLE'!A3 -> Bank fees | M4: $ | N4: ='Note Disclosures'!C248 -> 367 | O4: $ | P4: ='Note Disclosures'!D248 -> 0 | Q4: =N4-P4 -> 367 | R4: =IFERROR(Q4/P4,1) -> 1 | S4: Investing activities | U4: =FS.1!C128 -> 0 | W4: =FS.1!E128 -> #REF!
A5: Operating expenses | B5: 1404283 | C5: 63189 | G5: Total revenue | H5: =FS.1!C54 -> 0 | I5: - | J5: - | K5: - | L5: ='NOTES - TABLE'!A4 -> Professional fees | N5: ='Note Disclosures'!C249 -> 54025 | P5: ='Note Disclosures'!D249 -> 5600 | Q5: =N5-P5 -> 48425 | R5: =IFERROR(Q5/P5,1) -> 8.6473214 | S5: Financing activities | U5: =FS.1!C133 -> 0 | W5: =FS.1!E133 -> 225000
A6: Net loss for the period | B6: 1404283 | C6: 63189 | G6: Net loss | H6: =FS.1!C69 -> 0 | I6: =-'PL.2 - FY23'!K16 -> -74582.82 | J6: =-'PL.2 - FY23'!J16 -> -10194.66 | K6: =-'PL.2 - FY23'!I16+1 -> -1302030.1 | L6: ='NOTES - TABLE'!A5 -> Consulting expense | N6: ='Note Disclosures'!C250 -> 78800 | P6: ='Note Disclosures'!D250 -> 10000 | Q6: =N6-P6 -> 68800 | R6: =IFERROR(Q6/P6,1) -> 6.88 | S6: Increase (decrease) in cash | T6: $ | U6: =FS.1!C135 -> -5212 | V6: $ | W6: =FS.1!E135 -> #REF!
A7: Comprehensive loss for the period | B7: 1367883 | C7: 63189 | G7: Net income / (loss) and comprehensive income / (loss) | H7: =FS.1!C73 -> 0 | I7: ='PL.2 - FY23'!K19 -> -58982.82 | J7: ='PL.2 - FY23'!J19 -> 5405.34 | K7: ='PL.2 - FY23'!I19+1 -> -1296830.1 | L7: ='NOTES - TABLE'!A7 -> Other miscellaneous | N7: ='Note Disclosures'!#REF! -> #REF! | P7: ='Note Disclosures'!#REF! -> #REF! | Q7: =N7-P7 -> #REF! | R7: =IFERROR(Q7/P7,1) -> 1
A8: Basic and diluted loss per share | B8: -0.1 | C8: -0.02 | G8: Basic and diluted income / (loss) per share | H8: =FS.1!C77 -> 0 | I8: -0.0031023178 | J8: 0.00028430452 | K8: -0.19821692 | L8: ='NOTES - TABLE'!A8 -> Office expenses | N8: ='Note Disclosures'!C252 -> 1460 | P8: ='Note Disclosures'!D252 -> 0 | Q8: =N8-P8 -> 1460 | R8: =IFERROR(Q8/P8,1) -> 1
L9: ='NOTES - TABLE'!A9 -> Meals and entertainment | N9: ='Note Disclosures'!C253 -> 531 | P9: ='Note Disclosures'!D253 -> 1875 | Q9: =N9-P9 -> -1344 | R9: =IFERROR(Q9/P9,1) -> -0.7168
A10: As at | B10: =B2 -> June 30, 2024 | C10: =C2 -> June 30, 2023 | H10: Three-month periods ended | L10: ='NOTES - TABLE'!A10 -> Travel expenses | N10: ='Note Disclosures'!C254 -> 619 | P10: ='Note Disclosures'!D254 -> 0 | Q10: =N10-P10 -> 619 | R10: =IFERROR(Q10/P10,1) -> 1
B11: $ | C11: $ | H11: =TEXT(EOMONTH(EDATE(K3,-3),0),"MMMM DD, YYYY") -> June 30, 2024 | I11: =TEXT(EOMONTH(EDATE(H11,-3),0),"MMMM DD, YYYY") -> March 31, 2024 | J11: =TEXT(EOMONTH(EDATE(I11,-3),0),"MMMM DD, YYYY") -> December 31, 2023 | K11: =TEXT(EOMONTH(EDATE(J11,-3),0),"MMMM DD, YYYY") -> September 30, 2023 | L11: ='NOTES - TABLE'!A11 -> Transfer agent and regulatory expenses | N11: ='Note Disclosures'!C255 -> 985 | P11: ='Note Disclosures'!D255 -> 0 | Q11: =N11-P11 -> 985 | R11: =IFERROR(Q11/P11,1) -> 1
A12: Working capital (deficiency) | B12: =FS.1!E5 -> -67788 | C12: 417585 | H12: $ | I12: $ | J12: $ | K12: $ | L12: ='NOTES - TABLE'!A12 -> Insurance | N12: ='Note Disclosures'!C256 -> 5250 | P12: ='Note Disclosures'!D256 -> 0 | Q12: =N12-P12 -> 5250 | R12: =IFERROR(Q12/P12,1) -> 1
A13: Total assets | B13: =FS.1!E27 -> 6021565 | C13: 474315 | G13: Total revenue | H13: - | I13: - | J13: - | K13: - | L13: ='NOTES - TABLE'!A13 -> Shipping expense | N13: ='Note Disclosures'!C257 -> 9696 | P13: ='Note Disclosures'!D257 -> 0 | Q13: =N13-P13 -> 9696 | R13: =IFERROR(Q13/P13,1) -> 1
A14: Total liabilities | B14: =FS.1!E39 -> 556206 | C14: 56730 | G14: Net loss | H14: =FS.1!E73 -> 0 | I14: -46303 | J14: -1833 | K14: -9753 | L14: ='NOTES - TABLE'!A14 -> Shop supplies | N14: ='Note Disclosures'!C258 -> 5494 | P14: ='Note Disclosures'!D258 -> 0 | Q14: =N14-P14 -> 5494 | R14: =IFERROR(Q14/P14,1) -> 1
A15: Share capital | B15: =FS.1!E41 -> 8224099 | C15: 524174 | G15: Net income / (loss) and comprehensive income / (loss) | H15: =H14 -> 0 | I15: =I14 -> -46303 | J15: =J14 -> -1833 | K15: =K14 -> -9753 | L15: ='NOTES - TABLE'!A15 -> Depreciation and amortization | N15: ='Note Disclosures'!C259 -> 2728 | P15: ='Note Disclosures'!D259 -> 0 | Q15: =N15-P15 -> 2728 | R15: =IFERROR(Q15/P15,1) -> 1
A16: Accumulated deficit | B16: =FS.1!E43 -> #REF! | C16: -106589 | G16: Basic and diluted income / (loss) per share | H16: 0 | I16: -0.01 | J16: 0 | K16: 0 | L16: ='NOTES - TABLE'!A16 -> Foreign exchange | N16: ='Note Disclosures'!C260 -> 509 | P16: ='Note Disclosures'!D260 -> 0 | Q16: =N16-P16 -> 509 | R16: =IFERROR(Q16/P16,1) -> 1
L17: ='NOTES - TABLE'!#REF! -> #REF! | N17: ='Note Disclosures'!C261 -> 48 | P17: ='Note Disclosures'!D261 -> 0 | Q17: =N17-P17 -> 48 | R17: =IFERROR(Q17/P17,1) -> 1
L18: Total general and administration and sales and marketing | M18: $ | N18: =SUM(N4:N17) -> #REF! | O18: $ | P18: =SUM(P4:P17) -> #REF!
L19: ='BS & IS'!G10 -> Other income (expenses)
L20: ='BS & IS'!G12 -> Interest income | M20: $ | N20: ='BS & IS'!J12 -> 14 | O20: $ | P20: ='BS & IS'!L12 -> #REF! | Q20: =N20-P20 -> #REF! | R20: =IFERROR(Q20/P20,1) -> 1
L21: ='BS & IS'!G13 -> Net financial expenses | N21: ='BS & IS'!J13 -> -31957 | P21: ='BS & IS'!L13 -> 50062 | Q21: =N21-P21 -> -82019 | R21: =IFERROR(Q21/P21,1) -> -1.6383484 | S21: Total G&A breakdown
L22: ='BS & IS'!G14 -> Interest expense | N22: ='BS & IS'!J14 -> -45232 | P22: ='BS & IS'!L14 -> -33787 | Q22: =N22-P22 -> -11445 | R22: =IFERROR(Q22/P22,1) -> 0.33873975 | U22: =TEXT(currentperiod_end_date,"MMMM DD, YYYY") -> June 30, 2025 | W22: =TEXT(EDATE(U22,-12),"MMMM DD, YYYY") -> June 30, 2024
L23: Net loss and comprehensive loss | M23: $ | N23: =-N18+SUM(N19:N22) -> #REF! | O23: $ | P23: =-P18+SUM(P19:P22) -> #REF! | S23: Operating Expenses
S24: =L48 -> Bank fees | T24: $ | U24: =_xlfn.XLOOKUP($S24,$L$48:$L$61,$N$48:$N$61) -> 2281 | V24: $ | W24: =_xlfn.XLOOKUP($S24,$L$48:$L$61,$P$48:$P$61) -> 2282
S25: =L49 -> Professional fees | U25: =_xlfn.XLOOKUP($S25,$L$48:$L$61,$N$48:$N$61) -> 133726 | W25: =_xlfn.XLOOKUP($S25,$L$48:$L$61,$P$48:$P$61) -> #REF!
L26: CHECK | N26: =N23-'BS & IS'!J15 -> #REF! | P26: =P23-'BS & IS'!L15 -> #REF! | S26: =L50 -> Consulting expense | U26: =_xlfn.XLOOKUP($S26,$L$48:$L$61,$N$48:$N$61) -> 318291 | W26: =_xlfn.XLOOKUP($S26,$L$48:$L$61,$P$48:$P$61) -> 134140
S27: =L52 -> Office expenses | U27: =_xlfn.XLOOKUP($S27,$L$48:$L$61,$N$48:$N$61) -> 8370 | W27: =_xlfn.XLOOKUP($S27,$L$48:$L$61,$P$48:$P$61) -> #REF!
S28: =L53 -> Meals and entertainment | U28: =_xlfn.XLOOKUP($S28,$L$48:$L$61,$N$48:$N$61) -> 2747 | W28: =_xlfn.XLOOKUP($S28,$L$48:$L$61,$P$48:$P$61) -> #REF!
S29: =L54 -> Travel expenses | U29: =_xlfn.XLOOKUP($S29,$L$48:$L$61,$N$48:$N$61) -> 934 | W29: =_xlfn.XLOOKUP($S29,$L$48:$L$61,$P$48:$P$61) -> #REF!
S30: =L55 -> Transfer agent and regulatory expenses | U30: =_xlfn.XLOOKUP($S30,$L$48:$L$61,$N$48:$N$61) -> 4524 | W30: =_xlfn.XLOOKUP($S30,$L$48:$L$61,$P$48:$P$61) -> #REF!
S31: =L56 -> Insurance | U31: =_xlfn.XLOOKUP($S31,$L$48:$L$61,$N$48:$N$61) -> 0 | W31: =_xlfn.XLOOKUP($S31,$L$48:$L$61,$P$48:$P$61) -> 10700
S32: =L57 -> Shipping expense | U32: =_xlfn.XLOOKUP($S32,$L$48:$L$61,$N$48:$N$61) -> 26182 | W32: =_xlfn.XLOOKUP($S32,$L$48:$L$61,$P$48:$P$61) -> #REF!
S33: =L58 -> Shop supplies | U33: =_xlfn.XLOOKUP($S33,$L$48:$L$61,$N$48:$N$61) -> 0 | W33: =_xlfn.XLOOKUP($S33,$L$48:$L$61,$P$48:$P$61) -> #REF!
S34: =L59 -> Depreciation and amortization | U34: =_xlfn.XLOOKUP($S34,$L$48:$L$61,$N$48:$N$61) -> 241 | W34: =_xlfn.XLOOKUP($S34,$L$48:$L$61,$P$48:$P$61) -> #REF!
S35: =L60 -> Foreign exchange | U35: =_xlfn.XLOOKUP($S35,$L$48:$L$61,$N$48:$N$61) -> 1256364 | W35: =_xlfn.XLOOKUP($S35,$L$48:$L$61,$P$48:$P$61) -> #REF!
S36: =L61 -> #REF! | U36: =_xlfn.XLOOKUP($S36,$L$48:$L$61,$N$48:$N$61) -> #REF! | W36: =_xlfn.XLOOKUP($S36,$L$48:$L$61,$P$48:$P$61) -> #REF!
S37: Total general and administration | T37: $ | U37: =SUM(U24:U36) -> #REF! | V37: $ | W37: =SUM(W24:W36) -> #REF!
S39: CHECK | U39: =U37-'BS & IS'!J7 -> #REF! | W39: =W37-'BS & IS'!L7 -> #REF!
L45: Year to date
N46: =TEXT(currentperiod_end_date,"MMMM DD, YYYY") -> June 30, 2025 | P46: =TEXT(EDATE(N46,-12),"MMMM DD, YYYY") -> June 30, 2024 | Q46: $ Movement | R46: % Movement
L47: Operating Expenses
L48: ='NOTES - TABLE'!A3 -> Bank fees | M48: $ | N48: ='Note Disclosures'!E248 -> 2281 | O48: $ | P48: ='Note Disclosures'!F248 -> 2282 | Q48: =N48-P48 -> -1 | R48: =IFERROR(Q48/P48,1) -> -0.00043821209
L49: ='NOTES - TABLE'!A4 -> Professional fees | N49: ='Note Disclosures'!E249 -> 133726 | P49: ='Note Disclosures'!F249 -> #REF! | Q49: =N49-P49 -> #REF! | R49: =IFERROR(Q49/P49,1) -> 1
L50: ='NOTES - TABLE'!A5 -> Consulting expense | N50: ='Note Disclosures'!E250 -> 318291 | P50: ='Note Disclosures'!F250 -> 134140 | Q50: =N50-P50 -> 184151 | R50: =IFERROR(Q50/P50,1) -> 1.3728269
L51: ='NOTES - TABLE'!A7 -> Other miscellaneous | N51: ='Note Disclosures'!#REF! -> #REF! | P51: ='Note Disclosures'!#REF! -> #REF! | Q51: =N51-P51 -> #REF! | R51: =IFERROR(Q51/P51,1) -> 1
L52: ='NOTES - TABLE'!A8 -> Office expenses | N52: ='Note Disclosures'!E252 -> 8370 | P52: ='Note Disclosures'!F252 -> #REF! | Q52: =N52-P52 -> #REF! | R52: =IFERROR(Q52/P52,1) -> 1
L53: ='NOTES - TABLE'!A9 -> Meals and entertainment | N53: ='Note Disclosures'!E253 -> 2747 | P53: ='Note Disclosures'!F253 -> #REF! | Q53: =N53-P53 -> #REF! | R53: =IFERROR(Q53/P53,1) -> 1
L54: ='NOTES - TABLE'!A10 -> Travel expenses | N54: ='Note Disclosures'!E254 -> 934 | P54: ='Note Disclosures'!F254 -> #REF! | Q54: =N54-P54 -> #REF! | R54: =IFERROR(Q54/P54,1) -> 1
L55: ='NOTES - TABLE'!A11 -> Transfer agent and regulatory expenses | N55: ='Note Disclosures'!E255 -> 4524 | P55: ='Note Disclosures'!F255 -> #REF! | Q55: =N55-P55 -> #REF! | R55: =IFERROR(Q55/P55,1) -> 1
L56: ='NOTES - TABLE'!A12 -> Insurance | N56: ='Note Disclosures'!E256 -> 0 | P56: ='Note Disclosures'!F256 -> 10700 | Q56: =N56-P56 -> -10700 | R56: =IFERROR(Q56/P56,1) -> -1
L57: ='NOTES - TABLE'!A13 -> Shipping expense | N57: ='Note Disclosures'!E257 -> 26182 | P57: ='Note Disclosures'!F257 -> #REF! | Q57: =N57-P57 -> #REF! | R57: =IFERROR(Q57/P57,1) -> 1
L58: ='NOTES - TABLE'!A14 -> Shop supplies | N58: ='Note Disclosures'!E258 -> 0 | P58: ='Note Disclosures'!F258 -> #REF! | Q58: =N58-P58 -> #REF! | R58: =IFERROR(Q58/P58,1) -> 1
L59: ='NOTES - TABLE'!A15 -> Depreciation and amortization | N59: ='Note Disclosures'!E259 -> 241 | P59: ='Note Disclosures'!F259 -> #REF! | Q59: =N59-P59 -> #REF! | R59: =IFERROR(Q59/P59,1) -> 1
L60: ='NOTES - TABLE'!A16 -> Foreign exchange | N60: ='Note Disclosures'!E260 -> 1256364 | P60: ='Note Disclosures'!F260 -> #REF! | Q60: =N60-P60 -> #REF! | R60: =IFERROR(Q60/P60,1) -> 1
L61: ='NOTES - TABLE'!#REF! -> #REF! | N61: ='Note Disclosures'!E261 -> 43 | P61: ='Note Disclosures'!F261 -> #REF! | Q61: =N61-P61 -> #REF! | R61: =IFERROR(Q61/P61,1) -> 1
L62: Total general and administration and sales and marketing | M62: $ | N62: =SUM(N48:N61) -> #REF! | O62: $ | P62: =SUM(P48:P61) -> #REF!

Sheet FIN >>
B2: This page intentionally blank

Sheet BS.PRO
A1: =company_name -> Consolidated Hallor Group Inc.
A2: =currentperiod_end_date -> 45838 | AK2: Manual classification
F3: =SUM(F8:F186) -> 0 | G3: =SUM(G8:G186) -> 1.0113581e-09 | H3: =SUM(H8:H186) -> 0 | I3: =SUM(I8:I186) -> 0 | J3: =SUM(J8:J186) -> 0 | K3: =SUM(K8:K186) -> 0 | L3: =SUM(L8:L186) -> 0 | M3: =SUM(M8:M186) -> 9.3132257e-10 | ... AJ3: =SUM(AJ8:AJ186) -> 0
A4: Current Period Loss / (Profit) | B4: =SUM(B100:B186) -> 325418.6 | C4: =SUM(C100:C186) -> 289954.57 | D4: =SUM(D100:D186) -> 1256364 | E4: =SUM(E100:E186) -> -26 | F4: =SUM(F100:F186) -> 1871710 | G4: =SUM(G100:G186) -> 56265.91 | H4: =SUM(H100:H186) -> 468266.8 | I4: =SUM(I100:I186) -> 1314741.7 | ... AJ4: =SUM(AJ100:AJ186) -> -11765764
B5: TB.1 | C5: TB.1 | D5: AJE.1 | AP5: 101 | AQ5: =AP5+1 -> 102 | AR5: =AQ5+1 -> 103 | AS5: =AR5+1 -> 104 | AT5: =AS5+1 -> 105 | AU5: =AT5+1 -> 106 | AV5: =AU5+1 -> 107 | AW5: =AV5+1 -> 108 | AX5: =AW5+1 -> 109 | ... BG5: =BF5+1 -> 118
B6: Hallor Group | C6: Hallor Industries | D6: Consolidated | E6: Consolidated | F6: Consolidated | G6: Hallor Group | H6: Hallor Industries | I6: Hallor Group | J6: Hallor Industries | K6: Consolidated | L6: Consolidated | M6: Hallor Group | N6: Hallor Industries | O6: Hallor Group | P6: Hallor Industries | Q6: Consolidated | R6: Consolidated | S6: Hallor Group | T6: Hallor Industries | U6: Hallor Group | V6: Hallor Industries | W6: Consolidated | X6: Consolidated | Y6: Hallor Group | Z6: Hallor Industries | AA6: Hallor Group | AB6: Hallor Industries | AC6: Consolidated | AD6: Consolidated | AE6: Hallor Group | AF6: Hallor Industries | AG6: Hallor Group | AH6: Hallor Industries | AI6: Consolidated | AJ6: Consolidated | AP6: 201 | AQ6: =AP6+1 -> 202 | AR6: =AQ6+1 -> 203 | AS6: =AR6+1 -> 204 | AT6: =AS6+1 -> 205 | AU6: =AT6+1 -> 206 | AV6: =AU6+1 -> 207 | AW6: =AV6+1 -> 208 | AX6: =AW6+1 -> 209 | ... BG6: =BF6+1 -> 218
A7: GL account | B7: =TEXT(A2,"MMMM DD, YYYY") -> June 30, 2025 | C7: =B7 -> June 30, 2025 | D7: Summary of Manual Topside AJE's | E7: Consolidation + Reversing + OTH | F7: ="Adjusted Bal - "&TEXT($A$2,"MMMM DD, YYYY") -> Adjusted Bal - June 30, 2025 | G7: =EOMONTH(B7,12) -> 46203 | H7: =EOMONTH(C7,12) -> 46203 | I7: Topside - FORECAST | J7: Topside - OTH | K7: Consolidation + Reversing + OTH | L7: ="Adjusted Bal - "&TEXT(G$7,"MMMM DD, YYYY") -> Adjusted Bal - June 30, 2026 | M7: =EOMONTH(G7,12) -> 46568 | N7: =EOMONTH(H7,12) -> 46568 | O7: Topside - FORECAST | P7: Topside - OTH | Q7: Consolidation + Reversing + OTH | R7: ="Adjusted Bal - "&TEXT(M$7,"MMMM DD, YYYY") -> Adjusted Bal - June 30, 2027 | S7: =EOMONTH(M7,12) -> 46934 | T7: =EOMONTH(N7,12) -> 46934 | U7: Topside - FORECAST | V7: Topside - OTH | W7: Consolidation + Reversing + OTH | X7: ="Adjusted Bal - "&TEXT(S$7,"MMMM DD, YYYY") -> Adjusted Bal - June 30, 2028 | Y7: =EOMONTH(S7,12) -> 47299 | Z7: =EOMONTH(T7,12) -> 47299 | AA7: Topside - FORECAST | AB7: Topside - OTH | AC7: Consolidation + Reversing + OTH | AD7: ="Adjusted Bal - "&TEXT(Y$7,"MMMM DD, YYYY") -> Adjusted Bal - June 30, 2029 | AE7: =EOMONTH(Y7,12) -> 47664 | AF7: =EOMONTH(Z7,12) -> 47664 | AG7: Topside - FORECAST | AH7: Topside - OTH | AI7: Consolidation + Reversing | AJ7: ="Adjusted Bal - "&TEXT(AE$7,"MMMM DD, YYYY") -> Adjusted Bal - June 30, 2030 | AK7: FS Classification | AL7: FS Note Classification | AM7: Cash Flow Proof Classification | AP7: =_xlfn.XLOOKUP(AP6,FS.1!$T:$T,FS.1!$A:$A,0,0,1) -> Cash | AQ7: =_xlfn.XLOOKUP(AQ6,FS.1!$T:$T,FS.1!$A:$A,0,0,1) -> Receivables | AR7: =_xlfn.XLOOKUP(AR6,FS.1!$T:$T,FS.1!$A:$A,0,0,1) -> Prepaid expenses | AS7: =_xlfn.XLOOKUP(AS6,FS.1!$T:$T,FS.1!$A:$A,0,0,1) -> Sales tax receivable | AT7: =_xlfn.XLOOKUP(AT6,FS.1!$T:$T,FS.1!$A:$A,0,0,1) -> Inventory | AU7: =_xlfn.XLOOKUP(AU6,FS.1!$T:$T,FS.1!$A:$A,0,0,1) -> Due from related parties | AV7: =_xlfn.XLOOKUP(AV6,FS.1!$T:$T,FS.1!$A:$A,0,0,1) -> Current portion of loan receivable | AW7: =_xlfn.XLOOKUP(AW6,FS.1!$T:$T,FS.1!$A:$A,0,0,1) -> Equipment | ... BG7: =_xlfn.XLOOKUP(BG6,FS.1!$T:$T,FS.1!$A:$A,0,0,1) -> Accumulated deficit
A8: =COA!B4 -> 0001 Bank suspense | B8: =_xlfn.XLOOKUP(A8,'TB.1 - F25'!A:A,'TB.1 - F25'!D:D,0,0,1) -> 0 | C8: =_xlfn.XLOOKUP(A8,'TB.1 - F25'!A:A,'TB.1 - F25'!H:H,0,0,1) -> 0 | D8: =_xlfn.XLOOKUP(A8,'AJE.1 - F25'!A:A,'AJE.1 - F25'!F:F,0,0,1) -> 0 | F8: =ROUND(SUM(B8:E8),0) -> 0 | G8: =_xlfn.XLOOKUP($A8,TB.PRO!$A:$A,TB.PRO!F:F,0,0,1) -> 0 | H8: =_xlfn.XLOOKUP($A8,TB.PRO!$A:$A,TB.PRO!G:G,0,0,1) -> 0 | K8: =_xlfn.XLOOKUP($A8,'AJE.1 - F25'!$S$12:$S$21,'AJE.1 - F25'!$U$12:$U$21,0,0,1) -> 0 | L8: =ROUND(SUM(G8:K8),0) -> 0 | M8: =_xlfn.XLOOKUP($A8,TB.PRO!$A:$A,TB.PRO!I:I,0,0,1) -> 0 | N8: =_xlfn.XLOOKUP($A8,TB.PRO!$A:$A,TB.PRO!J:J,0,0,1) -> 0 | Q8: =_xlfn.XLOOKUP($A8,'AJE.1 - F25'!$S$12:$S$21,'AJE.1 - F25'!$U$12:$U$21,0,0,1) -> 0 | R8: =ROUND(SUM(M8:Q8),0) -> 0 | S8: =M8+O8 -> 0 | T8: =N8+P8 -> 0 | W8: =_xlfn.XLOOKUP($A8,'AJE.1 - F25'!$S$12:$S$21,'AJE.1 - F25'!$U$12:$U$21,0,0,1) -> 0 | X8: =ROUND(SUM(S8:W8),0) -> 0 | Y8: =S8+U8 -> 0 | Z8: =T8+V8 -> 0 | AC8: =_xlfn.XLOOKUP($A8,'AJE.1 - F25'!$S$12:$S$21,'AJE.1 - F25'!$U$12:$U$21,0,0,1) -> 0 | AD8: =ROUND(SUM(Y8:AC8),0) -> 0 | AE8: =Y8+AA8 -> 0 | AF8: =Z8+AB8 -> 0 | AI8: =_xlfn.XLOOKUP($A8,'AJE.1 - F25'!$S$12:$S$21,'AJE.1 - F25'!$U$12:$U$21,0,0,1) -> 0 | AJ8: =ROUND(SUM(AE8:AI8),0) -> 0 | AK8: =_xlfn.XLOOKUP($A8,COA!$B:$B,COA!$C:$C,0,0,1) -> Cash | AL8: =_xlfn.XLOOKUP($A8,COA!$B:$B,COA!$D:$D,0,0,1) -> Cash | AM8: =_xlfn.XLOOKUP($A8,COA!$B:$B,COA!$E:$E,0,0,1) -> Cash | AO8: =AM8 -> Cash
A9: =COA!B5 -> 1000 Chequing - 5002829 | B9: =_xlfn.XLOOKUP(A9,'TB.1 - F25'!A:A,'TB.1 - F25'!D:D,0,0,1) -> -101.64 | C9: =_xlfn.XLOOKUP(A9,'TB.1 - F25'!A:A,'TB.1 - F25'!H:H,0,0,1) -> 0 | D9: =_xlfn.XLOOKUP(A9,'AJE.1 - F25'!A:A,'AJE.1 - F25'!F:F,0,0,1) -> 0 | F9: =ROUND(SUM(B9:E9),0) -> -102 | G9: =_xlfn.XLOOKUP($A9,TB.PRO!$A:$A,TB.PRO!F:F,0,0,1) -> -165.34 | H9: =_xlfn.XLOOKUP($A9,TB.PRO!$A:$A,TB.PRO!G:G,0,0,1) -> 0 | I9: =-SUM(I100:I136) -> -111197.52 | J9: =-J110-J74-J133-SUM(J54,J55,J56,J57,J60,J62,J64) -> 2491092.9 | K9: =B192-SUM(K38,K39,K40,K45) -> -935886.12 | L9: =ROUND(SUM(G9:K9),0) -> 1443844 | M9: =_xlfn.XLOOKUP($A9,TB.PRO!$A:$A,TB.PRO!I:I,0,0,1) -> -165.34 | N9: =_xlfn.XLOOKUP($A9,TB.PRO!$A:$A,TB.PRO!J:J,0,0,1) -> 0 | O9: =I9-SUM(O100:O175,O177:O184) -> 150183.63 | P9: =J9-P133 -> 2131092.9 | Q9: =K9-Q41 -> -966337.32 | R9: =ROUND(SUM(M9:Q9),0) -> 1314774 | S9: =M9+O9+Q9 -> -816319.03 | T9: =N9+P9 -> 2131092.9 | U9: =-SUM(U101:U162,U178:U180)-U38-U39-U40-U45 -> 3113291.7 | V9: =-SUM(V74,V84,V133) -> -3360000 | W9: =-W41 -> -157951.2 | X9: =ROUND(SUM(S9:W9),0) -> 910114 | Y9: =S9+U9 -> 2296972.6 | Z9: =T9+V9 -> -1228907.1 | AA9: =-SUM(AA101:AA162,AA178:AA180)-AA38 -> 8747938.1 | AC9: =-AC41 -> -457951.2 | AD9: =ROUND(SUM(Y9:AC9),0) -> 9358052 | AE9: =Y9+AA9 -> 11044911 | AF9: =Z9+AB9 -> -1228907.1 | AG9: =-SUM(AG101:AG162,AG178:AG180)-AG38 -> 16100762 | AI9: =-AI41 -> -982951.2 | AJ9: =ROUND(SUM(AE9:AI9),0) -> 24933815 | AK9: =_xlfn.XLOOKUP($A9,COA!$B:$B,COA!$C:$C,0,0,1) -> Cash | AL9: =_xlfn.XLOOKUP($A9,COA!$B:$B,COA!$D:$D,0,0,1) -> Cash | AM9: =_xlfn.XLOOKUP($A9,COA!$B:$B,COA!$E:$E,0,0,1) -> Cash | AO9: =_xlfn.XLOOKUP(AM9,FS.1!A:A,AM:AM,0,0,1) -> Cash
A10: =COA!B6 -> 1000 Undeposited Funds | B10: =_xlfn.XLOOKUP(A10,'TB.1 - F25'!A:A,'TB.1 - F25'!D:D,0,0,1) -> 0 | C10: =_xlfn.XLOOKUP(A10,'TB.1 - F25'!A:A,'TB.1 - F25'!H:H,0,0,1) -> 0 | D10: =_xlfn.XLOOKUP(A10,'AJE.1 - F25'!A:A,'AJE.1 - F25'!F:F,0,0,1) -> 0 | F10: =ROUND(SUM(B10:E10),0) -> 0 | G10: =_xlfn.XLOOKUP($A10,TB.PRO!$A:$A,TB.PRO!F:F,0,0,1) -> 0 | H10: =_xlfn.XLOOKUP($A10,TB.PRO!$A:$A,TB.PRO!G:G,0,0,1) -> 0 | K10: =_xlfn.XLOOKUP($A10,'AJE.1 - F25'!$S$12:$S$21,'AJE.1 - F25'!$U$12:$U$21,0,0,1) -> 0 | L10: =ROUND(SUM(G10:K10),0) -> 0 | M10: =_xlfn.XLOOKUP($A10,TB.PRO!$A:$A,TB.PRO!I:I,0,0,1) -> 0 | N10: =_xlfn.XLOOKUP($A10,TB.PRO!$A:$A,TB.PRO!J:J,0,0,1) -> 0 | Q10: =_xlfn.XLOOKUP($A10,'AJE.1 - F25'!$S$12:$S$21,'AJE.1 - F25'!$U$12:$U$21,0,0,1) -> 0 | R10: =ROUND(SUM(M10:Q10),0) -> 0 | S10: =M10+O10 -> 0 | T10: =N10+P10 -> 0 | W10: =_xlfn.XLOOKUP($A10,'AJE.1 - F25'!$S$12:$S$21,'AJE.1 - F25'!$U$12:$U$21,0,0,1) -> 0 | X10: =ROUND(SUM(S10:W10),0) -> 0 | Y10: =S10+U10 -> 0 | Z10: =T10+V10 -> 0 | AC10: =_xlfn.XLOOKUP($A10,'AJE.1 - F25'!$S$12:$S$21,'AJE.1 - F25'!$U$12:$U$21,0,0,1) -> 0 | AD10: =ROUND(SUM(Y10:AC10),0) -> 0 | AE10: =Y10+AA10 -> 0 | AF10: =Z10+AB10 -> 0 | AI10: =_xlfn.XLOOKUP($A10,'AJE.1 - F25'!$S$12:$S$21,'AJE.1 - F25'!$U$12:$U$21,0,0,1) -> 0 | AJ10: =ROUND(SUM(AE10:AI10),0) -> 0 | AK10: =_xlfn.XLOOKUP($A10,COA!$B:$B,COA!$C:$C,0,0,1) -> Cash | AL10: =_xlfn.XLOOKUP($A10,COA!$B:$B,COA!$D:$D,0,0,1) -> Cash | AM10: =_xlfn.XLOOKUP($A10,COA!$B:$B,COA!$E:$E,0,0,1) -> Cash | AO10: =AM10 -> Cash
A11: =COA!B7 -> 1001 Petty Cash | B11: =_xlfn.XLOOKUP(A11,'TB.1 - F25'!A:A,'TB.1 - F25'!D:D,0,0,1) -> 0 | C11: =_xlfn.XLOOKUP(A11,'TB.1 - F25'!A:A,'TB.1 - F25'!H:H,0,0,1) -> 198 | D11: =_xlfn.XLOOKUP(A11,'AJE.1 - F25'!A:A,'AJE.1 - F25'!F:F,0,0,1) -> 0 | F11: =ROUND(SUM(B11:E11),0) -> 198 | G11: =_xlfn.XLOOKUP($A11,TB.PRO!$A:$A,TB.PRO!F:F,0,0,1) -> 0 | H11: =_xlfn.XLOOKUP($A11,TB.PRO!$A:$A,TB.PRO!G:G,0,0,1) -> 198 | K11: =_xlfn.XLOOKUP($A11,'AJE.1 - F25'!$S$12:$S$21,'AJE.1 - F25'!$U$12:$U$21,0,0,1) -> 0 | L11: =ROUND(SUM(G11:K11),0) -> 198 | M11: =_xlfn.XLOOKUP($A11,TB.PRO!$A:$A,TB.PRO!I:I,0,0,1) -> 0 | N11: =_xlfn.XLOOKUP($A11,TB.PRO!$A:$A,TB.PRO!J:J,0,0,1) -> 198 | Q11: =_xlfn.XLOOKUP($A11,'AJE.1 - F25'!$S$12:$S$21,'AJE.1 - F25'!$U$12:$U$21,0,0,1) -> 0 | R11: =ROUND(SUM(M11:Q11),0) -> 198 | S11: =M11+O11 -> 0 | T11: =N11+P11 -> 198 | W11: =_xlfn.XLOOKUP($A11,'AJE.1 - F25'!$S$12:$S$21,'AJE.1 - F25'!$U$12:$U$21,0,0,1) -> 0 | X11: =ROUND(SUM(S11:W11),0) -> 198 | Y11: =S11+U11 -> 0 | Z11: =T11+V11 -> 198 | AC11: =_xlfn.XLOOKUP($A11,'AJE.1 - F25'!$S$12:$S$21,'AJE.1 - F25'!$U$12:$U$21,0,0,1) -> 0 | AD11: =ROUND(SUM(Y11:AC11),0) -> 198 | AE11: =Y11+AA11 -> 0 | AF11: =Z11+AB11 -> 198 | AI11: =_xlfn.XLOOKUP($A11,'AJE.1 - F25'!$S$12:$S$21,'AJE.1 - F25'!$U$12:$U$21,0,0,1) -> 0 | AJ11: =ROUND(SUM(AE11:AI11),0) -> 198 | AK11: =_xlfn.XLOOKUP($A11,COA!$B:$B,COA!$C:$C,0,0,1) -> Cash | AL11: =_xlfn.XLOOKUP($A11,COA!$B:$B,COA!$D:$D,0,0,1) -> Cash | AM11: =_xlfn.XLOOKUP($A11,COA!$B:$B,COA!$E:$E,0,0,1) -> Cash | AO11: =AM11 -> Cash
A12: =COA!B8 -> 1002 TD - Chequing 1869 | B12: =_xlfn.XLOOKUP(A12,'TB.1 - F25'!A:A,'TB.1 - F25'!D:D,0,0,1) -> 0 | C12: =_xlfn.XLOOKUP(A12,'TB.1 - F25'!A:A,'TB.1 - F25'!H:H,0,0,1) -> 52.7 | D12: =_xlfn.XLOOKUP(A12,'AJE.1 - F25'!A:A,'AJE.1 - F25'!F:F,0,0,1) -> 0 | F12: =ROUND(SUM(B12:E12),0) -> 53 | G12: =_xlfn.XLOOKUP($A12,TB.PRO!$A:$A,TB.PRO!F:F,0,0,1) -> 0 | H12: =_xlfn.XLOOKUP($A12,TB.PRO!$A:$A,TB.PRO!G:G,0,0,1) -> 436367.55 | K12: =_xlfn.XLOOKUP($A12,'AJE.1 - F25'!$S$12:$S$21,'AJE.1 - F25'!$U$12:$U$21,0,0,1) -> 0 | L12: =ROUND(SUM(G12:K12),0) -> 436368 | M12: =_xlfn.XLOOKUP($A12,TB.PRO!$A:$A,TB.PRO!I:I,0,0,1) -> 0 | N12: =_xlfn.XLOOKUP($A12,TB.PRO!$A:$A,TB.PRO!J:J,0,0,1) -> 436367.55 | Q12: =_xlfn.XLOOKUP($A12,'AJE.1 - F25'!$S$12:$S$21,'AJE.1 - F25'!$U$12:$U$21,0,0,1) -> 0 | R12: =ROUND(SUM(M12:Q12),0) -> 436368 | S12: =M12+O12 -> 0 | T12: =N12+P12 -> 436367.55 | W12: =_xlfn.XLOOKUP($A12,'AJE.1 - F25'!$S$12:$S$21,'AJE.1 - F25'!$U$12:$U$21,0,0,1) -> 0 | X12: =ROUND(SUM(S12:W12),0) -> 436368 | Y12: =S12+U12 -> 0 | Z12: =T12+V12 -> 436367.55 | AC12: =_xlfn.XLOOKUP($A12,'AJE.1 - F25'!$S$12:$S$21,'AJE.1 - F25'!$U$12:$U$21,0,0,1) -> 0 | AD12: =ROUND(SUM(Y12:AC12),0) -> 436368 | AE12: =Y12+AA12 -> 0 | AF12: =Z12+AB12 -> 436367.55 | AI12: =_xlfn.XLOOKUP($A12,'AJE.1 - F25'!$S$12:$S$21,'AJE.1 - F25'!$U$12:$U$21,0,0,1) -> 0 | AJ12: =ROUND(SUM(AE12:AI12),0) -> 436368 | AK12: =_xlfn.XLOOKUP($A12,COA!$B:$B,COA!$C:$C,0,0,1) -> Cash | AL12: =_xlfn.XLOOKUP($A12,COA!$B:$B,COA!$D:$D,0,0,1) -> Cash | AM12: =_xlfn.XLOOKUP($A12,COA!$B:$B,COA!$E:$E,0,0,1) -> Cash | AO12: =_xlfn.XLOOKUP(AM12,FS.1!A:A,AM:AM,0,0,1) -> Cash
A13: =COA!B9 -> 1003 TD - Savings 2407 | B13: =_xlfn.XLOOKUP(A13,'TB.1 - F25'!A:A,'TB.1 - F25'!D:D,0,0,1) -> 0 | C13: =_xlfn.XLOOKUP(A13,'TB.1 - F25'!A:A,'TB.1 - F25'!H:H,0,0,1) -> 0.03 | D13: =_xlfn.XLOOKUP(A13,'AJE.1 - F25'!A:A,'AJE.1 - F25'!F:F,0,0,1) -> 0 | F13: =ROUND(SUM(B13:E13),0) -> 0 | G13: =_xlfn.XLOOKUP($A13,TB.PRO!$A:$A,TB.PRO!F:F,0,0,1) -> 0 | H13: =_xlfn.XLOOKUP($A13,TB.PRO!$A:$A,TB.PRO!G:G,0,0,1) -> 61000.03 | K13: =_xlfn.XLOOKUP($A13,'AJE.1 - F25'!$S$12:$S$21,'AJE.1 - F25'!$U$12:$U$21,0,0,1) -> 0 | L13: =ROUND(SUM(G13:K13),0) -> 61000 | M13: =_xlfn.XLOOKUP($A13,TB.PRO!$A:$A,TB.PRO!I:I,0,0,1) -> 0 | N13: =_xlfn.XLOOKUP($A13,TB.PRO!$A:$A,TB.PRO!J:J,0,0,1) -> 61000.03 | Q13: =_xlfn.XLOOKUP($A13,'AJE.1 - F25'!$S$12:$S$21,'AJE.1 - F25'!$U$12:$U$21,0,0,1) -> 0 | R13: =ROUND(SUM(M13:Q13),0) -> 61000 | S13: =M13+O13 -> 0 | T13: =N13+P13 -> 61000.03 | W13: =_xlfn.XLOOKUP($A13,'AJE.1 - F25'!$S$12:$S$21,'AJE.1 - F25'!$U$12:$U$21,0,0,1) -> 0 | X13: =ROUND(SUM(S13:W13),0) -> 61000 | Y13: =S13+U13 -> 0 | Z13: =T13+V13 -> 61000.03 | AC13: =_xlfn.XLOOKUP($A13,'AJE.1 - F25'!$S$12:$S$21,'AJE.1 - F25'!$U$12:$U$21,0,0,1) -> 0 | AD13: =ROUND(SUM(Y13:AC13),0) -> 61000 | AE13: =Y13+AA13 -> 0 | AF13: =Z13+AB13 -> 61000.03 | AI13: =_xlfn.XLOOKUP($A13,'AJE.1 - F25'!$S$12:$S$21,'AJE.1 - F25'!$U$12:$U$21,0,0,1) -> 0 | AJ13: =ROUND(SUM(AE13:AI13),0) -> 61000 | AK13: =_xlfn.XLOOKUP($A13,COA!$B:$B,COA!$C:$C,0,0,1) -> Cash | AL13: =_xlfn.XLOOKUP($A13,COA!$B:$B,COA!$D:$D,0,0,1) -> Cash | AM13: =_xlfn.XLOOKUP($A13,COA!$B:$B,COA!$E:$E,0,0,1) -> Cash | AO13: =AM13 -> Cash
A14: =COA!B10 -> 1004 TD - Visa 7692 | B14: =_xlfn.XLOOKUP(A14,'TB.1 - F25'!A:A,'TB.1 - F25'!D:D,0,0,1) -> 0 | C14: =_xlfn.XLOOKUP(A14,'TB.1 - F25'!A:A,'TB.1 - F25'!H:H,0,0,1) -> -7199.51 | D14: =_xlfn.XLOOKUP(A14,'AJE.1 - F25'!A:A,'AJE.1 - F25'!F:F,0,0,1) -> 0 | F14: =ROUND(SUM(B14:E14),0) -> -7200 | G14: =_xlfn.XLOOKUP($A14,TB.PRO!$A:$A,TB.PRO!F:F,0,0,1) -> 0 | H14: =_xlfn.XLOOKUP($A14,TB.PRO!$A:$A,TB.PRO!G:G,0,0,1) -> 777.83 | K14: =_xlfn.XLOOKUP($A14,'AJE.1 - F25'!$S$12:$S$21,'AJE.1 - F25'!$U$12:$U$21,0,0,1) -> 0 | L14: =ROUND(SUM(G14:K14),0) -> 778 | M14: =_xlfn.XLOOKUP($A14,TB.PRO!$A:$A,TB.PRO!I:I,0,0,1) -> 0 | N14: =_xlfn.XLOOKUP($A14,TB.PRO!$A:$A,TB.PRO!J:J,0,0,1) -> 777.83 | Q14: =_xlfn.XLOOKUP($A14,'AJE.1 - F25'!$S$12:$S$21,'AJE.1 - F25'!$U$12:$U$21,0,0,1) -> 0 | R14: =ROUND(SUM(M14:Q14),0) -> 778 | S14: =M14+O14 -> 0 | T14: =N14+P14 -> 777.83 | W14: =_xlfn.XLOOKUP($A14,'AJE.1 - F25'!$S$12:$S$21,'AJE.1 - F25'!$U$12:$U$21,0,0,1) -> 0 | X14: =ROUND(SUM(S14:W14),0) -> 778 | Y14: =S14+U14 -> 0 | Z14: =T14+V14 -> 777.83 | AC14: =_xlfn.XLOOKUP($A14,'AJE.1 - F25'!$S$12:$S$21,'AJE.1 - F25'!$U$12:$U$21,0,0,1) -> 0 | AD14: =ROUND(SUM(Y14:AC14),0) -> 778 | AE14: =Y14+AA14 -> 0 | AF14: =Z14+AB14 -> 777.83 | AI14: =_xlfn.XLOOKUP($A14,'AJE.1 - F25'!$S$12:$S$21,'AJE.1 - F25'!$U$12:$U$21,0,0,1) -> 0 | AJ14: =ROUND(SUM(AE14:AI14),0) -> 778 | AK14: =_xlfn.XLOOKUP($A14,COA!$B:$B,COA!$C:$C,0,0,1) -> Cash | AL14: =_xlfn.XLOOKUP($A14,COA!$B:$B,COA!$D:$D,0,0,1) -> Cash | AM14: =_xlfn.XLOOKUP($A14,COA!$B:$B,COA!$E:$E,0,0,1) -> Cash | AO14: =_xlfn.XLOOKUP(AM14,FS.1!A:A,AM:AM,0,0,1) -> Cash
A15: =COA!B11 -> 1005 Undeposited Funds | B15: =_xlfn.XLOOKUP(A15,'TB.1 - F25'!A:A,'TB.1 - F25'!D:D,0,0,1) -> 0 | C15: =_xlfn.XLOOKUP(A15,'TB.1 - F25'!A:A,'TB.1 - F25'!H:H,0,0,1) -> 0 | D15: =_xlfn.XLOOKUP(A15,'AJE.1 - F25'!A:A,'AJE.1 - F25'!F:F,0,0,1) -> 0 | F15: =ROUND(SUM(B15:E15),0) -> 0 | G15: =_xlfn.XLOOKUP($A15,TB.PRO!$A:$A,TB.PRO!F:F,0,0,1) -> 0 | H15: =_xlfn.XLOOKUP($A15,TB.PRO!$A:$A,TB.PRO!G:G,0,0,1) -> 0 | K15: =_xlfn.XLOOKUP($A15,'AJE.1 - F25'!$S$12:$S$21,'AJE.1 - F25'!$U$12:$U$21,0,0,1) -> 0 | L15: =ROUND(SUM(G15:K15),0) -> 0 | M15: =_xlfn.XLOOKUP($A15,TB.PRO!$A:$A,TB.PRO!I:I,0,0,1) -> 0 | N15: =_xlfn.XLOOKUP($A15,TB.PRO!$A:$A,TB.PRO!J:J,0,0,1) -> 0 | Q15: =_xlfn.XLOOKUP($A15,'AJE.1 - F25'!$S$12:$S$21,'AJE.1 - F25'!$U$12:$U$21,0,0,1) -> 0 | R15: =ROUND(SUM(M15:Q15),0) -> 0 | S15: =M15+O15 -> 0 | T15: =N15+P15 -> 0 | W15: =_xlfn.XLOOKUP($A15,'AJE.1 - F25'!$S$12:$S$21,'AJE.1 - F25'!$U$12:$U$21,0,0,1) -> 0 | X15: =ROUND(SUM(S15:W15),0) -> 0 | Y15: =S15+U15 -> 0 | Z15: =T15+V15 -> 0 | AC15: =_xlfn.XLOOKUP($A15,'AJE.1 - F25'!$S$12:$S$21,'AJE.1 - F25'!$U$12:$U$21,0,0,1) -> 0 | AD15: =ROUND(SUM(Y15:AC15),0) -> 0 | AE15: =Y15+AA15 -> 0 | AF15: =Z15+AB15 -> 0 | AI15: =_xlfn.XLOOKUP($A15,'AJE.1 - F25'!$S$12:$S$21,'AJE.1 - F25'!$U$12:$U$21,0,0,1) -> 0 | AJ15: =ROUND(SUM(AE15:AI15),0) -> 0 | AK15: =_xlfn.XLOOKUP($A15,COA!$B:$B,COA!$C:$C,0,0,1) -> Cash | AL15: =_xlfn.XLOOKUP($A15,COA!$B:$B,COA!$D:$D,0,0,1) -> Cash | AM15: =_xlfn.XLOOKUP($A15,COA!$B:$B,COA!$E:$E,0,0,1) -> Cash | AO15: =AM15 -> Cash
A16: =COA!B12 -> 1005 Interior Savings - 5224 | B16: =_xlfn.XLOOKUP(A16,'TB.1 - F25'!A:A,'TB.1 - F25'!D:D,0,0,1) -> 0 | C16: =_xlfn.XLOOKUP(A16,'TB.1 - F25'!A:A,'TB.1 - F25'!H:H,0,0,1) -> 242.6 | D16: =_xlfn.XLOOKUP(A16,'AJE.1 - F25'!A:A,'AJE.1 - F25'!F:F,0,0,1) -> 0 | F16: =ROUND(SUM(B16:E16),0) -> 243 | G16: =_xlfn.XLOOKUP($A16,TB.PRO!$A:$A,TB.PRO!F:F,0,0,1) -> 0 | H16: =_xlfn.XLOOKUP($A16,TB.PRO!$A:$A,TB.PRO!G:G,0,0,1) -> 242.6 | K16: =_xlfn.XLOOKUP($A16,'AJE.1 - F25'!$S$12:$S$21,'AJE.1 - F25'!$U$12:$U$21,0,0,1) -> 0 | L16: =ROUND(SUM(G16:K16),0) -> 243 | M16: =_xlfn.XLOOKUP($A16,TB.PRO!$A:$A,TB.PRO!I:I,0,0,1) -> 0 | N16: =_xlfn.XLOOKUP($A16,TB.PRO!$A:$A,TB.PRO!J:J,0,0,1) -> 242.6 | Q16: =_xlfn.XLOOKUP($A16,'AJE.1 - F25'!$S$12:$S$21,'AJE.1 - F25'!$U$12:$U$21,0,0,1) -> 0 | R16: =ROUND(SUM(M16:Q16),0) -> 243 | S16: =M16+O16 -> 0 | T16: =N16+P16 -> 242.6 | W16: =_xlfn.XLOOKUP($A16,'AJE.1 - F25'!$S$12:$S$21,'AJE.1 - F25'!$U$12:$U$21,0,0,1) -> 0 | X16: =ROUND(SUM(S16:W16),0) -> 243 | Y16: =S16+U16 -> 0 | Z16: =T16+V16 -> 242.6 | AC16: =_xlfn.XLOOKUP($A16,'AJE.1 - F25'!$S$12:$S$21,'AJE.1 - F25'!$U$12:$U$21,0,0,1) -> 0 | AD16: =ROUND(SUM(Y16:AC16),0) -> 243 | AE16: =Y16+AA16 -> 0 | AF16: =Z16+AB16 -> 242.6 | AI16: =_xlfn.XLOOKUP($A16,'AJE.1 - F25'!$S$12:$S$21,'AJE.1 - F25'!$U$12:$U$21,0,0,1) -> 0 | AJ16: =ROUND(SUM(AE16:AI16),0) -> 243 | AK16: =_xlfn.XLOOKUP($A16,COA!$B:$B,COA!$C:$C,0,0,1) -> Cash | AL16: =_xlfn.XLOOKUP($A16,COA!$B:$B,COA!$D:$D,0,0,1) -> Cash | AM16: =_xlfn.XLOOKUP($A16,COA!$B:$B,COA!$E:$E,0,0,1) -> Cash | AO16: =AM16 -> Cash
A17: =COA!B13 -> 1006 Interior Savings - Member Shares 5182 | B17: =_xlfn.XLOOKUP(A17,'TB.1 - F25'!A:A,'TB.1 - F25'!D:D,0,0,1) -> 0 | C17: =_xlfn.XLOOKUP(A17,'TB.1 - F25'!A:A,'TB.1 - F25'!H:H,0,0,1) -> 6.04 | D17: =_xlfn.XLOOKUP(A17,'AJE.1 - F25'!A:A,'AJE.1 - F25'!F:F,0,0,1) -> 0 | F17: =ROUND(SUM(B17:E17),0) -> 6 | G17: =_xlfn.XLOOKUP($A17,TB.PRO!$A:$A,TB.PRO!F:F,0,0,1) -> 0 | H17: =_xlfn.XLOOKUP($A17,TB.PRO!$A:$A,TB.PRO!G:G,0,0,1) -> 6.04 | K17: =_xlfn.XLOOKUP($A17,'AJE.1 - F25'!$S$12:$S$21,'AJE.1 - F25'!$U$12:$U$21,0,0,1) -> 0 | L17: =ROUND(SUM(G17:K17),0) -> 6 | M17: =_xlfn.XLOOKUP($A17,TB.PRO!$A:$A,TB.PRO!I:I,0,0,1) -> 0 | N17: =_xlfn.XLOOKUP($A17,TB.PRO!$A:$A,TB.PRO!J:J,0,0,1) -> 6.04 | Q17: =_xlfn.XLOOKUP($A17,'AJE.1 - F25'!$S$12:$S$21,'AJE.1 - F25'!$U$12:$U$21,0,0,1) -> 0 | R17: =ROUND(SUM(M17:Q17),0) -> 6 | S17: =M17+O17 -> 0 | T17: =N17+P17 -> 6.04 | W17: =_xlfn.XLOOKUP($A17,'AJE.1 - F25'!$S$12:$S$21,'AJE.1 - F25'!$U$12:$U$21,0,0,1) -> 0 | X17: =ROUND(SUM(S17:W17),0) -> 6 | Y17: =S17+U17 -> 0 | Z17: =T17+V17 -> 6.04 | AC17: =_xlfn.XLOOKUP($A17,'AJE.1 - F25'!$S$12:$S$21,'AJE.1 - F25'!$U$12:$U$21,0,0,1) -> 0 | AD17: =ROUND(SUM(Y17:AC17),0) -> 6 | AE17: =Y17+AA17 -> 0 | AF17: =Z17+AB17 -> 6.04 | AI17: =_xlfn.XLOOKUP($A17,'AJE.1 - F25'!$S$12:$S$21,'AJE.1 - F25'!$U$12:$U$21,0,0,1) -> 0 | AJ17: =ROUND(SUM(AE17:AI17),0) -> 6 | AK17: =_xlfn.XLOOKUP($A17,COA!$B:$B,COA!$C:$C,0,0,1) -> Cash | AL17: =_xlfn.XLOOKUP($A17,COA!$B:$B,COA!$D:$D,0,0,1) -> Cash | AM17: =_xlfn.XLOOKUP($A17,COA!$B:$B,COA!$E:$E,0,0,1) -> Cash | AO17: =AM17 -> Cash
A18: =COA!B14 -> 1010 Bank - suspense | B18: =_xlfn.XLOOKUP(A18,'TB.1 - F25'!A:A,'TB.1 - F25'!D:D,0,0,1) -> 0 | C18: =_xlfn.XLOOKUP(A18,'TB.1 - F25'!A:A,'TB.1 - F25'!H:H,0,0,1) -> -5.5 | D18: =_xlfn.XLOOKUP(A18,'AJE.1 - F25'!A:A,'AJE.1 - F25'!F:F,0,0,1) -> 0 | F18: =ROUND(SUM(B18:E18),0) -> -6 | G18: =_xlfn.XLOOKUP($A18,TB.PRO!$A:$A,TB.PRO!F:F,0,0,1) -> 0 | H18: =_xlfn.XLOOKUP($A18,TB.PRO!$A:$A,TB.PRO!G:G,0,0,1) -> -5.5 | K18: =_xlfn.XLOOKUP($A18,'AJE.1 - F25'!$S$12:$S$21,'AJE.1 - F25'!$U$12:$U$21,0,0,1) -> 0 | L18: =ROUND(SUM(G18:K18),0) -> -6 | M18: =_xlfn.XLOOKUP($A18,TB.PRO!$A:$A,TB.PRO!I:I,0,0,1) -> 0 | N18: =_xlfn.XLOOKUP($A18,TB.PRO!$A:$A,TB.PRO!J:J,0,0,1) -> -5.5 | Q18: =-Q98 -> 1 | R18: =ROUND(SUM(M18:Q18),0) -> -5 | S18: =M18+O18 -> 0 | T18: =N18+P18 -> -5.5 | W18: =-W98 -> 2 | X18: =ROUND(SUM(S18:W18),0) -> -4 | Y18: =S18+U18 -> 0 | Z18: =T18+V18 -> -5.5 | AC18: =-AC98 -> 2 | AD18: =ROUND(SUM(Y18:AC18),0) -> -4 | AE18: =Y18+AA18 -> 0 | AF18: =Z18+AB18 -> -5.5 | AI18: =-AI98 -> 3 | AJ18: =ROUND(SUM(AE18:AI18),0) -> -3 | AK18: =_xlfn.XLOOKUP($A18,COA!$B:$B,COA!$C:$C,0,0,1) -> Cash | AL18: =_xlfn.XLOOKUP($A18,COA!$B:$B,COA!$D:$D,0,0,1) -> Cash | AM18: =_xlfn.XLOOKUP($A18,COA!$B:$B,COA!$E:$E,0,0,1) -> Cash | AO18: =_xlfn.XLOOKUP(AM18,FS.1!A:A,AM:AM,0,0,1) -> Cash
A19: =COA!B15 -> 1100 Accounts Receivable (A/R) | B19: =_xlfn.XLOOKUP(A19,'TB.1 - F25'!A:A,'TB.1 - F25'!D:D,0,0,1) -> 0 | C19: =_xlfn.XLOOKUP(A19,'TB.1 - F25'!A:A,'TB.1 - F25'!H:H,0,0,1) -> 0 | D19: =_xlfn.XLOOKUP(A19,'AJE.1 - F25'!A:A,'AJE.1 - F25'!F:F,0,0,1) -> 0 | F19: =ROUND(SUM(B19:E19),0) -> 0 | G19: =_xlfn.XLOOKUP($A19,TB.PRO!$A:$A,TB.PRO!F:F,0,0,1) -> 0 | H19: =_xlfn.XLOOKUP($A19,TB.PRO!$A:$A,TB.PRO!G:G,0,0,1) -> 0 | K19: =_xlfn.XLOOKUP($A19,'AJE.1 - F25'!$S$12:$S$21,'AJE.1 - F25'!$U$12:$U$21,0,0,1) -> 0 | L19: =ROUND(SUM(G19:K19),0) -> 0 | M19: =_xlfn.XLOOKUP($A19,TB.PRO!$A:$A,TB.PRO!I:I,0,0,1) -> 0 | N19: =_xlfn.XLOOKUP($A19,TB.PRO!$A:$A,TB.PRO!J:J,0,0,1) -> 0 | Q19: =_xlfn.XLOOKUP($A19,'AJE.1 - F25'!$S$12:$S$21,'AJE.1 - F25'!$U$12:$U$21,0,0,1) -> 0 | R19: =ROUND(SUM(M19:Q19),0) -> 0 | S19: =M19+O19 -> 0 | T19: =N19+P19 -> 0 | W19: =_xlfn.XLOOKUP($A19,'AJE.1 - F25'!$S$12:$S$21,'AJE.1 - F25'!$U$12:$U$21,0,0,1) -> 0 | X19: =ROUND(SUM(S19:W19),0) -> 0 | Y19: =S19+U19 -> 0 | Z19: =T19+V19 -> 0 | AC19: =_xlfn.XLOOKUP($A19,'AJE.1 - F25'!$S$12:$S$21,'AJE.1 - F25'!$U$12:$U$21,0,0,1) -> 0 | AD19: =ROUND(SUM(Y19:AC19),0) -> 0 | AE19: =Y19+AA19 -> 0 | AF19: =Z19+AB19 -> 0 | AI19: =_xlfn.XLOOKUP($A19,'AJE.1 - F25'!$S$12:$S$21,'AJE.1 - F25'!$U$12:$U$21,0,0,1) -> 0 | AJ19: =ROUND(SUM(AE19:AI19),0) -> 0 | AK19: =_xlfn.XLOOKUP($A19,COA!$B:$B,COA!$C:$C,0,0,1) -> Receivables | AL19: =_xlfn.XLOOKUP($A19,COA!$B:$B,COA!$D:$D,0,0,1) -> Receivables | AM19: =_xlfn.XLOOKUP($A19,COA!$B:$B,COA!$E:$E,0,0,1) -> Receivables | AO19: =_xlfn.XLOOKUP(AM19,FS.1!A:A,AM:AM,0,0,1) -> Cash
A20: =COA!B16 -> 1100 Accounts Receivable | B20: =_xlfn.XLOOKUP(A20,'TB.1 - F25'!A:A,'TB.1 - F25'!D:D,0,0,1) -> 0 | C20: =_xlfn.XLOOKUP(A20,'TB.1 - F25'!A:A,'TB.1 - F25'!H:H,0,0,1) -> 0 | D20: =_xlfn.XLOOKUP(A20,'AJE.1 - F25'!A:A,'AJE.1 - F25'!F:F,0,0,1) -> 0 | F20: =ROUND(SUM(B20:E20),0) -> 0 | G20: =_xlfn.XLOOKUP($A20,TB.PRO!$A:$A,TB.PRO!F:F,0,0,1) -> 0 | H20: =_xlfn.XLOOKUP($A20,TB.PRO!$A:$A,TB.PRO!G:G,0,0,1) -> 17.5 | K20: =_xlfn.XLOOKUP($A20,'AJE.1 - F25'!$S$12:$S$21,'AJE.1 - F25'!$U$12:$U$21,0,0,1) -> 0 | L20: =ROUND(SUM(G20:K20),0) -> 18 | M20: =_xlfn.XLOOKUP($A20,TB.PRO!$A:$A,TB.PRO!I:I,0,0,1) -> 0 | N20: =_xlfn.XLOOKUP($A20,TB.PRO!$A:$A,TB.PRO!J:J,0,0,1) -> 17.5 | Q20: =_xlfn.XLOOKUP($A20,'AJE.1 - F25'!$S$12:$S$21,'AJE.1 - F25'!$U$12:$U$21,0,0,1) -> 0 | R20: =ROUND(SUM(M20:Q20),0) -> 18 | S20: =M20+O20 -> 0 | T20: =N20+P20 -> 17.5 | W20: =_xlfn.XLOOKUP($A20,'AJE.1 - F25'!$S$12:$S$21,'AJE.1 - F25'!$U$12:$U$21,0,0,1) -> 0 | X20: =ROUND(SUM(S20:W20),0) -> 18 | Y20: =S20+U20 -> 0 | Z20: =T20+V20 -> 17.5 | AC20: =_xlfn.XLOOKUP($A20,'AJE.1 - F25'!$S$12:$S$21,'AJE.1 - F25'!$U$12:$U$21,0,0,1) -> 0 | AD20: =ROUND(SUM(Y20:AC20),0) -> 18 | AE20: =Y20+AA20 -> 0 | AF20: =Z20+AB20 -> 17.5 | AI20: =_xlfn.XLOOKUP($A20,'AJE.1 - F25'!$S$12:$S$21,'AJE.1 - F25'!$U$12:$U$21,0,0,1) -> 0 | AJ20: =ROUND(SUM(AE20:AI20),0) -> 18 | AK20: =_xlfn.XLOOKUP($A20,COA!$B:$B,COA!$C:$C,0,0,1) -> Receivables | AL20: =_xlfn.XLOOKUP($A20,COA!$B:$B,COA!$D:$D,0,0,1) -> Receivables | AM20: =_xlfn.XLOOKUP($A20,COA!$B:$B,COA!$E:$E,0,0,1) -> Receivables | AO20: =AM20 -> Receivables
A21: =COA!B17 -> 1120 Work in progress inventory | B21: =_xlfn.XLOOKUP(A21,'TB.1 - F25'!A:A,'TB.1 - F25'!D:D,0,0,1) -> 0 | C21: =_xlfn.XLOOKUP(A21,'TB.1 - F25'!A:A,'TB.1 - F25'!H:H,0,0,1) -> 161256.15 | D21: =_xlfn.XLOOKUP(A21,'AJE.1 - F25'!A:A,'AJE.1 - F25'!F:F,0,0,1) -> 0 | F21: =ROUND(SUM(B21:E21),0) -> 161256 | G21: =_xlfn.XLOOKUP($A21,TB.PRO!$A:$A,TB.PRO!F:F,0,0,1) -> 0 | H21: =_xlfn.XLOOKUP($A21,TB.PRO!$A:$A,TB.PRO!G:G,0,0,1) -> 159516.72 | L21: =ROUND(SUM(G21:K21),0) -> 159517 | M21: =_xlfn.XLOOKUP($A21,TB.PRO!$A:$A,TB.PRO!I:I,0,0,1) -> 0 | N21: =_xlfn.XLOOKUP($A21,TB.PRO!$A:$A,TB.PRO!J:J,0,0,1) -> 159516.72 | P21: =J21-P110 -> 443333.33 | R21: =ROUND(SUM(M21:Q21),0) -> 602850 | S21: =M21+O21 -> 0 | T21: =N21+P21 -> 602850.05 | V21: =-V110 -> 1540000 | W21: =-W110 -> 0 | X21: =ROUND(SUM(S21:W21),0) -> 2142850 | Y21: =S21+U21 -> 0 | Z21: =T21+V21 -> 2142850.1 | AB21: =-AB110 -> 3126666.7 | AC21: =-AC110 -> 0 | AD21: =ROUND(SUM(Y21:AC21),0) -> 5269517 | AE21: =Y21+AA21 -> 0 | AF21: =Z21+AB21 -> 5269516.7 | AH21: =-AH110 -> 8166666.7 | AI21: =-AI110 -> -3126666.7 | AJ21: =ROUND(SUM(AE21:AI21),0) -> 10309517 | AK21: =_xlfn.XLOOKUP($A21,COA!$B:$B,COA!$C:$C,0,0,1) -> Inventory | AL21: =_xlfn.XLOOKUP($A21,COA!$B:$B,COA!$D:$D,0,0,1) -> Inventory | AM21: =_xlfn.XLOOKUP($A21,COA!$B:$B,COA!$E:$E,0,0,1) -> Inventory | AO21: =_xlfn.XLOOKUP(AM21,FS.1!A:A,AM:AM,0,0,1) -> Cash
A22: =COA!B18 -> 1020 Prepaid expenses | B22: =_xlfn.XLOOKUP(A22,'TB.1 - F25'!A:A,'TB.1 - F25'!D:D,0,0,1) -> 0 | C22: =_xlfn.XLOOKUP(A22,'TB.1 - F25'!A:A,'TB.1 - F25'!H:H,0,0,1) -> 0 | D22: =_xlfn.XLOOKUP(A22,'AJE.1 - F25'!A:A,'AJE.1 - F25'!F:F,0,0,1) -> 0 | F22: =ROUND(SUM(B22:E22),0) -> 0 | G22: =_xlfn.XLOOKUP($A22,TB.PRO!$A:$A,TB.PRO!F:F,0,0,1) -> 0 | H22: =_xlfn.XLOOKUP($A22,TB.PRO!$A:$A,TB.PRO!G:G,0,0,1) -> 0 | K22: =_xlfn.XLOOKUP($A22,'AJE.1 - F25'!$S$12:$S$21,'AJE.1 - F25'!$U$12:$U$21,0,0,1) -> 0 | L22: =ROUND(SUM(G22:K22),0) -> 0 | M22: =_xlfn.XLOOKUP($A22,TB.PRO!$A:$A,TB.PRO!I:I,0,0,1) -> 0 | N22: =_xlfn.XLOOKUP($A22,TB.PRO!$A:$A,TB.PRO!J:J,0,0,1) -> 0 | Q22: =_xlfn.XLOOKUP($A22,'AJE.1 - F25'!$S$12:$S$21,'AJE.1 - F25'!$U$12:$U$21,0,0,1) -> 0 | R22: =ROUND(SUM(M22:Q22),0) -> 0 | S22: =M22+O22 -> 0 | T22: =N22+P22 -> 0 | W22: =_xlfn.XLOOKUP($A22,'AJE.1 - F25'!$S$12:$S$21,'AJE.1 - F25'!$U$12:$U$21,0,0,1) -> 0 | X22: =ROUND(SUM(S22:W22),0) -> 0 | Y22: =S22+U22 -> 0 | Z22: =T22+V22 -> 0 | AC22: =_xlfn.XLOOKUP($A22,'AJE.1 - F25'!$S$12:$S$21,'AJE.1 - F25'!$U$12:$U$21,0,0,1) -> 0 | AD22: =ROUND(SUM(Y22:AC22),0) -> 0 | AE22: =Y22+AA22 -> 0 | AF22: =Z22+AB22 -> 0 | AI22: =_xlfn.XLOOKUP($A22,'AJE.1 - F25'!$S$12:$S$21,'AJE.1 - F25'!$U$12:$U$21,0,0,1) -> 0 | AJ22: =ROUND(SUM(AE22:AI22),0) -> 0 | AK22: =_xlfn.XLOOKUP($A22,COA!$B:$B,COA!$C:$C,0,0,1) -> Prepaid expenses | AL22: =_xlfn.XLOOKUP($A22,COA!$B:$B,COA!$D:$D,0,0,1) -> Prepaid expenses | AM22: =_xlfn.XLOOKUP($A22,COA!$B:$B,COA!$E:$E,0,0,1) -> Prepaid expenses | AO22: =_xlfn.XLOOKUP(AM22,FS.1!A:A,AM:AM,0,0,1) -> Cash
A23: =COA!B19 -> 1200 Prepaid expenses | B23: =_xlfn.XLOOKUP(A23,'TB.1 - F25'!A:A,'TB.1 - F25'!D:D,0,0,1) -> 0 | C23: =_xlfn.XLOOKUP(A23,'TB.1 - F25'!A:A,'TB.1 - F25'!H:H,0,0,1) -> 0 | D23: =_xlfn.XLOOKUP(A23,'AJE.1 - F25'!A:A,'AJE.1 - F25'!F:F,0,0,1) -> 0 | F23: =ROUND(SUM(B23:E23),0) -> 0 | G23: =_xlfn.XLOOKUP($A23,TB.PRO!$A:$A,TB.PRO!F:F,0,0,1) -> 0 | H23: =_xlfn.XLOOKUP($A23,TB.PRO!$A:$A,TB.PRO!G:G,0,0,1) -> 0 | K23: =_xlfn.XLOOKUP($A23,'AJE.1 - F25'!$S$12:$S$21,'AJE.1 - F25'!$U$12:$U$21,0,0,1) -> 0 | L23: =ROUND(SUM(G23:K23),0) -> 0 | M23: =_xlfn.XLOOKUP($A23,TB.PRO!$A:$A,TB.PRO!I:I,0,0,1) -> 0 | N23: =_xlfn.XLOOKUP($A23,TB.PRO!$A:$A,TB.PRO!J:J,0,0,1) -> 0 | Q23: =_xlfn.XLOOKUP($A23,'AJE.1 - F25'!$S$12:$S$21,'AJE.1 - F25'!$U$12:$U$21,0,0,1) -> 0 | R23: =ROUND(SUM(M23:Q23),0) -> 0 | S23: =M23+O23 -> 0 | T23: =N23+P23 -> 0 | W23: =_xlfn.XLOOKUP($A23,'AJE.1 - F25'!$S$12:$S$21,'AJE.1 - F25'!$U$12:$U$21,0,0,1) -> 0 | X23: =ROUND(SUM(S23:W23),0) -> 0 | Y23: =S23+U23 -> 0 | Z23: =T23+V23 -> 0 | AC23: =_xlfn.XLOOKUP($A23,'AJE.1 - F25'!$S$12:$S$21,'AJE.1 - F25'!$U$12:$U$21,0,0,1) -> 0 | AD23: =ROUND(SUM(Y23:AC23),0) -> 0 | AE23: =Y23+AA23 -> 0 | AF23: =Z23+AB23 -> 0 | AI23: =_xlfn.XLOOKUP($A23,'AJE.1 - F25'!$S$12:$S$21,'AJE.1 - F25'!$U$12:$U$21,0,0,1) -> 0 | AJ23: =ROUND(SUM(AE23:AI23),0) -> 0 | AK23: Intercompany | AL23: =AK23 -> Intercompany | AM23: =AL23 -> Intercompany | AO23: =AM23 -> Intercompany
A24: =COA!B20 -> 1300 Current portion of loan receivable | B24: =_xlfn.XLOOKUP(A24,'TB.1 - F25'!A:A,'TB.1 - F25'!D:D,0,0,1) -> 556400 | C24: =_xlfn.XLOOKUP(A24,'TB.1 - F25'!A:A,'TB.1 - F25'!H:H,0,0,1) -> 0 | D24: =_xlfn.XLOOKUP(A24,'AJE.1 - F25'!A:A,'AJE.1 - F25'!F:F,0,0,1) -> 0 | F24: =ROUND(SUM(B24:E24),0) -> 556400 | G24: =_xlfn.XLOOKUP($A24,TB.PRO!$A:$A,TB.PRO!F:F,0,0,1) -> 556400 | H24: =_xlfn.XLOOKUP($A24,TB.PRO!$A:$A,TB.PRO!G:G,0,0,1) -> 0 | K24: =_xlfn.XLOOKUP($A24,'AJE.1 - F25'!$S$12:$S$21,'AJE.1 - F25'!$U$12:$U$21,0,0,1) -> 0 | L24: =ROUND(SUM(G24:K24),0) -> 556400 | M24: =_xlfn.XLOOKUP($A24,TB.PRO!$A:$A,TB.PRO!I:I,0,0,1) -> 556400 | N24: =_xlfn.XLOOKUP($A24,TB.PRO!$A:$A,TB.PRO!J:J,0,0,1) -> 0 | Q24: =_xlfn.XLOOKUP($A24,'AJE.1 - F25'!$S$12:$S$21,'AJE.1 - F25'!$U$12:$U$21,0,0,1) -> 0 | R24: =ROUND(SUM(M24:Q24),0) -> 556400 | S24: =M24+O24 -> 556400 | T24: =N24+P24 -> 0 | W24: =_xlfn.XLOOKUP($A24,'AJE.1 - F25'!$S$12:$S$21,'AJE.1 - F25'!$U$12:$U$21,0,0,1) -> 0 | X24: =ROUND(SUM(S24:W24),0) -> 556400 | Y24: =S24+U24 -> 556400 | Z24: =T24+V24 -> 0 | AC24: =_xlfn.XLOOKUP($A24,'AJE.1 - F25'!$S$12:$S$21,'AJE.1 - F25'!$U$12:$U$21,0,0,1) -> 0 | AD24: =ROUND(SUM(Y24:AC24),0) -> 556400 | AE24: =Y24+AA24 -> 556400 | AF24: =Z24+AB24 -> 0 | AI24: =_xlfn.XLOOKUP($A24,'AJE.1 - F25'!$S$12:$S$21,'AJE.1 - F25'!$U$12:$U$21,0,0,1) -> 0 | AJ24: =ROUND(SUM(AE24:AI24),0) -> 556400 | AK24: Intercompany | AL24: =AK24 -> Intercompany | AM24: =AL24 -> Intercompany | AO24: =_xlfn.XLOOKUP(AM24,FS.1!A:A,AM:AM,0,0,1) -> 0
A25: =COA!B21 -> 1400 Other current assets | B25: =_xlfn.XLOOKUP(A25,'TB.1 - F25'!A:A,'TB.1 - F25'!D:D,0,0,1) -> 0 | C25: =_xlfn.XLOOKUP(A25,'TB.1 - F25'!A:A,'TB.1 - F25'!H:H,0,0,1) -> 0 | D25: =_xlfn.XLOOKUP(A25,'AJE.1 - F25'!A:A,'AJE.1 - F25'!F:F,0,0,1) -> 0 | F25: =ROUND(SUM(B25:E25),0) -> 0 | G25: =_xlfn.XLOOKUP($A25,TB.PRO!$A:$A,TB.PRO!F:F,0,0,1) -> 0 | H25: =_xlfn.XLOOKUP($A25,TB.PRO!$A:$A,TB.PRO!G:G,0,0,1) -> 0 | K25: =_xlfn.XLOOKUP($A25,'AJE.1 - F25'!$S$12:$S$21,'AJE.1 - F25'!$U$12:$U$21,0,0,1) -> 0 | L25: =ROUND(SUM(G25:K25),0) -> 0 | M25: =_xlfn.XLOOKUP($A25,TB.PRO!$A:$A,TB.PRO!I:I,0,0,1) -> 0 | N25: =_xlfn.XLOOKUP($A25,TB.PRO!$A:$A,TB.PRO!J:J,0,0,1) -> 0 | Q25: =_xlfn.XLOOKUP($A25,'AJE.1 - F25'!$S$12:$S$21,'AJE.1 - F25'!$U$12:$U$21,0,0,1) -> 0 | R25: =ROUND(SUM(M25:Q25),0) -> 0 | S25: =M25+O25 -> 0 | T25: =N25+P25 -> 0 | W25: =_xlfn.XLOOKUP($A25,'AJE.1 - F25'!$S$12:$S$21,'AJE.1 - F25'!$U$12:$U$21,0,0,1) -> 0 | X25: =ROUND(SUM(S25:W25),0) -> 0 | Y25: =S25+U25 -> 0 | Z25: =T25+V25 -> 0 | AC25: =_xlfn.XLOOKUP($A25,'AJE.1 - F25'!$S$12:$S$21,'AJE.1 - F25'!$U$12:$U$21,0,0,1) -> 0 | AD25: =ROUND(SUM(Y25:AC25),0) -> 0 | AE25: =Y25+AA25 -> 0 | AF25: =Z25+AB25 -> 0 | AI25: =_xlfn.XLOOKUP($A25,'AJE.1 - F25'!$S$12:$S$21,'AJE.1 - F25'!$U$12:$U$21,0,0,1) -> 0 | AJ25: =ROUND(SUM(AE25:AI25),0) -> 0 | AK25: =_xlfn.XLOOKUP($A25,COA!$B:$B,COA!$C:$C,0,0,1) -> Other current assets | AL25: =_xlfn.XLOOKUP($A25,COA!$B:$B,COA!$D:$D,0,0,1) -> Other current assets | AM25: =_xlfn.XLOOKUP($A25,COA!$B:$B,COA!$E:$E,0,0,1) -> Other current assets | AO25: =AM25 -> Other current assets
A26: =COA!B22 -> 1420 Intangible assets | B26: =_xlfn.XLOOKUP(A26,'TB.1 - F25'!A:A,'TB.1 - F25'!D:D,0,0,1) -> 450000 | C26: =_xlfn.XLOOKUP(A26,'TB.1 - F25'!A:A,'TB.1 - F25'!H:H,0,0,1) -> 0 | D26: =_xlfn.XLOOKUP(A26,'AJE.1 - F25'!A:A,'AJE.1 - F25'!F:F,0,0,1) -> 6281822 | F26: =ROUND(SUM(B26:E26),0) -> 6731822 | G26: =_xlfn.XLOOKUP($A26,TB.PRO!$A:$A,TB.PRO!F:F,0,0,1) -> 450000 | H26: =_xlfn.XLOOKUP($A26,TB.PRO!$A:$A,TB.PRO!G:G,0,0,1) -> 6281822 | K26: =_xlfn.XLOOKUP($A26,'AJE.1 - F25'!$S$12:$S$21,'AJE.1 - F25'!$U$12:$U$21,0,0,1) -> 0 | L26: =ROUND(SUM(G26:K26),0) -> 6731822 | M26: =_xlfn.XLOOKUP($A26,TB.PRO!$A:$A,TB.PRO!I:I,0,0,1) -> 450000 | N26: =_xlfn.XLOOKUP($A26,TB.PRO!$A:$A,TB.PRO!J:J,0,0,1) -> 6281822 | Q26: =_xlfn.XLOOKUP($A26,'AJE.1 - F25'!$S$12:$S$21,'AJE.1 - F25'!$U$12:$U$21,0,0,1) -> 0 | R26: =ROUND(SUM(M26:Q26),0) -> 6731822 | S26: =M26+O26 -> 450000 | T26: =N26+P26 -> 6281822 | W26: =_xlfn.XLOOKUP($A26,'AJE.1 - F25'!$S$12:$S$21,'AJE.1 - F25'!$U$12:$U$21,0,0,1) -> 0 | X26: =ROUND(SUM(S26:W26),0) -> 6731822 | Y26: =S26+U26 -> 450000 | Z26: =T26+V26 -> 6281822 | AC26: =_xlfn.XLOOKUP($A26,'AJE.1 - F25'!$S$12:$S$21,'AJE.1 - F25'!$U$12:$U$21,0,0,1) -> 0 | AD26: =ROUND(SUM(Y26:AC26),0) -> 6731822 | AE26: =Y26+AA26 -> 450000 | AF26: =Z26+AB26 -> 6281822 | AI26: =_xlfn.XLOOKUP($A26,'AJE.1 - F25'!$S$12:$S$21,'AJE.1 - F25'!$U$12:$U$21,0,0,1) -> 0 | AJ26: =ROUND(SUM(AE26:AI26),0) -> 6731822 | AK26: =_xlfn.XLOOKUP($A26,COA!$B:$B,COA!$C:$C,0,0,1) -> Intangible assets | AL26: =_xlfn.XLOOKUP($A26,COA!$B:$B,COA!$D:$D,0,0,1) -> Intangible assets | AM26: =_xlfn.XLOOKUP($A26,COA!$B:$B,COA!$E:$E,0,0,1) -> Intangible assets | AO26: =AM26 -> Intangible assets
A27: =COA!B23 -> 1421 Accumulated amortization | B27: =_xlfn.XLOOKUP(A27,'TB.1 - F25'!A:A,'TB.1 - F25'!D:D,0,0,1) -> 0 | C27: =_xlfn.XLOOKUP(A27,'TB.1 - F25'!A:A,'TB.1 - F25'!H:H,0,0,1) -> 0 | D27: =_xlfn.XLOOKUP(A27,'AJE.1 - F25'!A:A,'AJE.1 - F25'!F:F,0,0,1) -> -2460380 | F27: =ROUND(SUM(B27:E27),0) -> -2460380 | G27: =_xlfn.XLOOKUP($A27,TB.PRO!$A:$A,TB.PRO!F:F,0,0,1) -> 0 | H27: =_xlfn.XLOOKUP($A27,TB.PRO!$A:$A,TB.PRO!G:G,0,0,1) -> -2774471 | I27: =-I185 -> -942273 | K27: =_xlfn.XLOOKUP($A27,'AJE.1 - F25'!$S$12:$S$21,'AJE.1 - F25'!$U$12:$U$21,0,0,1) -> 0 | L27: =ROUND(SUM(G27:K27),0) -> -3716744 | M27: =_xlfn.XLOOKUP($A27,TB.PRO!$A:$A,TB.PRO!I:I,0,0,1) -> 0 | N27: =_xlfn.XLOOKUP($A27,TB.PRO!$A:$A,TB.PRO!J:J,0,0,1) -> -2774471 | O27: =I27-O185 -> -2198637 | Q27: =_xlfn.XLOOKUP($A27,'AJE.1 - F25'!$S$12:$S$21,'AJE.1 - F25'!$U$12:$U$21,0,0,1) -> 0 | R27: =ROUND(SUM(M27:Q27),0) -> -4973108 | S27: =M27+O27 -> -2198637 | T27: =N27+P27 -> -2774471 | U27: =-U185 -> -1256364 | W27: =_xlfn.XLOOKUP($A27,'AJE.1 - F25'!$S$12:$S$21,'AJE.1 - F25'!$U$12:$U$21,0,0,1) -> 0 | X27: =ROUND(SUM(S27:W27),0) -> -6229472 | Y27: =S27+U27 -> -3455001 | Z27: =T27+V27 -> -2774471 | AA27: =-AA185 -> -188259 | AC27: =_xlfn.XLOOKUP($A27,'AJE.1 - F25'!$S$12:$S$21,'AJE.1 - F25'!$U$12:$U$21,0,0,1) -> 0 | AD27: =ROUND(SUM(Y27:AC27),0) -> -6417731 | AE27: =Y27+AA27 -> -3643260 | AF27: =Z27+AB27 -> -2774471 | AG27: =-AG185 -> 0 | AH27: =AB27 -> 0 | AI27: =_xlfn.XLOOKUP($A27,'AJE.1 - F25'!$S$12:$S$21,'AJE.1 - F25'!$U$12:$U$21,0,0,1) -> 0 | AJ27: =ROUND(SUM(AE27:AI27),0) -> -6417731 | AK27: =_xlfn.XLOOKUP($A27,COA!$B:$B,COA!$C:$C,0,0,1) -> Intangible assets | AL27: =_xlfn.XLOOKUP($A27,COA!$B:$B,COA!$D:$D,0,0,1) -> Intangible assets | AM27: =_xlfn.XLOOKUP($A27,COA!$B:$B,COA!$E:$E,0,0,1) -> Intangible assets | AO27: =_xlfn.XLOOKUP(AM27,FS.1!A:A,AM:AM,0,0,1) -> Intercompany
A28: =COA!B24 -> 1500 Payroll Advances Receivable | B28: =_xlfn.XLOOKUP(A28,'TB.1 - F25'!A:A,'TB.1 - F25'!D:D,0,0,1) -> 0 | C28: =_xlfn.XLOOKUP(A28,'TB.1 - F25'!A:A,'TB.1 - F25'!H:H,0,0,1) -> 0 | D28: =_xlfn.XLOOKUP(A28,'AJE.1 - F25'!A:A,'AJE.1 - F25'!F:F,0,0,1) -> 0 | F28: =ROUND(SUM(B28:E28),0) -> 0 | G28: =_xlfn.XLOOKUP($A28,TB.PRO!$A:$A,TB.PRO!F:F,0,0,1) -> 0 | H28: =_xlfn.XLOOKUP($A28,TB.PRO!$A:$A,TB.PRO!G:G,0,0,1) -> 0 | K28: =_xlfn.XLOOKUP($A28,'AJE.1 - F25'!$S$12:$S$21,'AJE.1 - F25'!$U$12:$U$21,0,0,1) -> 0 | L28: =ROUND(SUM(G28:K28),0) -> 0 | M28: =_xlfn.XLOOKUP($A28,TB.PRO!$A:$A,TB.PRO!I:I,0,0,1) -> 0 | N28: =_xlfn.XLOOKUP($A28,TB.PRO!$A:$A,TB.PRO!J:J,0,0,1) -> 0 | Q28: =_xlfn.XLOOKUP($A28,'AJE.1 - F25'!$S$12:$S$21,'AJE.1 - F25'!$U$12:$U$21,0,0,1) -> 0 | R28: =ROUND(SUM(M28:Q28),0) -> 0 | S28: =M28+O28 -> 0 | T28: =N28+P28 -> 0 | W28: =_xlfn.XLOOKUP($A28,'AJE.1 - F25'!$S$12:$S$21,'AJE.1 - F25'!$U$12:$U$21,0,0,1) -> 0 | X28: =ROUND(SUM(S28:W28),0) -> 0 | Y28: =S28+U28 -> 0 | Z28: =T28+V28 -> 0 | AC28: =_xlfn.XLOOKUP($A28,'AJE.1 - F25'!$S$12:$S$21,'AJE.1 - F25'!$U$12:$U$21,0,0,1) -> 0 | AD28: =ROUND(SUM(Y28:AC28),0) -> 0 | AE28: =Y28+AA28 -> 0 | AF28: =Z28+AB28 -> 0 | AI28: =_xlfn.XLOOKUP($A28,'AJE.1 - F25'!$S$12:$S$21,'AJE.1 - F25'!$U$12:$U$21,0,0,1) -> 0 | AJ28: =ROUND(SUM(AE28:AI28),0) -> 0 | AK28: =_xlfn.XLOOKUP($A28,COA!$B:$B,COA!$C:$C,0,0,1) -> Receivables | AL28: =_xlfn.XLOOKUP($A28,COA!$B:$B,COA!$D:$D,0,0,1) -> Receivables | AM28: =_xlfn.XLOOKUP($A28,COA!$B:$B,COA!$E:$E,0,0,1) -> Receivables | AO28: =AM28 -> Receivables
A29: =COA!B25 -> 1500 Intercompany - Due from Hallor Industries Inc. | B29: =_xlfn.XLOOKUP(A29,'TB.1 - F25'!A:A,'TB.1 - F25'!D:D,0,0,1) -> 109064.08 | C29: =_xlfn.XLOOKUP(A29,'TB.1 - F25'!A:A,'TB.1 - F25'!H:H,0,0,1) -> 0 | D29: =_xlfn.XLOOKUP(A29,'AJE.1 - F25'!A:A,'AJE.1 - F25'!F:F,0,0,1) -> 0 | E29: 26 | F29: =ROUND(SUM(B29:E29),0) -> 109090 | G29: =_xlfn.XLOOKUP($A29,TB.PRO!$A:$A,TB.PRO!F:F,0,0,1) -> 88831.23 | H29: =_xlfn.XLOOKUP($A29,TB.PRO!$A:$A,TB.PRO!G:G,0,0,1) -> 0 | J29: 73 | K29: =_xlfn.XLOOKUP($A29,'AJE.1 - F25'!$S$12:$S$21,'AJE.1 - F25'!$U$12:$U$21,0,0,1) -> 0 | L29: =ROUND(SUM(G29:K29),0) -> 88904 | M29: =_xlfn.XLOOKUP($A29,TB.PRO!$A:$A,TB.PRO!I:I,0,0,1) -> 88831.23 | N29: =_xlfn.XLOOKUP($A29,TB.PRO!$A:$A,TB.PRO!J:J,0,0,1) -> 0 | P29: 73 | Q29: =_xlfn.XLOOKUP($A29,'AJE.1 - F25'!$S$12:$S$21,'AJE.1 - F25'!$U$12:$U$21,0,0,1) -> 0 | R29: =ROUND(SUM(M29:Q29),0) -> 88904 | S29: =M29+O29 -> 88831.23 | T29: =N29+P29 -> 73 | W29: =_xlfn.XLOOKUP($A29,'AJE.1 - F25'!$S$12:$S$21,'AJE.1 - F25'!$U$12:$U$21,0,0,1) -> 0 | X29: =ROUND(SUM(S29:W29),0) -> 88904 | Y29: =S29+U29 -> 88831.23 | Z29: =T29+V29 -> 73 | AC29: =_xlfn.XLOOKUP($A29,'AJE.1 - F25'!$S$12:$S$21,'AJE.1 - F25'!$U$12:$U$21,0,0,1) -> 0 | AD29: =ROUND(SUM(Y29:AC29),0) -> 88904 | AE29: =Y29+AA29 -> 88831.23 | AF29: =Z29+AB29 -> 73 | AI29: =_xlfn.XLOOKUP($A29,'AJE.1 - F25'!$S$12:$S$21,'AJE.1 - F25'!$U$12:$U$21,0,0,1) -> 0 | AJ29: =ROUND(SUM(AE29:AI29),0) -> 88904 | AK29: =_xlfn.XLOOKUP($A29,COA!$B:$B,COA!$C:$C,0,0,1) -> Intercompany | AL29: =_xlfn.XLOOKUP($A29,COA!$B:$B,COA!$D:$D,0,0,1) -> Intercompany | AM29: =_xlfn.XLOOKUP($A29,COA!$B:$B,COA!$E:$E,0,0,1) -> Intercompany | AO29: =_xlfn.XLOOKUP(AM29,FS.1!A:A,AM:AM,0,0,1) -> 0
A30: =COA!B26 -> 1600 Investment in Hallor Industries | B30: =_xlfn.XLOOKUP(A30,'TB.1 - F25'!A:A,'TB.1 - F25'!D:D,0,0,1) -> 6000000 | C30: =_xlfn.XLOOKUP(A30,'TB.1 - F25'!A:A,'TB.1 - F25'!H:H,0,0,1) -> 0 | D30: =_xlfn.XLOOKUP(A30,'AJE.1 - F25'!A:A,'AJE.1 - F25'!F:F,0,0,1) -> -6000000 | F30: =ROUND(SUM(B30:E30),0) -> 0 | G30: =_xlfn.XLOOKUP($A30,TB.PRO!$A:$A,TB.PRO!F:F,0,0,1) -> 6000000 | H30: =_xlfn.XLOOKUP($A30,TB.PRO!$A:$A,TB.PRO!G:G,0,0,1) -> 0 | K30: =_xlfn.XLOOKUP($A30,'AJE.1 - F25'!$S$12:$S$21,'AJE.1 - F25'!$U$12:$U$21,0,0,1) -> -6000000 | L30: =ROUND(SUM(G30:K30),0) -> 0 | M30: =_xlfn.XLOOKUP($A30,TB.PRO!$A:$A,TB.PRO!I:I,0,0,1) -> 6000000 | N30: =_xlfn.XLOOKUP($A30,TB.PRO!$A:$A,TB.PRO!J:J,0,0,1) -> 0 | Q30: =_xlfn.XLOOKUP($A30,'AJE.1 - F25'!$S$12:$S$21,'AJE.1 - F25'!$U$12:$U$21,0,0,1) -> -6000000 | R30: =ROUND(SUM(M30:Q30),0) -> 0 | S30: =M30+O30 -> 6000000 | T30: =N30+P30 -> 0 | W30: =_xlfn.XLOOKUP($A30,'AJE.1 - F25'!$S$12:$S$21,'AJE.1 - F25'!$U$12:$U$21,0,0,1) -> -6000000 | X30: =ROUND(SUM(S30:W30),0) -> 0 | Y30: =S30+U30 -> 6000000 | Z30: =T30+V30 -> 0 | AC30: =_xlfn.XLOOKUP($A30,'AJE.1 - F25'!$S$12:$S$21,'AJE.1 - F25'!$U$12:$U$21,0,0,1) -> -6000000 | AD30: =ROUND(SUM(Y30:AC30),0) -> 0 | AE30: =Y30+AA30 -> 6000000 | AF30: =Z30+AB30 -> 0 | AI30: =_xlfn.XLOOKUP($A30,'AJE.1 - F25'!$S$12:$S$21,'AJE.1 - F25'!$U$12:$U$21,0,0,1) -> -6000000 | AJ30: =ROUND(SUM(AE30:AI30),0) -> 0 | AK30: =_xlfn.XLOOKUP($A30,COA!$B:$B,COA!$C:$C,0,0,1) -> Investment in subsidiary | AL30: =_xlfn.XLOOKUP($A30,COA!$B:$B,COA!$D:$D,0,0,1) -> Investment in subsidiary | AM30: =_xlfn.XLOOKUP($A30,COA!$B:$B,COA!$E:$E,0,0,1) -> Investment in subsidiary | AO30: =_xlfn.XLOOKUP(AM30,FS.1!A:A,AM:AM,0,0,1) -> 0
A31: =COA!B27 -> 1800 Computer Equipment | B31: =_xlfn.XLOOKUP(A31,'TB.1 - F25'!A:A,'TB.1 - F25'!D:D,0,0,1) -> 0 | C31: =_xlfn.XLOOKUP(A31,'TB.1 - F25'!A:A,'TB.1 - F25'!H:H,0,0,1) -> 0 | D31: =_xlfn.XLOOKUP(A31,'AJE.1 - F25'!A:A,'AJE.1 - F25'!F:F,0,0,1) -> 0 | F31: =ROUND(SUM(B31:E31),0) -> 0 | G31: =_xlfn.XLOOKUP($A31,TB.PRO!$A:$A,TB.PRO!F:F,0,0,1) -> 0 | H31: =_xlfn.XLOOKUP($A31,TB.PRO!$A:$A,TB.PRO!G:G,0,0,1) -> 0 | K31: =_xlfn.XLOOKUP($A31,'AJE.1 - F25'!$S$12:$S$21,'AJE.1 - F25'!$U$12:$U$21,0,0,1) -> 0 | L31: =ROUND(SUM(G31:K31),0) -> 0 | M31: =_xlfn.XLOOKUP($A31,TB.PRO!$A:$A,TB.PRO!I:I,0,0,1) -> 0 | N31: =_xlfn.XLOOKUP($A31,TB.PRO!$A:$A,TB.PRO!J:J,0,0,1) -> 0 | Q31: =_xlfn.XLOOKUP($A31,'AJE.1 - F25'!$S$12:$S$21,'AJE.1 - F25'!$U$12:$U$21,0,0,1) -> 0 | R31: =ROUND(SUM(M31:Q31),0) -> 0 | S31: =M31+O31 -> 0 | T31: =N31+P31 -> 0 | W31: =_xlfn.XLOOKUP($A31,'AJE.1 - F25'!$S$12:$S$21,'AJE.1 - F25'!$U$12:$U$21,0,0,1) -> 0 | X31: =ROUND(SUM(S31:W31),0) -> 0 | Y31: =S31+U31 -> 0 | Z31: =T31+V31 -> 0 | AC31: =_xlfn.XLOOKUP($A31,'AJE.1 - F25'!$S$12:$S$21,'AJE.1 - F25'!$U$12:$U$21,0,0,1) -> 0 | AD31: =ROUND(SUM(Y31:AC31),0) -> 0 | AE31: =Y31+AA31 -> 0 | AF31: =Z31+AB31 -> 0 | AI31: =_xlfn.XLOOKUP($A31,'AJE.1 - F25'!$S$12:$S$21,'AJE.1 - F25'!$U$12:$U$21,0,0,1) -> 0 | AJ31: =ROUND(SUM(AE31:AI31),0) -> 0 | AK31: =_xlfn.XLOOKUP($A31,COA!$B:$B,COA!$C:$C,0,0,1) -> Equipment | AL31: =_xlfn.XLOOKUP($A31,COA!$B:$B,COA!$D:$D,0,0,1) -> Equipment | AM31: =_xlfn.XLOOKUP($A31,COA!$B:$B,COA!$E:$E,0,0,1) -> Equipment | AO31: =_xlfn.XLOOKUP(AM31,FS.1!A:A,AM:AM,0,0,1) -> Intercompany
A32: =COA!B28 -> 1801 Computer Equipment:Accumulated Depreciation | B32: =_xlfn.XLOOKUP(A32,'TB.1 - F25'!A:A,'TB.1 - F25'!D:D,0,0,1) -> 0 | C32: =_xlfn.XLOOKUP(A32,'TB.1 - F25'!A:A,'TB.1 - F25'!H:H,0,0,1) -> 0 | D32: =_xlfn.XLOOKUP(A32,'AJE.1 - F25'!A:A,'AJE.1 - F25'!F:F,0,0,1) -> 0 | F32: =ROUND(SUM(B32:E32),0) -> 0 | G32: =_xlfn.XLOOKUP($A32,TB.PRO!$A:$A,TB.PRO!F:F,0,0,1) -> 0 | H32: =_xlfn.XLOOKUP($A32,TB.PRO!$A:$A,TB.PRO!G:G,0,0,1) -> 0 | K32: =_xlfn.XLOOKUP($A32,'AJE.1 - F25'!$S$12:$S$21,'AJE.1 - F25'!$U$12:$U$21,0,0,1) -> 0 | L32: =ROUND(SUM(G32:K32),0) -> 0 | M32: =_xlfn.XLOOKUP($A32,TB.PRO!$A:$A,TB.PRO!I:I,0,0,1) -> 0 | N32: =_xlfn.XLOOKUP($A32,TB.PRO!$A:$A,TB.PRO!J:J,0,0,1) -> 0 | Q32: =_xlfn.XLOOKUP($A32,'AJE.1 - F25'!$S$12:$S$21,'AJE.1 - F25'!$U$12:$U$21,0,0,1) -> 0 | R32: =ROUND(SUM(M32:Q32),0) -> 0 | S32: =M32+O32 -> 0 | T32: =N32+P32 -> 0 | W32: =_xlfn.XLOOKUP($A32,'AJE.1 - F25'!$S$12:$S$21,'AJE.1 - F25'!$U$12:$U$21,0,0,1) -> 0 | X32: =ROUND(SUM(S32:W32),0) -> 0 | Y32: =S32+U32 -> 0 | Z32: =T32+V32 -> 0 | AC32: =_xlfn.XLOOKUP($A32,'AJE.1 - F25'!$S$12:$S$21,'AJE.1 - F25'!$U$12:$U$21,0,0,1) -> 0 | AD32: =ROUND(SUM(Y32:AC32),0) -> 0 | AE32: =Y32+AA32 -> 0 | AF32: =Z32+AB32 -> 0 | AI32: =_xlfn.XLOOKUP($A32,'AJE.1 - F25'!$S$12:$S$21,'AJE.1 - F25'!$U$12:$U$21,0,0,1) -> 0 | AJ32: =ROUND(SUM(AE32:AI32),0) -> 0 | AK32: =_xlfn.XLOOKUP($A32,COA!$B:$B,COA!$C:$C,0,0,1) -> Equipment | AL32: =_xlfn.XLOOKUP($A32,COA!$B:$B,COA!$D:$D,0,0,1) -> Equipment | AM32: =_xlfn.XLOOKUP($A32,COA!$B:$B,COA!$E:$E,0,0,1) -> Equipment | AO32: =_xlfn.XLOOKUP(AM32,FS.1!A:A,AM:AM,0,0,1) -> Intercompany
A33: =COA!B29 -> 1810 Office Furniture | B33: =_xlfn.XLOOKUP(A33,'TB.1 - F25'!A:A,'TB.1 - F25'!D:D,0,0,1) -> 0 | C33: =_xlfn.XLOOKUP(A33,'TB.1 - F25'!A:A,'TB.1 - F25'!H:H,0,0,1) -> 0 | D33: =_xlfn.XLOOKUP(A33,'AJE.1 - F25'!A:A,'AJE.1 - F25'!F:F,0,0,1) -> 0 | F33: =ROUND(SUM(B33:E33),0) -> 0 | G33: =_xlfn.XLOOKUP($A33,TB.PRO!$A:$A,TB.PRO!F:F,0,0,1) -> 0 | H33: =_xlfn.XLOOKUP($A33,TB.PRO!$A:$A,TB.PRO!G:G,0,0,1) -> 0 | K33: =_xlfn.XLOOKUP($A33,'AJE.1 - F25'!$S$12:$S$21,'AJE.1 - F25'!$U$12:$U$21,0,0,1) -> 0 | L33: =ROUND(SUM(G33:K33),0) -> 0 | M33: =_xlfn.XLOOKUP($A33,TB.PRO!$A:$A,TB.PRO!I:I,0,0,1) -> 0 | N33: =_xlfn.XLOOKUP($A33,TB.PRO!$A:$A,TB.PRO!J:J,0,0,1) -> 0 | Q33: =_xlfn.XLOOKUP($A33,'AJE.1 - F25'!$S$12:$S$21,'AJE.1 - F25'!$U$12:$U$21,0,0,1) -> 0 | R33: =ROUND(SUM(M33:Q33),0) -> 0 | S33: =M33+O33 -> 0 | T33: =N33+P33 -> 0 | W33: =_xlfn.XLOOKUP($A33,'AJE.1 - F25'!$S$12:$S$21,'AJE.1 - F25'!$U$12:$U$21,0,0,1) -> 0 | X33: =ROUND(SUM(S33:W33),0) -> 0 | Y33: =S33+U33 -> 0 | Z33: =T33+V33 -> 0 | AC33: =_xlfn.XLOOKUP($A33,'AJE.1 - F25'!$S$12:$S$21,'AJE.1 - F25'!$U$12:$U$21,0,0,1) -> 0 | AD33: =ROUND(SUM(Y33:AC33),0) -> 0 | AE33: =Y33+AA33 -> 0 | AF33: =Z33+AB33 -> 0 | AI33: =_xlfn.XLOOKUP($A33,'AJE.1 - F25'!$S$12:$S$21,'AJE.1 - F25'!$U$12:$U$21,0,0,1) -> 0 | AJ33: =ROUND(SUM(AE33:AI33),0) -> 0 | AK33: =_xlfn.XLOOKUP($A33,COA!$B:$B,COA!$C:$C,0,0,1) -> Equipment | AL33: =_xlfn.XLOOKUP($A33,COA!$B:$B,COA!$D:$D,0,0,1) -> Equipment | AM33: =_xlfn.XLOOKUP($A33,COA!$B:$B,COA!$E:$E,0,0,1) -> Equipment | AO33: =_xlfn.XLOOKUP(AM33,FS.1!A:A,AM:AM,0,0,1) -> Intercompany
A34: =COA!B30 -> 1811 Office Furniture:Accumulated Depreciation | B34: =_xlfn.XLOOKUP(A34,'TB.1 - F25'!A:A,'TB.1 - F25'!D:D,0,0,1) -> 0 | C34: =_xlfn.XLOOKUP(A34,'TB.1 - F25'!A:A,'TB.1 - F25'!H:H,0,0,1) -> 0 | D34: =_xlfn.XLOOKUP(A34,'AJE.1 - F25'!A:A,'AJE.1 - F25'!F:F,0,0,1) -> 0 | F34: =ROUND(SUM(B34:E34),0) -> 0 | G34: =_xlfn.XLOOKUP($A34,TB.PRO!$A:$A,TB.PRO!F:F,0,0,1) -> 0 | H34: =_xlfn.XLOOKUP($A34,TB.PRO!$A:$A,TB.PRO!G:G,0,0,1) -> 0 | K34: =_xlfn.XLOOKUP($A34,'AJE.1 - F25'!$S$12:$S$21,'AJE.1 - F25'!$U$12:$U$21,0,0,1) -> 0 | L34: =ROUND(SUM(G34:K34),0) -> 0 | M34: =_xlfn.XLOOKUP($A34,TB.PRO!$A:$A,TB.PRO!I:I,0,0,1) -> 0 | N34: =_xlfn.XLOOKUP($A34,TB.PRO!$A:$A,TB.PRO!J:J,0,0,1) -> 0 | Q34: =_xlfn.XLOOKUP($A34,'AJE.1 - F25'!$S$12:$S$21,'AJE.1 - F25'!$U$12:$U$21,0,0,1) -> 0 | R34: =ROUND(SUM(M34:Q34),0) -> 0 | S34: =M34+O34 -> 0 | T34: =N34+P34 -> 0 | W34: =_xlfn.XLOOKUP($A34,'AJE.1 - F25'!$S$12:$S$21,'AJE.1 - F25'!$U$12:$U$21,0,0,1) -> 0 | X34: =ROUND(SUM(S34:W34),0) -> 0 | Y34: =S34+U34 -> 0 | Z34: =T34+V34 -> 0 | AC34: =_xlfn.XLOOKUP($A34,'AJE.1 - F25'!$S$12:$S$21,'AJE.1 - F25'!$U$12:$U$21,0,0,1) -> 0 | AD34: =ROUND(SUM(Y34:AC34),0) -> 0 | AE34: =Y34+AA34 -> 0 | AF34: =Z34+AB34 -> 0 | AI34: =_xlfn.XLOOKUP($A34,'AJE.1 - F25'!$S$12:$S$21,'AJE.1 - F25'!$U$12:$U$21,0,0,1) -> 0 | AJ34: =ROUND(SUM(AE34:AI34),0) -> 0 | AK34: =_xlfn.XLOOKUP($A34,COA!$B:$B,COA!$C:$C,0,0,1) -> Equipment | AL34: =_xlfn.XLOOKUP($A34,COA!$B:$B,COA!$D:$D,0,0,1) -> Equipment | AM34: =_xlfn.XLOOKUP($A34,COA!$B:$B,COA!$E:$E,0,0,1) -> Equipment | AO34: =AM34 -> Equipment
A35: =COA!B31 -> 1900 Shop Equipment | B35: =_xlfn.XLOOKUP(A35,'TB.1 - F25'!A:A,'TB.1 - F25'!D:D,0,0,1) -> 0 | C35: =_xlfn.XLOOKUP(A35,'TB.1 - F25'!A:A,'TB.1 - F25'!H:H,0,0,1) -> 6288.98 | D35: =_xlfn.XLOOKUP(A35,'AJE.1 - F25'!A:A,'AJE.1 - F25'!F:F,0,0,1) -> 0 | F35: =ROUND(SUM(B35:E35),0) -> 6289 | G35: =_xlfn.XLOOKUP($A35,TB.PRO!$A:$A,TB.PRO!F:F,0,0,1) -> 0 | H35: =_xlfn.XLOOKUP($A35,TB.PRO!$A:$A,TB.PRO!G:G,0,0,1) -> 6288.98 | K35: =_xlfn.XLOOKUP($A35,'AJE.1 - F25'!$S$12:$S$21,'AJE.1 - F25'!$U$12:$U$21,0,0,1) -> 0 | L35: =ROUND(SUM(G35:K35),0) -> 6289 | M35: =_xlfn.XLOOKUP($A35,TB.PRO!$A:$A,TB.PRO!I:I,0,0,1) -> 0 | N35: =_xlfn.XLOOKUP($A35,TB.PRO!$A:$A,TB.PRO!J:J,0,0,1) -> 6288.98 | Q35: =_xlfn.XLOOKUP($A35,'AJE.1 - F25'!$S$12:$S$21,'AJE.1 - F25'!$U$12:$U$21,0,0,1) -> 0 | R35: =ROUND(SUM(M35:Q35),0) -> 6289 | S35: =M35+O35 -> 0 | T35: =N35+P35 -> 6288.98 | W35: =_xlfn.XLOOKUP($A35,'AJE.1 - F25'!$S$12:$S$21,'AJE.1 - F25'!$U$12:$U$21,0,0,1) -> 0 | X35: =ROUND(SUM(S35:W35),0) -> 6289 | Y35: =S35+U35 -> 0 | Z35: =T35+V35 -> 6288.98 | AC35: =_xlfn.XLOOKUP($A35,'AJE.1 - F25'!$S$12:$S$21,'AJE.1 - F25'!$U$12:$U$21,0,0,1) -> 0 | AD35: =ROUND(SUM(Y35:AC35),0) -> 6289 | AE35: =Y35+AA35 -> 0 | AF35: =Z35+AB35 -> 6288.98 | AI35: =_xlfn.XLOOKUP($A35,'AJE.1 - F25'!$S$12:$S$21,'AJE.1 - F25'!$U$12:$U$21,0,0,1) -> 0 | AJ35: =ROUND(SUM(AE35:AI35),0) -> 6289 | AK35: =_xlfn.XLOOKUP($A35,COA!$B:$B,COA!$C:$C,0,0,1) -> Equipment | AL35: =_xlfn.XLOOKUP($A35,COA!$B:$B,COA!$D:$D,0,0,1) -> Equipment | AM35: =_xlfn.XLOOKUP($A35,COA!$B:$B,COA!$E:$E,0,0,1) -> Equipment | AO35: =AM35 -> Equipment
