Workbook

Sheet Summary
A1: Hallor Group Inc. — Pro Forma Cap Table
A2: Pre-listing snapshot · As of 2026-04-27
A4: Source data
A5: Existing CSR data | B5: Q1 2024 CSR (Shareholders + Warrant Holders tabs)
A6: Categorization basis | B6: Issuance Code in CSR: PPA + INCORP → Founders; PP@$0.05 → Seed; PP@$0.10 + SFD + Finders → Investors
A7: New raise terms | B7: Approximately $2,000,000 at $0.14 per share
A9: Top-line totals
A10: Metric | B10: Shares / $
A11: Founders shares | B11: =Founders!E8 -> 12000001
A12: Seed shares | B12: =Seed!E8 -> 2000000
A13: Investors shares | B13: =Investors!E182 -> 17912500
A14: Sub-total: existing issued shares | B14: =B11+B12+B13 -> 31912501
A15: Warrants converted (added) | B15: ='Warrants Converted'!E58 -> 2687500
A16: Sub-total: post-conversion shares | B16: =B14+B15 -> 34600001
A17: New raise shares | B17: =Inputs!B16 -> 14285714
A18: PRO FORMA FULLY DILUTED | B18: =B16+B17 -> 48885715
A20: Consideration — Seed (PP @ $0.05) | B20: =Seed!F8 -> 100000
A21: Consideration — Investors (PP+SFD+Finders) | B21: =Investors!F182 -> 2151250
A22: Consideration — Special Warrants | B22: ='Warrants Converted'!F58 -> 308750
A23: Consideration — New Raise | B23: =Inputs!B17 -> 2000000
A24: TOTAL CONSIDERATION RECORDED | B24: =B20+B21+B22+B23 -> 4560000
A25: Note: 'Consideration' includes both cash and deemed value. Of the Investors block, $1,258,080 was non-cash (SFD shares-for-debt) and the PPA $6M was a deemed acquisition price.
A27: Valuation snapshot @ $0.14
A28: Pre-money shares (post-warrant conversion) | B28: =B16 -> 34600001
A29: Pre-money valuation | B29: =B16*Inputs!B15 -> 4844000.1
A30: Post-money shares | B30: =B18 -> 48885715
A31: Post-money valuation | B31: =B18*Inputs!B15 -> 6844000.1
A32: New money % | B32: =Inputs!B16/B18 -> 0.29222676
A33: Existing % | B33: =B16/B18 -> 0.70777324

Sheet Inputs
A1: Hallor Group Inc. — Cap Table Inputs
A2: All assumptions in blue. Change here, the model recalculates.
A4: Assumption | B4: Value | C4: Notes
A5: As-of date | B5: 2026-04-27 | C5: Cap table snapshot date
A6: Existing issued & outstanding | B6: 31912501 | C6: Per CSR Q1 2024 (Total)
A7: Founders shares (PPA + INCORP) | B7: 12000001 | C7: Halston 6M + Taylor 6M + Karim 1
A8: Seed shares (PP @ $0.05) | B8: 2000000 | C8: April 2021 — 3 holders, $100K
A9: Investor shares (PP $0.10/SFD) | B9: 17912500 | C9: PP @ $0.10 + SFD + Finders
A10: Warrants outstanding (2022 SW) | B10: 2587500 | C10: $0.10, 1:1 conversion, no add'l cash
A11: Warrants outstanding (2023 SW) | B11: 100000 | C11: $0.50, 1:1 conversion, no add'l cash
A12: Total warrants to convert | B12: 2687500 | C12: Sum of 2022 + 2023 SW
A14: NEW RAISE — target gross proceeds ($) | B14: 2000000 | C14: Bill: 'approximately $2M'
A15: NEW RAISE — issue price per share ($) | B15: 0.14 | C15: Bill: '$0.14'
A16: NEW RAISE — shares to issue (calc) | B16: =ROUND(B14/B15,0) -> 14285714 | C16: Calc: proceeds ÷ price
A17: NEW RAISE — actual gross proceeds (calc) | B17: =B16*B15 -> 2000000 | C17: Calc: shares × price

Sheet Founders
A1: Founders
A2: PPA (acquisition) + INCORP — original control block
A4: # | B4: Holder | C4: Code | D4: Issue Price | E4: Shares | F4: Consideration ($) | G4: % of Class
A5: 1 | B5: ASHIK KARIM | C5: INCORP | D5: 1 | E5: 1 | F5: =D5*E5 -> 1 | G5: =E5/$E$8 -> 8.3333326e-08
A6: 2 | B6: Keith Halston | C6: PPA | D6: 0.5 | E6: 6000000 | F6: =D6*E6 -> 3000000 | G6: =E6/$E$8 -> 0.49999996
A7: 3 | B7: James Taylor | C7: PPA | D7: 0.5 | E7: 6000000 | F7: =D7*E7 -> 3000000 | G7: =E7/$E$8 -> 0.49999996
B8: TOTAL | E8: =SUM(E5:E7) -> 12000001 | F8: =SUM(F5:F7) -> 6000001 | G8: =SUM(G5:G7) -> 1
A10: Notes:
A11: PPA = Acquisition (Hallor Industries roll-in, July 2023). INCORP = Single incorporation share. CVan Finders Fee classified under Investors.

Sheet Seed
A1: Seed Round
A2: Private placement at $0.05 — April 2021
A4: # | B4: Holder | C4: Code | D4: Issue Price | E4: Shares | F4: Consideration ($) | G4: % of Class
A5: 1 | B5: ASHIK KARIM | C5: PP | D5: 0.05 | E5: 1400000 | F5: =D5*E5 -> 70000 | G5: =E5/$E$8 -> 0.7
A6: 2 | B6: GURJIT AUJLA | C6: PP | D6: 0.05 | E6: 400000 | F6: =D6*E6 -> 20000 | G6: =E6/$E$8 -> 0.2
A7: 3 | B7: ROPEBAKE MANAGEMENT CORP. | C7: PP | D7: 0.05 | E7: 200000 | F7: =D7*E7 -> 10000 | G7: =E7/$E$8 -> 0.1
B8: TOTAL | E8: =SUM(E5:E7) -> 2000000 | F8: =SUM(F5:F7) -> 100000 | G8: =SUM(G5:G7) -> 1
A10: Notes:
A11: All three subscribers paid cash. Foundational round at $0.05 issue price.

Sheet Investors
A1: Investors
A2: Subsequent PPs at $0.10 + Shares for Debt + Acquisition Finders Fee
A4: # | B4: Holder | C4: Code | D4: Issue Price | E4: Shares | F4: Consideration ($) | G4: % of Class
A5: 1 | B5: PETER DAVIDSON | C5: PP | D5: 0.1 | E5: 25000 | F5: =D5*E5 -> 2500 | G5: =E5/$E$182 -> 0.0013956734
A6: 2 | B6: GEORGE JOHNSTONE | C6: PP | D6: 0.1 | E6: 30000 | F6: =D6*E6 -> 3000 | G6: =E6/$E$182 -> 0.0016748081
A7: 3 | B7: JOHN H.C. PINSENT | C7: PP | D7: 0.1 | E7: 50000 | F7: =D7*E7 -> 5000 | G7: =E7/$E$182 -> 0.0027913468
A8: 4 | B8: ROB PARKHILL | C8: PP | D8: 0.1 | E8: 5000 | F8: =D8*E8 -> 500 | G8: =E8/$E$182 -> 0.00027913468
A9: 5 | B9: JOANNE JACKSON | C9: PP | D9: 0.1 | E9: 4000 | F9: =D9*E9 -> 400 | G9: =E9/$E$182 -> 0.00022330775
A10: 6 | B10: LEED JONES GABLE | C10: PP | D10: 0.1 | E10: 4000 | F10: =D10*E10 -> 400 | G10: =E10/$E$182 -> 0.00022330775
A11: 7 | B11: CARLA THOMAS | C11: PP | D11: 0.1 | E11: 4000 | F11: =D11*E11 -> 400 | G11: =E11/$E$182 -> 0.00022330775
A12: 8 | B12: VISIO VENTURES INC. | C12: PP | D12: 0.1 | E12: 100000 | F12: =D12*E12 -> 10000 | G12: =E12/$E$182 -> 0.0055826936
A13: 9 | B13: BOB TITUS | C13: PP | D13: 0.1 | E13: 70000 | F13: =D13*E13 -> 7000 | G13: =E13/$E$182 -> 0.0039078856
A14: 10 | B14: ERNIE LALONDE | C14: PP | D14: 0.1 | E14: 4000 | F14: =D14*E14 -> 400 | G14: =E14/$E$182 -> 0.00022330775
A15: 11 | B15: PETER GORGENYI | C15: PP | D15: 0.1 | E15: 4000 | F15: =D15*E15 -> 400 | G15: =E15/$E$182 -> 0.00022330775
A16: 12 | B16: GORDON LEE | C16: PP | D16: 0.1 | E16: 4000 | F16: =D16*E16 -> 400 | G16: =E16/$E$182 -> 0.00022330775
... A181: 177 | B181: CVan Finders Fee | C181: PPA | D181: 0.5 | E181: 900000 | F181: =D181*E181 -> 450000 | G181: =E181/$E$182 -> 0.050244243
B182: TOTAL | E182: =SUM(E5:E181) -> 17912500 | F182: =SUM(F5:F181) -> 2151250 | G182: =SUM(G5:G181) -> 1
A184: Notes:
A185: Includes 167 PP @ $0.10 holders, 9 SFD holders (services rendered), and CVan Finders Fee from PPA.

Sheet Warrants Converted
A1: Special Warrants — Converted to Common
A2: All 53 SW holders convert 1:1 (no additional consideration on exercise)
A4: # | B4: Holder | C4: Year | D4: Subscription Price | E4: Shares Issued | F4: Original $ Subscribed
A5: 1 | B5: SUSAN LYN KNEIDER | C5: 2022 | D5: 0.1 | E5: 100000 | F5: =D5*E5 -> 10000
A6: 2 | B6: ROPE BAKE MANAGEMENT CORP. | C6: 2022 | D6: 0.1 | E6: 100000 | F6: =D6*E6 -> 10000
A7: 3 | B7: ABHINAV KANTI | C7: 2022 | D7: 0.1 | E7: 10000 | F7: =D7*E7 -> 1000
A8: 4 | B8: ALAN MCGREGOR | C8: 2022 | D8: 0.1 | E8: 20000 | F8: =D8*E8 -> 2000
A9: 5 | B9: ALAN MICHAEL TAYLOR | C9: 2022 | D9: 0.1 | E9: 40000 | F9: =D9*E9 -> 4000
A10: 6 | B10: BRANDON FARR | C10: 2022 | D10: 0.1 | E10: 50000 | F10: =D10*E10 -> 5000
A11: 7 | B11: BRANDON DALE HALSTON | C11: 2022 | D11: 0.1 | E11: 100000 | F11: =D11*E11 -> 10000
A12: 8 | B12: BRETT HALSTON | C12: 2022 | D12: 0.1 | E12: 100000 | F12: =D12*E12 -> 10000
A13: 9 | B13: BRIAN OLIVEIRA | C13: 2022 | D13: 0.1 | E13: 100000 | F13: =D13*E13 -> 10000
A14: 10 | B14: CHASE TAYLOR | C14: 2022 | D14: 0.1 | E14: 25000 | F14: =D14*E14 -> 2500
A15: 11 | B15: CHERYL ANN BOTT | C15: 2022 | D15: 0.1 | E15: 27500 | F15: =D15*E15 -> 2750
A16: 12 | B16: CHRISTINE J. HALSTON | C16: 2022 | D16: 0.1 | E16: 50000 | F16: =D16*E16 -> 5000
... A57: 53 | B57: TAMARA MACPHERSON | C57: 2023 | D57: 0.5 | E57: 10000 | F57: =D57*E57 -> 5000
B58: TOTAL | E58: =SUM(E5:E57) -> 2687500 | F58: =SUM(F5:F57) -> 308750
A60: Note: Special warrants entitle holders to 1 common share on exercise for no additional consideration; subscription price was paid at issue.

Sheet New Raise
A1: New Equity Raise — $2M @ $0.14
A2: Pricing & sizing pulled from Inputs!B14:B17
A4: Round summary
A5: Target gross proceeds ($) | B5: =Inputs!B14 -> 2000000
A6: Issue price per share ($) | B6: =Inputs!B15 -> 0.14
A7: Shares to be issued | B7: =Inputs!B16 -> 14285714
A8: Actual gross proceeds ($) | B8: =Inputs!B17 -> 2000000
A9: Rounding gap ($) | B9: =Inputs!B17-Inputs!B14 -> -0.04
A11: Allocation to new investors (placeholder rows — fill in once allocations are confirmed)
A12: # | B12: New Investor (TBD) | C12: Subscription ($) | D12: Shares (= sub÷price) | E12: % of round | F12: Notes
A13: 1 | B13: [TBD] | C13: 0 | D13: =IF(Inputs!$B$15>0,ROUND(C13/Inputs!$B$15,0),0) -> 0 | E13: =IF($B$9>0,D13/$B$9,0) -> 0
A14: 2 | B14: [TBD] | C14: 0 | D14: =IF(Inputs!$B$15>0,ROUND(C14/Inputs!$B$15,0),0) -> 0 | E14: =IF($B$9>0,D14/$B$9,0) -> 0
A15: 3 | B15: [TBD] | C15: 0 | D15: =IF(Inputs!$B$15>0,ROUND(C15/Inputs!$B$15,0),0) -> 0 | E15: =IF($B$9>0,D15/$B$9,0) -> 0
A16: 4 | B16: [TBD] | C16: 0 | D16: =IF(Inputs!$B$15>0,ROUND(C16/Inputs!$B$15,0),0) -> 0 | E16: =IF($B$9>0,D16/$B$9,0) -> 0
A17: 5 | B17: [TBD] | C17: 0 | D17: =IF(Inputs!$B$15>0,ROUND(C17/Inputs!$B$15,0),0) -> 0 | E17: =IF($B$9>0,D17/$B$9,0) -> 0
A18: 6 | B18: [TBD] | C18: 0 | D18: =IF(Inputs!$B$15>0,ROUND(C18/Inputs!$B$15,0),0) -> 0 | E18: =IF($B$9>0,D18/$B$9,0) -> 0
B19: Allocated | C19: =SUM(C13:C18) -> 0 | D19: =SUM(D13:D18) -> 0 | E19: =SUM(E13:E18) -> 0
B20: Unallocated | C20: =B7-C19 -> 14285714 | D20: =B9-D19 -> -0.04

Sheet Pro Forma
A1: Pro Forma Cap Table — Post-Conversion + New Raise
A2: Each column shows the share count at that stage. % columns recalc against the stage total.
A4: Class | B4: Pre-Raise Shares | C4: % (Pre) | D4: + New Raise | E4: Pro Forma Shares | F4: % (Post) | G4: Consideration ($)
A5: Founders (PPA + INCORP) | B5: =Founders!E8 -> 12000001 | C5: =IF($B$10>0,B5/$B$10,0) -> 0.34682083 | D5: 0 | E5: =B5+D5 -> 12000001 | F5: =IF($E$10>0,E5/$E$10,0) -> 0.2454705 | G5: =Founders!F8 -> 6000001
A6: Seed (PP @ $0.05) | B6: =Seed!E8 -> 2000000 | C6: =IF($B$10>0,B6/$B$10,0) -> 0.057803467 | D6: 0 | E6: =B6+D6 -> 2000000 | F6: =IF($E$10>0,E6/$E$10,0) -> 0.040911747 | G6: =Seed!F8 -> 100000
A7: Investors (PP $0.10 / SFD) | B7: =Investors!E182 -> 17912500 | C7: =IF($B$10>0,B7/$B$10,0) -> 0.5177023 | D7: 0 | E7: =B7+D7 -> 17912500 | F7: =IF($E$10>0,E7/$E$10,0) -> 0.36641583 | G7: =Investors!F182 -> 2151250
A8: Warrants converted | B8: ='Warrants Converted'!E58 -> 2687500 | C8: =IF($B$10>0,B8/$B$10,0) -> 0.077673408 | D8: 0 | E8: =B8+D8 -> 2687500 | F8: =IF($E$10>0,E8/$E$10,0) -> 0.05497516 | G8: ='Warrants Converted'!F58 -> 308750
A9: New Raise ($2M @ $0.14) | B9: 0 | C9: =IF($B$10>0,B9/$B$10,0) -> 0 | D9: =Inputs!B16 -> 14285714 | E9: =B9+D9 -> 14285714 | F9: =IF($E$10>0,E9/$E$10,0) -> 0.29222676 | G9: =Inputs!B17 -> 2000000
A10: TOTAL FULLY DILUTED | B10: =SUM(B5:B9) -> 34600001 | C10: =SUM(C5:C9) -> 1 | D10: =SUM(D5:D9) -> 14285714 | E10: =SUM(E5:E9) -> 48885715 | F10: =SUM(F5:F9) -> 1 | G10: =SUM(G5:G9) -> 10560001
A13: Implied Valuation Snapshot
A14: Pre-money shares (post warrant conversion) | B14: =B10 -> 34600001
A15: New raise issue price ($) | B15: =Inputs!B15 -> 0.14
A16: Pre-money valuation ($) | B16: =B10*Inputs!B15 -> 4844000.1
A17: New money in ($) | B17: =Inputs!B17 -> 2000000
A18: Post-money valuation ($) | B18: =B10*Inputs!B15+Inputs!B17 -> 6844000.1
A19: New investors % of post | B19: =Inputs!B16/E10 -> 0.29222676
A20: Existing holders % of post (dilution) | B20: =B10/E10 -> 0.70777324
